{"bbox":{"south":24.634375,"north":24.85625,"west":121.8375,"east":121.96875},"pois":[{"id":"node-2278520716","lat":24.841557,"lon":121.953191,"name":"龜山島山","decorType":"mountain"},{"id":"node-2482639596","lat":24.837,"lon":121.962674,"name":"龜山頭山","decorType":"mountain"},{"id":"node-7712858269","lat":24.653744,"lon":121.838242,"name":"鬥陣來七桃體驗館","decorType":"restaurant"},{"id":"way-1053560596","lat":24.662567,"lon":121.837954,"name":"未命名森林","decorType":"forest"},{"id":"way-1053560597","lat":24.654468,"lon":121.839755,"name":"未命名森林","decorType":"forest"},{"id":"way-1053586251","lat":24.650125,"lon":121.841257,"name":"未命名森林","decorType":"forest"},{"id":"way-1053586252","lat":24.644499,"lon":121.842868,"name":"未命名森林","decorType":"forest"},{"id":"way-1053586253","lat":24.638464,"lon":121.843852,"name":"頂寮生態公園","decorType":"park"},{"id":"way-1115207437","lat":24.651044,"lon":121.838741,"name":"未命名水邊","decorType":"waterside"},{"id":"way-1115207438","lat":24.651521,"lon":121.838489,"name":"利工體育館","decorType":"stadium"},{"id":"way-129614855","lat":24.84341,"lon":121.952186,"name":"未命名森林","decorType":"forest"},{"id":"way-129614865","lat":24.849425,"lon":121.947794,"name":"未命名海邊","decorType":"beach"},{"id":"way-129614869","lat":24.84609,"lon":121.958127,"name":"龜首潭","decorType":"waterside"},{"id":"way-129614870","lat":24.843311,"lon":121.940922,"name":"未命名海邊","decorType":"beach"},{"id":"way-129614874","lat":24.849078,"lon":121.954628,"name":"未命名山丘","decorType":"mountain"},{"id":"way-129614879","lat":24.841031,"lon":121.9421,"name":"龜尾潭","decorType":"waterside"},{"id":"way-129614885","lat":24.843794,"lon":121.959442,"name":"未命名海邊","decorType":"beach"},{"id":"way-1298841403","lat":24.84194,"lon":121.941678,"name":"未命名橋樑","decorType":"bridge"},{"id":"way-142441885","lat":24.672198,"lon":121.842775,"name":"未命名水邊","decorType":"waterside"},{"id":"way-184592462","lat":24.842117,"lon":121.94272,"name":"未命名美術館","decorType":"art_gallery"},{"id":"way-184592467","lat":24.842215,"lon":121.943253,"name":"普陀巖","decorType":"shrine"},{"id":"way-184592468","lat":24.841485,"lon":121.943754,"name":"環湖步道","decorType":"bridge"},{"id":"way-192030573","lat":24.840507,"lon":121.941987,"name":"環湖步道","decorType":"bridge"},{"id":"way-210777752","lat":24.644605,"lon":121.845523,"name":"未命名海邊","decorType":"beach"},{"id":"way-210777753","lat":24.682821,"lon":121.838252,"name":"未命名海邊","decorType":"beach"},{"id":"way-323598216","lat":24.638163,"lon":121.840957,"name":"利澤排水","decorType":"waterside"},{"id":"way-402825718","lat":24.638634,"lon":121.844181,"name":"頂寮生態池","decorType":"waterside"},{"id":"way-402825719","lat":24.640116,"lon":121.843919,"name":"未命名水邊","decorType":"waterside"},{"id":"way-403776726","lat":24.637383,"lon":121.845249,"name":"未命名森林","decorType":"forest"},{"id":"way-444936617","lat":24.635126,"lon":121.842715,"name":"頂強路","decorType":"bridge"},{"id":"way-528615902","lat":24.839576,"lon":121.953136,"name":"未命名山丘","decorType":"mountain"},{"id":"way-822299708","lat":24.836962,"lon":121.946793,"name":"未命名海邊","decorType":"beach"}]}