{"bbox":{"south":22.045833333333334,"north":22.34166666666667,"west":120.35,"east":120.525},"pois":[{"id":"node-2406748530","lat":22.33452,"lon":120.3744629,"name":"大福渡船碼頭遊客中心","decorType":"station","decorName":"車站","decorIcon":"🚉"},{"id":"node-4362231890","lat":22.3353602,"lon":120.3714571,"name":"洪媽媽早餐店","decorType":"restaurant","decorName":"餐廳","decorIcon":"🍽️"},{"id":"node-4362231891","lat":22.3354727,"lon":120.3720795,"name":"大福羊肉店","decorType":"restaurant","decorName":"餐廳","decorIcon":"🍽️"},{"id":"node-4362727891","lat":22.3387888,"lon":120.3699421,"name":"7-Eleven","decorType":"convenience-store","decorName":"便利商店","decorIcon":"🏪"},{"id":"node-6320091957","lat":22.3390923,"lon":120.3702677,"name":"龍鑽烘炸手工麻花捲","decorType":"sweetshop","decorName":"甜點店","decorIcon":"🍩"},{"id":"node-7654550085","lat":22.3351043,"lon":120.3715534,"name":"小小島","decorType":"cafe","decorName":"咖啡廳","decorIcon":"☕"},{"id":"node-10777516609","lat":22.3386725,"lon":120.3700577,"name":"厚呷早餐店","decorType":"restaurant","decorName":"餐廳","decorIcon":"🍽️"},{"id":"node-10777518724","lat":22.3393157,"lon":120.3701592,"name":"未命名服飾店","decorType":"clothing-store","decorName":"服飾店","decorIcon":"👕"},{"id":"node-10779316337","lat":22.3409961,"lon":120.3714004,"name":"Good Thai","decorType":"restaurant","decorName":"餐廳","decorIcon":"🍽️"},{"id":"node-11278570431","lat":22.3400208,"lon":120.3672026,"name":"Unknown Café","decorType":"cafe","decorName":"咖啡廳","decorIcon":"☕"},{"id":"node-11278751372","lat":22.3389817,"lon":120.3624411,"name":"Wild Boar","decorType":"restaurant","decorName":"餐廳","decorIcon":"🍽️"},{"id":"node-12189801838","lat":22.3292359,"lon":120.3552053,"name":"海角8號","decorType":"restaurant","decorName":"餐廳","decorIcon":"🍽️"},{"id":"node-13251246902","lat":22.338512,"lon":120.37002,"name":"好窄食堂","decorType":"restaurant","decorName":"餐廳","decorIcon":"🍽️"},{"id":"way-224315185-1/22032033133010120","lat":22.33855949028122,"lon":120.37633679289479,"name":"未命名森林","decorType":"forest","decorName":"森林","decorIcon":"🌲"},{"id":"way-224315185-1/22032033133010113","lat":22.33841102514759,"lon":120.37705727487423,"name":"未命名森林","decorType":"forest","decorName":"森林","decorIcon":"🌲"},{"id":"way-224315185-1/22032033133010131","lat":22.339229943287194,"lon":120.37633679289479,"name":"未命名森林","decorType":"forest","decorName":"森林","decorIcon":"🌲"},{"id":"way-224315185-1/22032033133010102","lat":22.339081474639652,"lon":120.37705727487423,"name":"未命名森林","decorType":"forest","decorName":"森林","decorIcon":"🌲"},{"id":"way-224315185-1/22032033133010103","lat":22.338933003315468,"lon":120.37777775285184,"name":"未命名森林","decorType":"forest","decorName":"森林","decorIcon":"🌲"},{"id":"way-224315185-1/22032033133010101","lat":22.33975192424814,"lon":120.37705727487423,"name":"未命名森林","decorType":"forest","decorName":"森林","decorIcon":"🌲"},{"id":"way-224315185-1/22032033133010100","lat":22.339603449410045,"lon":120.37777775285184,"name":"未命名森林","decorType":"forest","decorName":"森林","decorIcon":"🌲"},{"id":"way-224315185-1/22032033133003011","lat":22.33945497189535,"lon":120.37849822682733,"name":"未命名森林","decorType":"forest","decorName":"森林","decorIcon":"🌲"},{"id":"way-224315185-1/22032033133010130","lat":22.339378409257982,"lon":120.37561630691391,"name":"未命名森林","decorType":"forest","decorName":"森林","decorIcon":"🌲"},{"id":"way-224315185-1/22032033133010132","lat":22.339900396409515,"lon":120.37633679289479,"name":"未命名森林","decorType":"forest","decorName":"森林","decorIcon":"🌲"},{"id":"way-224315185-1/22032033133003012","lat":22.33930649170418,"lon":120.37921869680054,"name":"未命名森林","decorType":"forest","decorName":"森林","decorIcon":"🌲"},{"id":"way-224315185-1/22032033133010203","lat":22.33952687255189,"lon":120.37489581693183,"name":"未命名森林","decorType":"forest","decorName":"森林","decorIcon":"🌲"},{"id":"way-224315185-1/22032033133010133","lat":22.340048865894055,"lon":120.37561630691391,"name":"未命名森林","decorType":"forest","decorName":"森林","decorIcon":"🌲"},{"id":"way-224315185-1/22032033133003322","lat":22.340125414592244,"lon":120.37849822682733,"name":"未命名森林","decorType":"forest","decorName":"森林","decorIcon":"🌲"},{"id":"way-224315185-1/22032033133003321","lat":22.339976930887072,"lon":120.37921869680054,"name":"未命名森林","decorType":"forest","decorName":"森林","decorIcon":"🌲"},{"id":"way-224315185-1/22032033133010033","lat":22.340273895620854,"lon":120.37777775285184,"name":"未命名森林","decorType":"forest","decorName":"森林","decorIcon":"🌲"},{"id":"way-224315185-1/22032033133003312","lat":22.33982844450547,"lon":120.37993916277105,"name":"未命名森林","decorType":"forest","decorName":"森林","decorIcon":"🌲"},{"id":"way-224315185-1/22032033133010023","lat":22.340570849647914,"lon":120.37633679289479,"name":"未命名森林","decorType":"forest","decorName":"森林","decorIcon":"🌲"},{"id":"way-224315185-1/22032033133010030","lat":22.340422373972782,"lon":120.37705727487423,"name":"未命名森林","decorType":"forest","decorName":"森林","decorIcon":"🌲"},{"id":"way-224315185-1/22032033133010200","lat":22.34019733270163,"lon":120.37489581693183,"name":"未命名森林","decorType":"forest","decorName":"森林","decorIcon":"🌲"},{"id":"way-224315185-1/22032033133010022","lat":22.340719322646123,"lon":120.37561630691391,"name":"未命名森林","decorType":"forest","decorName":"森林","decorIcon":"🌲"},{"id":"way-224315185-1/22032033133003320","lat":22.340647370186083,"lon":120.37921869680054,"name":"未命名森林","decorType":"forest","decorName":"森林","decorIcon":"🌲"},{"id":"way-224315185-1/22032033133010311","lat":22.340867792967295,"lon":120.37489581693183,"name":"未命名森林","decorType":"forest","decorName":"森林","decorIcon":"🌲"},{"id":"way-224315185-1/22032033133010032","lat":22.340944341947615,"lon":120.37777775285184,"name":"未命名森林","decorType":"forest","decorName":"森林","decorIcon":"🌲"},{"id":"way-224315185-1/22032033133003323","lat":22.34079585740517,"lon":120.37849822682733,"name":"未命名森林","decorType":"forest","decorName":"森林","decorIcon":"🌲"},{"id":"way-224315185-1/22032033133010031","lat":22.341092823813298,"lon":120.37705727487423,"name":"未命名森林","decorType":"forest","decorName":"森林","decorIcon":"🌲"},{"id":"way-224315185-1/22032033133003303","lat":22.34102082010541,"lon":120.38065962473866,"name":"未命名森林","decorType":"forest","decorName":"森林","decorIcon":"🌲"},{"id":"way-224315185-1/22032033133003231","lat":22.34072381990447,"lon":120.38210053666387,"name":"未命名森林","decorType":"forest","decorName":"森林","decorIcon":"🌲"},{"id":"way-224315185-1/22032033133003220","lat":22.340575315789767,"lon":120.38282098662097,"name":"未命名森林","decorType":"forest","decorName":"森林","decorIcon":"🌲"},{"id":"way-224315185-1/22032033133010020","lat":22.341241303002104,"lon":120.37633679289479,"name":"未命名森林","decorType":"forest","decorName":"森林","decorIcon":"🌲"},{"id":"way-224315185-1/22032033133003331","lat":22.341317809600923,"lon":120.37921869680054,"name":"未命名森林","decorType":"forest","decorName":"森林","decorIcon":"🌲"},{"id":"way-224315185-1/22032033133003302","lat":22.341169316191408,"lon":120.37993916277105,"name":"未命名森林","decorType":"forest","decorName":"森林","decorIcon":"🌲"},{"id":"way-224315185-1/22032033133003232","lat":22.340872321343056,"lon":120.381380082703,"name":"未命名森林","decorType":"forest","decorName":"森林","decorIcon":"🌲"},{"id":"way-224315185-1/22032033133003223","lat":22.34124573775017,"lon":120.38282098662097,"name":"未命名森林","decorType":"forest","decorName":"森林","decorIcon":"🌲"},{"id":"way-224315185-1/22032033133003222","lat":22.341097227445236,"lon":120.38354143257402,"name":"未命名森林","decorType":"forest","decorName":"森林","decorIcon":"🌲"},{"id":"way-224315185-1/22032033133010312","lat":22.341538253348578,"lon":120.37489581693183,"name":"未命名森林","decorType":"forest","decorName":"森林","decorIcon":"🌲"},{"id":"way-224315185-1/22032033133010021","lat":22.3413897795139,"lon":120.37561630691391,"name":"未命名森林","decorType":"forest","decorName":"森林","decorIcon":"🌲"},{"id":"way-224315185-1/22032033133003330","lat":22.341466300333845,"lon":120.37849822682733,"name":"未命名森林","decorType":"forest","decorName":"森林","decorIcon":"🌲"},{"id":"way-224315185-1/22032033133003233","lat":22.341542750331705,"lon":120.381380082703,"name":"未命名森林","decorType":"forest","decorName":"森林","decorIcon":"🌲"},{"id":"way-224315185-1/22032033133003230","lat":22.341394245379036,"lon":120.38210053666387,"name":"未命名森林","decorType":"forest","decorName":"森林","decorIcon":"🌲"},{"id":"way-224315185-1/22032033133010001","lat":22.341614788390046,"lon":120.37777775285184,"name":"未命名森林","decorType":"forest","decorName":"森林","decorIcon":"🌲"},{"id":"way-224315185-1/22032033022333000","lat":22.34161912951202,"lon":120.38426187452262,"name":"未命名森林","decorType":"forest","decorName":"森林","decorIcon":"🌲"},{"id":"way-224315185-1/22032033022333003","lat":22.341470610340973,"lon":120.3849823124666,"name":"未命名森林","decorType":"forest","decorName":"森林","decorIcon":"🌲"},{"id":"way-224315185-1/22032033133010121","lat":22.337889037391875,"lon":120.37633679289479,"name":"未命名森林","decorType":"forest","decorName":"森林","decorIcon":"🌲"},{"id":"way-224315185-1/22032033133003313","lat":22.340498880290486,"lon":120.37993916277105,"name":"未命名森林","decorType":"forest","decorName":"森林","decorIcon":"🌲"},{"id":"way-227521640-1/22032033133311020","lat":22.325957897084397,"lon":120.36264687532645,"name":"未命名森林","decorType":"forest","decorName":"森林","decorIcon":"🌲"},{"id":"way-227521640-1/22032033133311023","lat":22.325809563635122,"lon":120.36336743328553,"name":"未命名森林","decorType":"forest","decorName":"森林","decorIcon":"🌲"},{"id":"way-227521640-1/22032033133311021","lat":22.326628414121195,"lon":120.36264687532645,"name":"未命名森林","decorType":"forest","decorName":"森林","decorIcon":"🌲"},{"id":"way-227521640-1/22032033133311022","lat":22.326480077157697,"lon":120.36336743328553,"name":"未命名森林","decorType":"forest","decorName":"森林","decorIcon":"🌲"},{"id":"way-227521640-1/22032033133311133","lat":22.326331737517123,"lon":120.36408798724824,"name":"未命名森林","decorType":"forest","decorName":"森林","decorIcon":"🌲"},{"id":"way-227521640-1/22032033133311200","lat":22.327002247646817,"lon":120.36408798724824,"name":"未命名森林","decorType":"forest","decorName":"森林","decorIcon":"🌲"},{"id":"way-227521640-1/22032033133022122","lat":22.326408848258538,"lon":120.36697016312985,"name":"未命名森林","decorType":"forest","decorName":"森林","decorIcon":"🌲"},{"id":"way-227521640-1/22032033133311311","lat":22.327150590801615,"lon":120.36336743328553,"name":"未命名森林","decorType":"forest","decorName":"森林","decorIcon":"🌲"},{"id":"way-227521640-1/22032033133311212","lat":22.327227701828637,"lon":120.36624962515543,"name":"未命名森林","decorType":"forest","decorName":"森林","decorIcon":"🌲"},{"id":"way-227521640-1/22032033133022121","lat":22.327079344451978,"lon":120.36697016312985,"name":"未命名森林","decorType":"forest","decorName":"森林","decorIcon":"🌲"},{"id":"way-227521640-1/22032033133311203","lat":22.326853901814985,"lon":120.36480853721434,"name":"未命名森林","decorType":"forest","decorName":"森林","decorIcon":"🌲"},{"id":"way-227521640-1/22032033133311202","lat":22.32752440855159,"lon":120.36480853721434,"name":"未命名森林","decorType":"forest","decorName":"森林","decorIcon":"🌲"},{"id":"way-227521640-1/22032033133311213","lat":22.327376056528554,"lon":120.3655290831835,"name":"未命名森林","decorType":"forest","decorName":"森林","decorIcon":"🌲"},{"id":"way-227521640-1/22032033133022120","lat":22.326930984398697,"lon":120.36769069710653,"name":"未命名森林","decorType":"forest","decorName":"森林","decorIcon":"🌲"},{"id":"way-227521640-1/22032033133311310","lat":22.327821104566585,"lon":120.36336743328553,"name":"未命名森林","decorType":"forest","decorName":"森林","decorIcon":"🌲"},{"id":"way-227521640-1/22032033133311201","lat":22.32767275789765,"lon":120.36408798724824,"name":"未命名森林","decorType":"forest","decorName":"森林","decorIcon":"🌲"},{"id":"way-227521640-1/22032033133022112","lat":22.327749840766604,"lon":120.36697016312985,"name":"未命名森林","decorType":"forest","decorName":"森林","decorIcon":"🌲"},{"id":"way-227521640-1/22032033133022113","lat":22.327601477198847,"lon":120.36769069710653,"name":"未命名森林","decorType":"forest","decorName":"森林","decorIcon":"🌲"},{"id":"way-227521640-1/22032033133311220","lat":22.328046559871872,"lon":120.3655290831835,"name":"未命名森林","decorType":"forest","decorName":"森林","decorIcon":"🌲"},{"id":"way-227521640-1/22032033133311221","lat":22.32789820165765,"lon":120.36624962515543,"name":"未命名森林","decorType":"forest","decorName":"森林","decorIcon":"🌲"},{"id":"way-227521640-1/22032033133311231","lat":22.328194915409135,"lon":120.36480853721434,"name":"未命名森林","decorType":"forest","decorName":"森林","decorIcon":"🌲"},{"id":"way-227521640-1/22032033133311232","lat":22.328343268269336,"lon":120.36408798724824,"name":"未命名森林","decorType":"forest","decorName":"森林","decorIcon":"🌲"},{"id":"way-227521640-1/22032033133022111","lat":22.32842033720213,"lon":120.36697016312985,"name":"未命名森林","decorType":"forest","decorName":"森林","decorIcon":"🌲"},{"id":"way-227521640-1/22032033133022110","lat":22.328271970119985,"lon":120.36769069710653,"name":"未命名森林","decorType":"forest","decorName":"森林","decorIcon":"🌲"},{"id":"way-227521640-1/22032033133311222","lat":22.328568701607484,"lon":120.36624962515543,"name":"未命名森林","decorType":"forest","decorName":"森林","decorIcon":"🌲"},{"id":"way-227521640-1/22032033133311230","lat":22.32886542238734,"lon":120.36480853721434,"name":"未命名森林","decorType":"forest","decorName":"森林","decorIcon":"🌲"},{"id":"way-227521640-1/22032033133311223","lat":22.328717063335933,"lon":120.3655290831835,"name":"未命名森林","decorType":"forest","decorName":"森林","decorIcon":"🌲"},{"id":"way-227521640-1/22032033133311233","lat":22.329013778761606,"lon":120.36408798724824,"name":"未命名森林","decorType":"forest","decorName":"森林","decorIcon":"🌲"},{"id":"way-227521640-1/22032033133021223","lat":22.328942463161827,"lon":120.36769069710653,"name":"未命名森林","decorType":"forest","decorName":"森林","decorIcon":"🌲"},{"id":"way-227521640-1/22032033133021230","lat":22.32879408988862,"lon":120.36841122708512,"name":"未命名森林","decorType":"forest","decorName":"森林","decorIcon":"🌲"},{"id":"way-227521640-1/22032033133312111","lat":22.32923920167786,"lon":120.36624962515543,"name":"未命名森林","decorType":"forest","decorName":"森林","decorIcon":"🌲"},{"id":"way-227521640-1/22032033133021222","lat":22.329090833758276,"lon":120.36697016312985,"name":"未命名森林","decorType":"forest","decorName":"森林","decorIcon":"🌲"},{"id":"way-227521640-1/22032033133312110","lat":22.329387566920452,"lon":120.3655290831835,"name":"未命名森林","decorType":"forest","decorName":"森林","decorIcon":"🌲"},{"id":"way-227521640-1/22032033133312103","lat":22.329535929485928,"lon":120.36480853721434,"name":"未命名森林","decorType":"forest","decorName":"森林","decorIcon":"🌲"},{"id":"way-227521640-1/22032033133021220","lat":22.329612956324087,"lon":120.36769069710653,"name":"未命名森林","decorType":"forest","decorName":"森林","decorIcon":"🌲"},{"id":"way-227521640-1/22032033133021231","lat":22.32946457953657,"lon":120.36841122708512,"name":"未命名森林","decorType":"forest","decorName":"森林","decorIcon":"🌲"},{"id":"way-227521640-1/22032033133021221","lat":22.329761330434764,"lon":120.36697016312985,"name":"未命名森林","decorType":"forest","decorName":"森林","decorIcon":"🌲"},{"id":"way-227521640-1/22032033133312112","lat":22.329909701868495,"lon":120.36624962515543,"name":"未命名森林","decorType":"forest","decorName":"森林","decorIcon":"🌲"},{"id":"way-227521640-1/22032033133312113","lat":22.330058070625153,"lon":120.3655290831835,"name":"未命名森林","decorType":"forest","decorName":"森林","decorIcon":"🌲"},{"id":"way-227521640-1/22032033133021202","lat":22.33013506930475,"lon":120.36841122708512,"name":"未命名森林","decorType":"forest","decorName":"森林","decorIcon":"🌲"},{"id":"way-227521640-1/22032033133021212","lat":22.33043182723132,"lon":120.36697016312985,"name":"未命名森林","decorType":"forest","decorName":"森林","decorIcon":"🌲"},{"id":"way-227521640-1/22032033133021213","lat":22.330283449606494,"lon":120.36769069710653,"name":"未命名森林","decorType":"forest","decorName":"森林","decorIcon":"🌲"},{"id":"way-227521640-1/22032033133312121","lat":22.330580202179117,"lon":120.36624962515543,"name":"未命名森林","decorType":"forest","decorName":"森林","decorIcon":"🌲"},{"id":"way-227521640-1/22032033133312120","lat":22.330728574449758,"lon":120.3655290831835,"name":"未命名森林","decorType":"forest","decorName":"森林","decorIcon":"🌲"},{"id":"way-227521640-1/22032033133311211","lat":22.326557202120725,"lon":120.36624962515543,"name":"未命名森林","decorType":"forest","decorName":"森林","decorIcon":"🌲"},{"id":"way-227521640-1/22032033133312102","lat":22.33020643670461,"lon":120.36480853721434,"name":"未命名森林","decorType":"forest","decorName":"森林","decorIcon":"🌲"},{"id":"way-227521640-1/22032033133311312","lat":22.327298931279255,"lon":120.36264687532645,"name":"未命名森林","decorType":"forest","decorName":"森林","decorIcon":"🌲"},{"id":"way-372689679-1/22032033133313031","lat":22.333927052736126,"lon":120.35976460353226,"name":"蛤板灣 (威尼斯沙灘)","decorType":"beach","decorName":"海灘","decorIcon":"🏖️"},{"id":"way-372689679-1/22032033133313002","lat":22.33459758514389,"lon":120.35976460353226,"name":"蛤板灣 (威尼斯沙灘)","decorType":"beach","decorName":"海灘","decorIcon":"🏖️"},{"id":"way-372689679-1/22032033133313001","lat":22.334449220242327,"lon":120.36048517747389,"name":"蛤板灣 (威尼斯沙灘)","decorType":"beach","decorName":"海灘","decorIcon":"🏖️"},{"id":"way-372689679-1/22032033133313000","lat":22.33511974925502,"lon":120.36048517747389,"name":"蛤板灣 (威尼斯沙灘)","decorType":"beach","decorName":"海灘","decorIcon":"🏖️"},{"id":"way-372689679-1/22032033133313023","lat":22.333404875643538,"lon":120.35904402559567,"name":"蛤板灣 (威尼斯沙灘)","decorType":"beach","decorName":"海灘","decorIcon":"🏖️"},{"id":"way-630709652-1/22032033133021021","lat":22.331030871149537,"lon":120.37057279302957,"name":"大福亭天然泳池","decorType":"waterside","decorName":"水邊","decorIcon":"💧"},{"id":"way-630709652-1/22032033133021012","lat":22.330882473112492,"lon":120.37129330701293,"name":"大福亭天然泳池","decorType":"waterside","decorName":"水邊","decorIcon":"💧"},{"id":"way-1299511340-1/22032033133311122","lat":22.325886702534195,"lon":120.36624962515543,"name":"未命名海灘","decorType":"beach","decorName":"海灘","decorIcon":"🏖️"},{"id":"way-1299511340-1/22032033133311121","lat":22.325216203069328,"lon":120.36624962515543,"name":"未命名海灘","decorType":"beach","decorName":"海灘","decorIcon":"🏖️"},{"id":"way-1299511340-1/22032033133311123","lat":22.326035050205252,"lon":120.3655290831835,"name":"未命名海灘","decorType":"beach","decorName":"海灘","decorIcon":"🏖️"},{"id":"way-1299511343-1/22032033133310330","lat":22.325210142287368,"lon":120.35976460353226,"name":"未命名水邊","decorType":"waterside","decorName":"水邊","decorIcon":"💧"},{"id":"way-1299511343-1/22032033133201001","lat":22.324539611558983,"lon":120.35976460353226,"name":"未命名水邊","decorType":"waterside","decorName":"水邊","decorIcon":"💧"},{"id":"way-1299511343-1/22032033133201032","lat":22.324687921079565,"lon":120.35904402559567,"name":"未命名水邊","decorType":"waterside","decorName":"水邊","decorIcon":"💧"},{"id":"way-1299511343-1/22032033133201031","lat":22.324017386959092,"lon":120.35904402559567,"name":"未命名水邊","decorType":"waterside","decorName":"水邊","decorIcon":"💧"},{"id":"way-1299511343-1/22032033133201030","lat":22.324165690288144,"lon":120.3583234436644,"name":"未命名水邊","decorType":"waterside","decorName":"水邊","decorIcon":"💧"},{"id":"way-1299511343-1/22032033133201023","lat":22.323495152775788,"lon":120.3583234436644,"name":"未命名水邊","decorType":"waterside","decorName":"水邊","decorIcon":"💧"},{"id":"way-1299511343-1/22032033133201133","lat":22.322972909009238,"lon":120.35760285773881,"name":"未命名水邊","decorType":"waterside","decorName":"水邊","decorIcon":"💧"}]}