{"bbox":{"south":24.9607,"north":24.976306,"west":121.626406,"east":121.639438},"pois":[{"id":"node-2482633485","lat":24.965211,"lon":121.638592,"name":"烏土堀山","decorType":"mountain"},{"id":"node-4100038313","lat":24.974829,"lon":121.630368,"name":"筆架山","decorType":"mountain"},{"id":"node-4478400392","lat":24.974295,"lon":121.63765,"name":"土地公廟","decorType":"shrine"},{"id":"node-7973573604","lat":24.975079,"lon":121.630498,"name":"筆架山北峰","decorType":"mountain"},{"id":"way-487093100","lat":24.968828,"lon":121.633406,"name":"未命名水邊","decorType":"waterside"},{"id":"way-528393018","lat":24.962105,"lon":121.638815,"name":"二格自然時光","decorType":"forest"},{"id":"way-791226241","lat":24.970736,"lon":121.639188,"name":"未命名水邊","decorType":"waterside"},{"id":"way-791226242","lat":24.970213,"lon":121.633215,"name":"未命名水邊","decorType":"waterside"},{"id":"way-791226244","lat":24.961176,"lon":121.634936,"name":"未命名水邊","decorType":"waterside"},{"id":"way-791226245","lat":24.959798,"lon":121.637996,"name":"未命名水邊","decorType":"waterside"},{"id":"way-791226249","lat":24.960821,"lon":121.631222,"name":"未命名水邊","decorType":"waterside"},{"id":"way-1433967719","lat":24.974482,"lon":121.633789,"name":"未命名水邊","decorType":"waterside"},{"id":"way-1433967720","lat":24.974858,"lon":121.634468,"name":"未命名水邊","decorType":"waterside"},{"id":"way-1433967721","lat":24.97475,"lon":121.636196,"name":"未命名水邊","decorType":"waterside"},{"id":"way-1433967722","lat":24.974106,"lon":121.637935,"name":"未命名水邊","decorType":"waterside"},{"id":"way-1433967723","lat":24.974465,"lon":121.638968,"name":"未命名水邊","decorType":"waterside"},{"id":"way-1433967731","lat":24.965176,"lon":121.63766,"name":"烏塗溪","decorType":"waterside"},{"id":"way-1433967742","lat":24.962492,"lon":121.63855,"name":"未命名水邊","decorType":"waterside"},{"id":"way-1450939833","lat":24.968553,"lon":121.628783,"name":"未命名水邊","decorType":"waterside"},{"id":"way-1450939834","lat":24.968614,"lon":121.630542,"name":"未命名水邊","decorType":"waterside"},{"id":"way-1450939835","lat":24.97219,"lon":121.632944,"name":"未命名水邊","decorType":"waterside"},{"id":"way-1450939836","lat":24.971359,"lon":121.633274,"name":"未命名水邊","decorType":"waterside"}]}