{"bbox":{"south":24.976306,"north":24.991912,"west":121.535187,"east":121.548219},"pois":[{"id":"node-1224950079","lat":24.982156,"lon":121.541605,"name":"出口 2","decorType":"station"},{"id":"node-1224950597","lat":24.982781,"lon":121.54099,"name":"出口 1","decorType":"station"},{"id":"node-1262769474","lat":24.978019,"lon":121.542933,"name":"7-Eleven","decorType":"convenience"},{"id":"node-1703008954","lat":24.982589,"lon":121.540805,"name":"新北市立圖書館新店分館","decorType":"library"},{"id":"node-1703071856","lat":24.98061,"lon":121.54169,"name":"麥當勞","decorType":"burger"},{"id":"node-1705753088","lat":24.978269,"lon":121.539243,"name":"7-Eleven","decorType":"convenience"},{"id":"node-1882978597","lat":24.983589,"lon":121.53611,"name":"未命名郵局","decorType":"post_office"},{"id":"node-1882978598","lat":24.982052,"lon":121.539077,"name":"未命名郵局","decorType":"post_office"},{"id":"node-1996853623","lat":24.976834,"lon":121.546817,"name":"寶橋路口","decorType":"bus_stop"},{"id":"node-1996853624","lat":24.976881,"lon":121.546356,"name":"寶橋路口","decorType":"bus_stop"},{"id":"node-2081952932","lat":24.978023,"lon":121.542843,"name":"新店郵局","decorType":"bus_stop"},{"id":"node-2081952936","lat":24.990749,"lon":121.539807,"name":"滬江中學","decorType":"bus_stop"},{"id":"node-2081952937","lat":24.983672,"lon":121.541092,"name":"捷運大坪林站","decorType":"bus_stop"},{"id":"node-2081952943","lat":24.980942,"lon":121.541872,"name":"大坪林","decorType":"bus_stop"},{"id":"node-2081952944","lat":24.983583,"lon":121.541331,"name":"捷運大坪林站","decorType":"bus_stop"},{"id":"node-2081952945","lat":24.978242,"lon":121.542521,"name":"新店郵局","decorType":"bus_stop"},{"id":"node-2081952947","lat":24.980948,"lon":121.541674,"name":"大坪林","decorType":"bus_stop"},{"id":"node-2081952950","lat":24.990851,"lon":121.540114,"name":"滬江中學","decorType":"bus_stop"},{"id":"node-2170239680","lat":24.990112,"lon":121.540901,"name":"永和豆漿","decorType":"restaurant"},{"id":"node-2177250580","lat":24.989355,"lon":121.541028,"name":"許家粿仔湯","decorType":"restaurant"},{"id":"node-2285210326","lat":24.980953,"lon":121.541571,"name":"康是美","decorType":"pharmacy"},{"id":"node-2292708733","lat":24.978204,"lon":121.542874,"name":"摩斯漢堡","decorType":"burger"},{"id":"node-2292708737","lat":24.977886,"lon":121.543119,"name":"全聯福利中心","decorType":"supermarket"},{"id":"node-2294865883","lat":24.978591,"lon":121.542625,"name":"未命名郵局","decorType":"post_office"},{"id":"node-2294865893","lat":24.977385,"lon":121.545389,"name":"燦坤3C","decorType":"electronics"},{"id":"node-2333018089","lat":24.986904,"lon":121.546504,"name":"復興派出所","decorType":"bus_stop"},{"id":"node-2333018090","lat":24.988517,"lon":121.544161,"name":"世新大學","decorType":"bus_stop"},{"id":"node-2333018091","lat":24.988488,"lon":121.543759,"name":"世新大學","decorType":"bus_stop"},{"id":"node-2333018092","lat":24.991548,"lon":121.541259,"name":"文山二分局","decorType":"bus_stop"},{"id":"node-2333018093","lat":24.989706,"lon":121.542489,"name":"景美國小(景興)","decorType":"bus_stop"},{"id":"node-2333018109","lat":24.986804,"lon":121.546884,"name":"復興派出所","decorType":"bus_stop"},{"id":"node-2335071369","lat":24.989043,"lon":121.540808,"name":"景美國小(景文)","decorType":"bus_stop"},{"id":"node-2335071376","lat":24.989112,"lon":121.540913,"name":"景美國小(景文)","decorType":"bus_stop"},{"id":"node-2349360987","lat":24.991745,"lon":121.540677,"name":"佳佳影城","decorType":"movie_theater"},{"id":"node-2378064674","lat":24.978181,"lon":121.53971,"name":"哈利波特專業烘焙坊","decorType":"bakery"},{"id":"node-2399354852","lat":24.991769,"lon":121.541214,"name":"85度C麵包坊","decorType":"cafe"},{"id":"node-2399354853","lat":24.991383,"lon":121.539987,"name":"全家便利商店","decorType":"convenience"},{"id":"node-2399354855","lat":24.991187,"lon":121.541383,"name":"全家便利商店","decorType":"convenience"},{"id":"node-2399354857","lat":24.990939,"lon":121.541308,"name":"康宜庭景文藥局","decorType":"pharmacy"},{"id":"node-2399354858","lat":24.991008,"lon":121.541327,"name":"CoCo都可","decorType":"cafe"},{"id":"node-2399354876","lat":24.990891,"lon":121.541298,"name":"吉野家","decorType":"burger"},{"id":"node-2399354916","lat":24.991101,"lon":121.541167,"name":"屈臣氏","decorType":"pharmacy"},{"id":"node-2399354917","lat":24.990303,"lon":121.540963,"name":"7-Eleven","decorType":"convenience"},{"id":"node-2424147438","lat":24.980613,"lon":121.547462,"name":"寶中路","decorType":"bus_stop"},{"id":"node-2424147448","lat":24.986293,"lon":121.540884,"name":"順安街","decorType":"bus_stop"},{"id":"node-2424147455","lat":24.986331,"lon":121.540781,"name":"順安街","decorType":"bus_stop"},{"id":"node-2424147465","lat":24.97931,"lon":121.545195,"name":"臺灣銀行","decorType":"bus_stop"},{"id":"node-2424147466","lat":24.97921,"lon":121.54363,"name":"寶強路口","decorType":"bus_stop"},{"id":"node-2424147467","lat":24.979117,"lon":121.543611,"name":"寶強路口","decorType":"bus_stop"},{"id":"node-2443290847","lat":24.977704,"lon":121.538519,"name":"大豐國小","decorType":"bus_stop"},{"id":"node-2443290848","lat":24.977716,"lon":121.538866,"name":"大豐國小","decorType":"bus_stop"},{"id":"node-2443290866","lat":24.979038,"lon":121.538645,"name":"大豐路","decorType":"bus_stop"},{"id":"node-2443290867","lat":24.979522,"lon":121.538405,"name":"大豐路","decorType":"bus_stop"},{"id":"node-2443290884","lat":24.981513,"lon":121.537773,"name":"建國路","decorType":"bus_stop"},{"id":"node-2443290885","lat":24.981665,"lon":121.537555,"name":"建國路","decorType":"bus_stop"},{"id":"node-2443290895","lat":24.983012,"lon":121.538557,"name":"民權工業區","decorType":"bus_stop"},{"id":"node-2443290896","lat":24.982839,"lon":121.538106,"name":"民權工業區","decorType":"bus_stop"},{"id":"node-2443290897","lat":24.982859,"lon":121.539998,"name":"民權路口","decorType":"bus_stop"},{"id":"node-2443290898","lat":24.983005,"lon":121.539646,"name":"民權路口","decorType":"bus_stop"},{"id":"node-2454119055","lat":24.981697,"lon":121.544059,"name":"中興路三段","decorType":"bus_stop"},{"id":"node-2454119058","lat":24.981301,"lon":121.543791,"name":"中興路三段","decorType":"bus_stop"},{"id":"node-2454119067","lat":24.979868,"lon":121.544664,"name":"寶中路口","decorType":"bus_stop"},{"id":"node-2454119070","lat":24.979824,"lon":121.544406,"name":"寶中路口","decorType":"bus_stop"},{"id":"node-2454138008","lat":24.97888,"lon":121.541144,"name":"民族北新路口","decorType":"bus_stop"},{"id":"node-2454138009","lat":24.978713,"lon":121.541092,"name":"民族北新路口","decorType":"bus_stop"},{"id":"node-2458066422","lat":24.976422,"lon":121.547784,"name":"寶橋中興路口一","decorType":"bus_stop"},{"id":"node-2460010000","lat":24.991717,"lon":121.541107,"name":"肉多多火鍋","decorType":"restaurant"},{"id":"node-2470165733","lat":24.98728,"lon":121.540872,"name":"寶斗厝熱炒店","decorType":"restaurant"},{"id":"node-2470165818","lat":24.987242,"lon":121.540711,"name":"笑居季節料理","decorType":"restaurant"},{"id":"node-2470166025","lat":24.987241,"lon":121.540872,"name":"洗衣王","decorType":"laundry"},{"id":"node-2470166027","lat":24.987023,"lon":121.540716,"name":"八廚師小籠湯包","decorType":"restaurant"},{"id":"node-2470166028","lat":24.986478,"lon":121.541011,"name":"夢幻雞","decorType":"restaurant"},{"id":"node-2470166035","lat":24.986462,"lon":121.540755,"name":"7-Eleven","decorType":"convenience"},{"id":"node-2470166074","lat":24.986419,"lon":121.540748,"name":"歐爺熱炒","decorType":"restaurant"},{"id":"node-2470166169","lat":24.986486,"lon":121.540741,"name":"正升藥局","decorType":"pharmacy"},{"id":"node-2470166246","lat":24.986557,"lon":121.540694,"name":"眾饕","decorType":"restaurant"},{"id":"node-2470166426","lat":24.98445,"lon":121.541264,"name":"四海豆漿","decorType":"restaurant"},{"id":"node-2470166880","lat":24.985475,"lon":121.539983,"name":"全家便利商店","decorType":"convenience"},{"id":"node-2482625767","lat":24.989617,"lon":121.543608,"name":"圳後山","decorType":"mountain"},{"id":"node-2507924073","lat":24.985203,"lon":121.536848,"name":"慈濟醫院","decorType":"bus_stop"},{"id":"node-2507924074","lat":24.985202,"lon":121.537026,"name":"慈濟醫院","decorType":"bus_stop"},{"id":"node-2526178893","lat":24.990049,"lon":121.547501,"name":"萊爾富","decorType":"convenience"},{"id":"node-2526191688","lat":24.990151,"lon":121.546402,"name":"異便當","decorType":"restaurant"},{"id":"node-2526198095","lat":24.989233,"lon":121.544954,"name":"未命名郵局","decorType":"post_office"},{"id":"node-2526282920","lat":24.986647,"lon":121.546081,"name":"萊爾富","decorType":"convenience"},{"id":"node-2526282924","lat":24.98682,"lon":121.545814,"name":"未命名郵局","decorType":"post_office"},{"id":"node-2526402990","lat":24.98971,"lon":121.541403,"name":"阿明","decorType":"restaurant"},{"id":"node-2527955444","lat":24.986322,"lon":121.547519,"name":"溝子口天主堂","decorType":"shrine"},{"id":"node-2529515832","lat":24.986657,"lon":121.546155,"name":"富粥城","decorType":"restaurant"},{"id":"node-2529515876","lat":24.98667,"lon":121.546202,"name":"裕康藥局","decorType":"pharmacy"},{"id":"node-2529515915","lat":24.986687,"lon":121.546266,"name":"勤習堂","decorType":"pharmacy"},{"id":"node-2529516103","lat":24.98671,"lon":121.546543,"name":"至仁堂健康素食餐廳","decorType":"restaurant"},{"id":"node-2529516151","lat":24.986748,"lon":121.546757,"name":"良粟商號","decorType":"burger"},{"id":"node-2529516309","lat":24.987133,"lon":121.547544,"name":"試院精緻自助餐","decorType":"restaurant"},{"id":"node-2529516361","lat":24.987118,"lon":121.547446,"name":"永春燒臘快餐","decorType":"restaurant"},{"id":"node-2529516403","lat":24.987101,"lon":121.547336,"name":"全家便利商店","decorType":"convenience"},{"id":"node-2529516960","lat":24.986935,"lon":121.546342,"name":"世心早餐吧","decorType":"restaurant"},{"id":"node-2536754288","lat":24.984495,"lon":121.541265,"name":"捷運大坪林站","decorType":"station"},{"id":"node-2547207564","lat":24.98082,"lon":121.541612,"name":"台灣大哥大","decorType":"electronics"},{"id":"node-2563901886","lat":24.982993,"lon":121.53662,"name":"7-Eleven","decorType":"convenience"},{"id":"node-2563901887","lat":24.982725,"lon":121.5365,"name":"全家便利商店","decorType":"convenience"},{"id":"node-2563901888","lat":24.982718,"lon":121.537307,"name":"客美多咖啡","decorType":"cafe"},{"id":"node-2563901889","lat":24.982784,"lon":121.536888,"name":"大禾拉麵","decorType":"restaurant"},{"id":"node-2563901890","lat":24.983133,"lon":121.536925,"name":"小蒙牛","decorType":"restaurant"},{"id":"node-2563901891","lat":24.983194,"lon":121.537061,"name":"原燒","decorType":"restaurant"},{"id":"node-2563901892","lat":24.983339,"lon":121.537104,"name":"西堤牛排","decorType":"restaurant"},{"id":"node-2563901893","lat":24.983412,"lon":121.536503,"name":"暹邏皇朝","decorType":"restaurant"},{"id":"node-2563901894","lat":24.983017,"lon":121.535653,"name":"伊薇特冰淇淋夢工廠","decorType":"bakery"},{"id":"node-2563901895","lat":24.983009,"lon":121.535523,"name":"百八漁場","decorType":"restaurant"},{"id":"node-2563901896","lat":24.983001,"lon":121.535373,"name":"水上鮮","decorType":"restaurant"},{"id":"node-2563901903","lat":24.982679,"lon":121.535315,"name":"50嵐","decorType":"cafe"},{"id":"node-2563901904","lat":24.982689,"lon":121.53541,"name":"正群川味牛肉麵","decorType":"restaurant"},{"id":"node-2563901905","lat":24.982668,"lon":121.535553,"name":"原師父小籠湯包","decorType":"restaurant"},{"id":"node-2628972337","lat":24.989699,"lon":121.542354,"name":"全家便利商店","decorType":"convenience"},{"id":"node-2628972338","lat":24.990015,"lon":121.542077,"name":"景新分館","decorType":"library"},{"id":"node-2667124110","lat":24.980139,"lon":121.536506,"name":"7-Eleven","decorType":"convenience"},{"id":"node-2667124116","lat":24.981002,"lon":121.537526,"name":"全家便利商店","decorType":"convenience"},{"id":"node-2667124117","lat":24.98096,"lon":121.537802,"name":"全聯福利中心","decorType":"supermarket"},{"id":"node-2667124118","lat":24.98102,"lon":121.537351,"name":"DRINK EAT COFFEE","decorType":"cafe"},{"id":"node-2667124119","lat":24.979652,"lon":121.539526,"name":"大豐牛肉麵","decorType":"restaurant"},{"id":"node-2667124120","lat":24.979784,"lon":121.538947,"name":"貴格會大坪林教會","decorType":"shrine"},{"id":"node-2667124121","lat":24.982796,"lon":121.541673,"name":"茶湯會","decorType":"cafe"},{"id":"node-2667124122","lat":24.982794,"lon":121.54174,"name":"Subway","decorType":"burger"},{"id":"node-2667124123","lat":24.982662,"lon":121.541226,"name":"可口豬腳大王","decorType":"restaurant"},{"id":"node-2690923542","lat":24.977711,"lon":121.545547,"name":"星巴克","decorType":"cafe"},{"id":"node-2713719850","lat":24.977996,"lon":121.539359,"name":"家樂福超市","decorType":"supermarket"},{"id":"node-2772748855","lat":24.983095,"lon":121.541119,"name":"橘村屋","decorType":"sweetshop"},{"id":"node-2772748899","lat":24.983164,"lon":121.541118,"name":"一条通","decorType":"restaurant"},{"id":"node-2772748954","lat":24.98324,"lon":121.541115,"name":"饗醬燒烤","decorType":"restaurant"},{"id":"node-2772749016","lat":24.983706,"lon":121.541042,"name":"茶裡不然 SPICE UP","decorType":"cafe"},{"id":"node-2772749311","lat":24.984109,"lon":121.540933,"name":"越南小吃","decorType":"restaurant"},{"id":"node-2772749525","lat":24.984344,"lon":121.541268,"name":"FUN鍋子","decorType":"restaurant"},{"id":"node-2772749949","lat":24.983325,"lon":121.541118,"name":"甜椒","decorType":"restaurant"},{"id":"node-2772750021","lat":24.983377,"lon":121.541112,"name":"泰味廚房","decorType":"restaurant"},{"id":"node-2772750113","lat":24.983053,"lon":121.540724,"name":"錢都日式刷刷鍋","decorType":"restaurant"},{"id":"node-2772750433","lat":24.98309,"lon":121.538225,"name":"全家便利商店","decorType":"convenience"},{"id":"node-2772751587","lat":24.983088,"lon":121.538412,"name":"十里安手麵","decorType":"restaurant"},{"id":"node-2772751681","lat":24.983089,"lon":121.538475,"name":"必勝客","decorType":"restaurant"},{"id":"node-2772751775","lat":24.983091,"lon":121.538554,"name":"永和豆漿","decorType":"restaurant"},{"id":"node-2772752159","lat":24.982777,"lon":121.538573,"name":"未命名餐廳","decorType":"restaurant"},{"id":"node-2772752481","lat":24.982772,"lon":121.539431,"name":"屈臣氏","decorType":"pharmacy"},{"id":"node-2772752603","lat":24.982773,"lon":121.539759,"name":"摩斯漢堡","decorType":"burger"},{"id":"node-2772752674","lat":24.982722,"lon":121.54034,"name":"全家便利商店","decorType":"convenience"},{"id":"node-2772752792","lat":24.982759,"lon":121.540475,"name":"日藥本舖","decorType":"pharmacy"},{"id":"node-2772752876","lat":24.982759,"lon":121.540591,"name":"康是美","decorType":"pharmacy"},{"id":"node-2820063988","lat":24.986796,"lon":121.54155,"name":"景美橋頭","decorType":"bus_stop"},{"id":"node-2820063989","lat":24.98667,"lon":121.538736,"name":"江陵二村","decorType":"bus_stop"},{"id":"node-2820063990","lat":24.986861,"lon":121.538545,"name":"江陵二村","decorType":"bus_stop"},{"id":"node-2839793645","lat":24.982124,"lon":121.541658,"name":"Motorla佶事通訊","decorType":"electronics"},{"id":"node-2839793646","lat":24.980743,"lon":121.541635,"name":"GR GLORY21","decorType":"clothing"},{"id":"node-2839793647","lat":24.9812,"lon":121.541516,"name":"HANG TEN","decorType":"clothing"},{"id":"node-2839793648","lat":24.980695,"lon":121.541654,"name":"HONOR 山形屋","decorType":"clothing"},{"id":"node-2839793649","lat":24.981134,"lon":121.541535,"name":"L'OCCITANE","decorType":"clothing"},{"id":"node-2839793651","lat":24.982255,"lon":121.541291,"name":"NET","decorType":"clothing"},{"id":"node-2839793652","lat":24.981263,"lon":121.541498,"name":"Triumph","decorType":"clothing"},{"id":"node-2839793654","lat":24.980712,"lon":121.542018,"name":"赫爾藥局","decorType":"pharmacy"},{"id":"node-2839793657","lat":24.981405,"lon":121.541815,"name":"信宏水電衛材大批發","decorType":"electronics"},{"id":"node-2839793662","lat":24.982219,"lon":121.541296,"name":"力苑時尚精品","decorType":"clothing"},{"id":"node-2839793665","lat":24.981524,"lon":121.541776,"name":"新店大坪林郵局","decorType":"post_office"},{"id":"node-2839793666","lat":24.981377,"lon":121.541466,"name":"Roots","decorType":"clothing"},{"id":"node-2839793671","lat":24.98142,"lon":121.541456,"name":"Poly Lulu","decorType":"clothing"},{"id":"node-2839793672","lat":24.982617,"lon":121.541234,"name":"康宜庭大坪林藥局","decorType":"pharmacy"},{"id":"node-2839793677","lat":24.980774,"lon":121.541625,"name":"慶生藥行","decorType":"pharmacy"},{"id":"node-2839793682","lat":24.981708,"lon":121.541732,"name":"全家便利商店","decorType":"convenience"},{"id":"node-2839793687","lat":24.981546,"lon":121.541424,"name":"獨身貴族","decorType":"clothing"},{"id":"node-2839793688","lat":24.982511,"lon":121.54158,"name":"神腦數位","decorType":"electronics"},{"id":"node-2839793693","lat":24.981591,"lon":121.541411,"name":"羅多達服飾","decorType":"clothing"},{"id":"node-2839793696","lat":24.982732,"lon":121.541544,"name":"WooTea五桐號","decorType":"cafe"},{"id":"node-2839793697","lat":24.981464,"lon":121.541443,"name":"芃諭名品北新店","decorType":"clothing"},{"id":"node-2839793698","lat":24.981708,"lon":121.541388,"name":"華歌爾","decorType":"clothing"},{"id":"node-2839793699","lat":24.981822,"lon":121.541712,"name":"薇朵漾Spa","decorType":"cosmetics"},{"id":"node-2839793701","lat":24.982485,"lon":121.541245,"name":"Oh My Girl","decorType":"clothing"},{"id":"node-2839793702","lat":24.982179,"lon":121.541301,"name":"衣戀流行服飾","decorType":"clothing"},{"id":"node-2839793704","lat":24.98259,"lon":121.541564,"name":"酸奶星球","decorType":"restaurant"},{"id":"node-2839793705","lat":24.98194,"lon":121.54134,"name":"阿瘦皮鞋","decorType":"clothing"},{"id":"node-2917177201","lat":24.990491,"lon":121.539709,"name":"未命名郵局","decorType":"post_office"},{"id":"node-2919811074","lat":24.98226,"lon":121.540772,"name":"小蔬杭上海風蔬食飲茶","decorType":"restaurant"},{"id":"node-2957302488","lat":24.980326,"lon":121.541359,"name":"COMEBUY","decorType":"cafe"},{"id":"node-2958618463","lat":24.980382,"lon":121.54116,"name":"7-Eleven","decorType":"convenience"},{"id":"node-2961064555","lat":24.980643,"lon":121.542037,"name":"水巷茶弄","decorType":"cafe"},{"id":"node-2961064556","lat":24.980416,"lon":121.542101,"name":"50嵐","decorType":"cafe"},{"id":"node-2961147707","lat":24.983116,"lon":121.541592,"name":"出口 3","decorType":"station"},{"id":"node-2961158874","lat":24.981779,"lon":121.541371,"name":"天仁茗茶","decorType":"cafe"},{"id":"node-2961225103","lat":24.981162,"lon":121.540701,"name":"OK超商","decorType":"convenience"},{"id":"node-2962648504","lat":24.983051,"lon":121.541046,"name":"coffee blablabla","decorType":"cafe"},{"id":"node-2964581090","lat":24.982766,"lon":121.542032,"name":"全家便利商店","decorType":"convenience"},{"id":"node-2964581091","lat":24.983055,"lon":121.542092,"name":"7-Eleven","decorType":"convenience"},{"id":"node-2971370248","lat":24.991554,"lon":121.542728,"name":"燦坤3C","decorType":"electronics"},{"id":"node-3053663634","lat":24.99068,"lon":121.538835,"name":"基督教信義會慈恩堂","decorType":"shrine"},{"id":"node-3065310818","lat":24.976947,"lon":121.542698,"name":"七張站2號出口","decorType":"station"},{"id":"node-3087727934","lat":24.986805,"lon":121.541893,"name":"7-Eleven","decorType":"convenience"},{"id":"node-3087727935","lat":24.983552,"lon":121.541493,"name":"出口 4","decorType":"station"},{"id":"node-3100255229","lat":24.980464,"lon":121.541687,"name":"家和日本料理","decorType":"restaurant"},{"id":"node-3104845927","lat":24.983482,"lon":121.53701,"name":"1010湘","decorType":"restaurant"},{"id":"node-3105692739","lat":24.983194,"lon":121.537744,"name":"繼光香香雞","decorType":"burger"},{"id":"node-3117934556","lat":24.991408,"lon":121.541193,"name":"Curves女性30分鐘健身中心","decorType":"stadium"},{"id":"node-3145515542","lat":24.984522,"lon":121.54236,"name":"白帝城精緻涮鍋","decorType":"restaurant"},{"id":"node-3145515544","lat":24.98401,"lon":121.541781,"name":"FOX Coffee","decorType":"cafe"},{"id":"node-3157780063","lat":24.990702,"lon":121.539703,"name":"池上木片便當","decorType":"restaurant"},{"id":"node-3157785561","lat":24.991659,"lon":121.540093,"name":"客拉客台式自助餐","decorType":"restaurant"},{"id":"node-3182093767","lat":24.989823,"lon":121.54237,"name":"mint義大利麵店","decorType":"restaurant"},{"id":"node-3182093768","lat":24.989856,"lon":121.54119,"name":"168鐵板燒","decorType":"restaurant"},{"id":"node-3182105513","lat":24.989394,"lon":121.541031,"name":"麥園蛋糕","decorType":"bakery"},{"id":"node-3182109607","lat":24.991338,"lon":121.541423,"name":"欣安藥局","decorType":"pharmacy"},{"id":"node-3182115422","lat":24.991542,"lon":121.541838,"name":"鵝媽媽","decorType":"restaurant"},{"id":"node-3182115423","lat":24.990644,"lon":121.541393,"name":"阿陳麵店","decorType":"restaurant"},{"id":"node-3182115424","lat":24.99057,"lon":121.541498,"name":"阿昌麵線","decorType":"restaurant"},{"id":"node-3182115426","lat":24.990774,"lon":121.541441,"name":"粥粥頌","decorType":"restaurant"},{"id":"node-3200065444","lat":24.986364,"lon":121.542232,"name":"進寶殿","decorType":"shrine"},{"id":"node-3230950217","lat":24.986969,"lon":121.536718,"name":"復興路口","decorType":"bus_stop"},{"id":"node-3230950218","lat":24.987272,"lon":121.53673,"name":"復興路口","decorType":"bus_stop"},{"id":"node-3316663083","lat":24.990411,"lon":121.53948,"name":"陶媽溫州大餛飩","decorType":"restaurant"},{"id":"node-3316912674","lat":24.991748,"lon":121.541046,"name":"家賓大旅社","decorType":"hotel"},{"id":"node-3316912675","lat":24.990114,"lon":121.540796,"name":"景美大旅社","decorType":"hotel"},{"id":"node-3358124913","lat":24.987212,"lon":121.537968,"name":"二十張土地公廟","decorType":"shrine"},{"id":"node-3445169937","lat":24.990193,"lon":121.541799,"name":"欣欣大眾魷魚羹","decorType":"restaurant"},{"id":"node-3451792793","lat":24.991336,"lon":121.541218,"name":"Giordano","decorType":"clothing"},{"id":"node-3451792893","lat":24.991425,"lon":121.541018,"name":"小林髮廊","decorType":"hair_salon"},{"id":"node-3451793393","lat":24.991617,"lon":121.540079,"name":"La New","decorType":"clothing"},{"id":"node-3489978793","lat":24.98439,"lon":121.541212,"name":"捷運大坪林站","decorType":"bus_stop"},{"id":"node-3489979193","lat":24.983841,"lon":121.541289,"name":"捷運大坪林站","decorType":"bus_stop"},{"id":"node-3502209235","lat":24.98293,"lon":121.541329,"name":"大坪林","decorType":"station"},{"id":"node-3503443032","lat":24.989466,"lon":121.541412,"name":"穀香雞肉飯","decorType":"restaurant"},{"id":"node-3503443033","lat":24.982776,"lon":121.54289,"name":"三三活力早餐","decorType":"restaurant"},{"id":"node-3505403808","lat":24.991421,"lon":121.539957,"name":"景美教會","decorType":"shrine"},{"id":"node-3617148999","lat":24.97847,"lon":121.53953,"name":"丹媞絲手作烘焙坊","decorType":"bakery"},{"id":"node-3652897622","lat":24.984827,"lon":121.541216,"name":"金鑽髮型","decorType":"hair_salon"},{"id":"node-3662465218","lat":24.980175,"lon":121.542143,"name":"炸老大","decorType":"restaurant"},{"id":"node-3731157012","lat":24.976395,"lon":121.542737,"name":"7-Eleven","decorType":"convenience"},{"id":"node-3740341264","lat":24.991801,"lon":121.540161,"name":"御馥西點麵包","decorType":"bakery"},{"id":"node-3740347526","lat":24.991718,"lon":121.540136,"name":"全美素食","decorType":"restaurant"},{"id":"node-3740347527","lat":24.991502,"lon":121.540043,"name":"7-Eleven","decorType":"convenience"},{"id":"node-3767530258","lat":24.989138,"lon":121.541001,"name":"Mymore","decorType":"bakery"},{"id":"node-3767530261","lat":24.989454,"lon":121.54105,"name":"元山五金衡器行","decorType":"hardware"},{"id":"node-3767530262","lat":24.99037,"lon":121.541232,"name":"八方雲集","decorType":"burger"},{"id":"node-3767530263","lat":24.989259,"lon":121.541027,"name":"勝琪電器","decorType":"electronics"},{"id":"node-3767530265","lat":24.988869,"lon":121.540989,"name":"吉祥素食自助餐","decorType":"restaurant"},{"id":"node-3767530267","lat":24.990334,"lon":121.540976,"name":"大苑子","decorType":"cafe"},{"id":"node-3767530268","lat":24.98931,"lon":121.541025,"name":"太發五金行","decorType":"hardware"},{"id":"node-3767530271","lat":24.988715,"lon":121.540996,"name":"景美水果行","decorType":"supermarket"},{"id":"node-3767530273","lat":24.989729,"lon":121.541058,"name":"景美鐵板燒","decorType":"restaurant"},{"id":"node-3767530275","lat":24.989934,"lon":121.54114,"name":"人从众厚切牛排","decorType":"restaurant"},{"id":"node-3767530279","lat":24.990246,"lon":121.541198,"name":"清心福全","decorType":"cafe"},{"id":"node-3767530298","lat":24.990315,"lon":121.541221,"name":"景美藥局","decorType":"pharmacy"},{"id":"node-3767530299","lat":24.99047,"lon":121.541218,"name":"義興樓","decorType":"restaurant"},{"id":"node-3767530301","lat":24.990192,"lon":121.540927,"name":"荷雅婷","decorType":"clothing"},{"id":"node-3767530302","lat":24.990209,"lon":121.541182,"name":"串門兒麻辣串串","decorType":"restaurant"},{"id":"node-3767530306","lat":24.99067,"lon":121.541323,"name":"未命名超市","decorType":"supermarket"},{"id":"node-3767530309","lat":24.989071,"lon":121.540994,"name":"鹿港滷肉飯","decorType":"restaurant"},{"id":"node-3767530310","lat":24.988932,"lon":121.540988,"name":"甘那青水產","decorType":"restaurant"},{"id":"node-3767530311","lat":24.988736,"lon":121.540998,"name":"番薯の店生猛活海鮮","decorType":"restaurant"},{"id":"node-3780481378","lat":24.984281,"lon":121.540101,"name":"7-Eleven","decorType":"convenience"},{"id":"node-3780487164","lat":24.982037,"lon":121.538267,"name":"上川館","decorType":"restaurant"},{"id":"node-3780487808","lat":24.982578,"lon":121.539747,"name":"美養莊園","decorType":"restaurant"},{"id":"node-3780490283","lat":24.983136,"lon":121.540382,"name":"有名堂","decorType":"restaurant"},{"id":"node-3780638675","lat":24.984025,"lon":121.53991,"name":"頤品大飯店新店北新館","decorType":"restaurant"},{"id":"node-3780638676","lat":24.984225,"lon":121.539945,"name":"豪鼎飯店 北新旗艦館","decorType":"restaurant"},{"id":"node-3794607142","lat":24.99117,"lon":121.542278,"name":"V1租書DVD","decorType":"library"},{"id":"node-3794607148","lat":24.991591,"lon":121.541202,"name":"蛋白盒子","decorType":"restaurant"},{"id":"node-3794607156","lat":24.990985,"lon":121.54132,"name":"桶一天下現滷滷味","decorType":"restaurant"},{"id":"node-3794607283","lat":24.991394,"lon":121.54141,"name":"超時代名店","decorType":"clothing"},{"id":"node-3794607286","lat":24.991446,"lon":121.541399,"name":"喫尤平價鐵板燒","decorType":"restaurant"},{"id":"node-3809456229","lat":24.989343,"lon":121.544934,"name":"Subway","decorType":"burger"},{"id":"node-3809467542","lat":24.980626,"lon":121.544596,"name":"全家便利商店","decorType":"convenience"},{"id":"node-3809467544","lat":24.987129,"lon":121.547512,"name":"Qburger","decorType":"burger"},{"id":"node-3811441545","lat":24.977525,"lon":121.538664,"name":"全家便利商店","decorType":"convenience"},{"id":"node-3811447088","lat":24.978747,"lon":121.540097,"name":"未命名漢堡店","decorType":"burger"},{"id":"node-3812406072","lat":24.990515,"lon":121.542973,"name":"投幣式自助洗衣","decorType":"laundry"},{"id":"node-3812406074","lat":24.991822,"lon":121.540641,"name":"日溢通訊","decorType":"electronics"},{"id":"node-3812406083","lat":24.991191,"lon":121.543772,"name":"浸信會義美堂","decorType":"shrine"},{"id":"node-3812406118","lat":24.991277,"lon":121.543814,"name":"精美理髮廳","decorType":"hair_salon"},{"id":"node-3812406119","lat":24.991205,"lon":121.540342,"name":"紅蕃茄精緻早午餐","decorType":"restaurant"},{"id":"node-3812614657","lat":24.982778,"lon":121.542761,"name":"白甘蔗養生涮涮屋","decorType":"restaurant"},{"id":"node-3819937637","lat":24.986899,"lon":121.547603,"name":"金瑪莉","decorType":"restaurant"},{"id":"node-3819941587","lat":24.9856,"lon":121.54639,"name":"鄉村漢堡","decorType":"restaurant"},{"id":"node-3867437306","lat":24.982768,"lon":121.542208,"name":"圍樂鮮境精緻涮涮鍋","decorType":"restaurant"},{"id":"node-3867437820","lat":24.980939,"lon":121.541451,"name":"黎明Hotel","decorType":"hotel"},{"id":"node-3891423025","lat":24.981106,"lon":121.54182,"name":"大坪林","decorType":"bus_stop"},{"id":"node-3891423028","lat":24.983745,"lon":121.541043,"name":"妙觀音","decorType":"restaurant"},{"id":"node-3929888362","lat":24.99015,"lon":121.540345,"name":"Trouble Maker手工鬆餅專賣店","decorType":"bakery"},{"id":"node-3929888369","lat":24.990927,"lon":121.539808,"name":"佳醫藥局","decorType":"pharmacy"},{"id":"node-3929888371","lat":24.990059,"lon":121.540802,"name":"修指甲","decorType":"cosmetics"},{"id":"node-3929888390","lat":24.990973,"lon":121.539831,"name":"天德堂蔘藥行","decorType":"pharmacy"},{"id":"node-3929888409","lat":24.98677,"lon":121.541926,"name":"未命名郵局","decorType":"post_office"},{"id":"node-3929888464","lat":24.990152,"lon":121.540406,"name":"萱悅髮型設計","decorType":"hair_salon"},{"id":"node-3929888473","lat":24.990812,"lon":121.539748,"name":"雅客剪燙設計","decorType":"hair_salon"},{"id":"node-3929888478","lat":24.990113,"lon":121.540568,"name":"麥味登","decorType":"restaurant"},{"id":"node-4007798810","lat":24.989534,"lon":121.542075,"name":"吃!早午餐","decorType":"restaurant"},{"id":"node-4007798812","lat":24.989824,"lon":121.541638,"name":"上園肉羹","decorType":"restaurant"},{"id":"node-4007798814","lat":24.991188,"lon":121.541889,"name":"九九鞋店","decorType":"clothing"},{"id":"node-4007798816","lat":24.989604,"lon":121.541928,"name":"Manny Pasta 義大利麵","decorType":"restaurant"},{"id":"node-4007798818","lat":24.989823,"lon":121.541537,"name":"口昍品麻辣臭豆腐","decorType":"restaurant"},{"id":"node-4007798819","lat":24.989713,"lon":121.541488,"name":"吃得飽牛肉麵店","decorType":"restaurant"},{"id":"node-4007798821","lat":24.99112,"lon":121.541859,"name":"嘉利精品皮鞋","decorType":"clothing"},{"id":"node-4007798823","lat":24.990643,"lon":121.54241,"name":"宇秀理髮","decorType":"hair_salon"},{"id":"node-4007798827","lat":24.989672,"lon":121.54164,"name":"巧藝沙龍","decorType":"hair_salon"},{"id":"node-4007798829","lat":24.991062,"lon":121.541846,"name":"未命名服飾店","decorType":"clothing"},{"id":"node-4007798830","lat":24.990549,"lon":121.542369,"name":"新景美理髮","decorType":"hair_salon"},{"id":"node-4007798831","lat":24.991583,"lon":121.541522,"name":"新進安藥房","decorType":"pharmacy"},{"id":"node-4007798832","lat":24.991344,"lon":121.541931,"name":"春風鮮果專賣廣場","decorType":"supermarket"},{"id":"node-4007798834","lat":24.990318,"lon":121.543164,"name":"景美南聖堂","decorType":"shrine"},{"id":"node-4007798837","lat":24.990184,"lon":121.542333,"name":"首爾食堂","decorType":"restaurant"},{"id":"node-4007798839","lat":24.990766,"lon":121.541487,"name":"歡喜素食","decorType":"restaurant"},{"id":"node-4007798840","lat":24.99139,"lon":121.542016,"name":"正光皮鞋店","decorType":"clothing"},{"id":"node-4007798841","lat":24.991258,"lon":121.541899,"name":"永安皮鞋","decorType":"clothing"},{"id":"node-4007798842","lat":24.991696,"lon":121.541481,"name":"瑞麟美又美","decorType":"restaurant"},{"id":"node-4007798874","lat":24.989703,"lon":121.541671,"name":"泰讚了","decorType":"cafe"},{"id":"node-4007811620","lat":24.991492,"lon":121.539712,"name":"未命名餐廳","decorType":"restaurant"},{"id":"node-4007811643","lat":24.989812,"lon":121.541414,"name":"炎帝炒飯鐵板燒","decorType":"restaurant"},{"id":"node-4007811645","lat":24.991407,"lon":121.541799,"name":"華明西藥房","decorType":"pharmacy"},{"id":"node-4007811646","lat":24.991324,"lon":121.542159,"name":"華歌爾","decorType":"clothing"},{"id":"node-4007811647","lat":24.991618,"lon":121.54004,"name":"菲林髮型美容","decorType":"hair_salon"},{"id":"node-4007811650","lat":24.990884,"lon":121.54183,"name":"裕豐","decorType":"clothing"},{"id":"node-4007811651","lat":24.989705,"lon":121.541609,"name":"詩威特","decorType":"cosmetics"},{"id":"node-4007811654","lat":24.989338,"lon":121.542194,"name":"路邊攤日式小吃","decorType":"restaurant"},{"id":"node-4007811655","lat":24.991647,"lon":121.541465,"name":"鄭家燒肉飯","decorType":"restaurant"},{"id":"node-4033147894","lat":24.98177,"lon":121.543542,"name":"全家便利商店","decorType":"convenience"},{"id":"node-4033147895","lat":24.981698,"lon":121.54357,"name":"咕咕G廚房","decorType":"restaurant"},{"id":"node-4033147897","lat":24.982796,"lon":121.540047,"name":"小林髮廊","decorType":"hair_salon"},{"id":"node-4033147902","lat":24.982548,"lon":121.540757,"name":"星巴克","decorType":"cafe"},{"id":"node-4043625902","lat":24.990519,"lon":121.541609,"name":"J.L傑儷流行服飾","decorType":"clothing"},{"id":"node-4043625903","lat":24.989729,"lon":121.541276,"name":"五高滷味","decorType":"restaurant"},{"id":"node-4043625904","lat":24.990103,"lon":121.541263,"name":"冬鮮堂","decorType":"cafe"},{"id":"node-4043625905","lat":24.989395,"lon":121.541442,"name":"小六越南美食","decorType":"restaurant"},{"id":"node-4043625907","lat":24.990836,"lon":121.541721,"name":"妮妮孕婦裝","decorType":"clothing"},{"id":"node-4043625910","lat":24.989423,"lon":121.541543,"name":"素煮意越式素食","decorType":"restaurant"},{"id":"node-4043625911","lat":24.99085,"lon":121.541818,"name":"未命名服飾店","decorType":"clothing"},{"id":"node-4043625915","lat":24.989643,"lon":121.541304,"name":"獨特牛排館","decorType":"restaurant"},{"id":"node-4043625916","lat":24.990212,"lon":121.541493,"name":"玲兒Fashion Store","decorType":"clothing"},{"id":"node-4043625917","lat":24.990112,"lon":121.541133,"name":"祖傳牛肉麵","decorType":"restaurant"},{"id":"node-4043625920","lat":24.99077,"lon":121.541797,"name":"未命名服飾店","decorType":"clothing"},{"id":"node-4043625923","lat":24.989829,"lon":121.541365,"name":"蛋包飯達人","decorType":"restaurant"},{"id":"node-4043625924","lat":24.989466,"lon":121.541532,"name":"秀夫丼飯","decorType":"restaurant"},{"id":"node-4043625926","lat":24.989642,"lon":121.541422,"name":"北投紅茶","decorType":"cafe"},{"id":"node-4043625927","lat":24.990279,"lon":121.541563,"name":"駭客走廊精緻牛仔","decorType":"clothing"},{"id":"node-4043625928","lat":24.989589,"lon":121.541455,"name":"高家雙管四神湯","decorType":"restaurant"},{"id":"node-4070047121","lat":24.990223,"lon":121.541338,"name":"She in","decorType":"clothing"},{"id":"node-4070047129","lat":24.990107,"lon":121.541333,"name":"兩兄弟臭豆腐","decorType":"restaurant"},{"id":"node-4070047134","lat":24.99025,"lon":121.541521,"name":"景美機場","decorType":"electronics"},{"id":"node-4070047135","lat":24.991626,"lon":121.540637,"name":"景美錫安堂","decorType":"shrine"},{"id":"node-4070047138","lat":24.987584,"lon":121.543198,"name":"寶安宮","decorType":"shrine"},{"id":"node-4070047187","lat":24.990753,"lon":121.541518,"name":"聰明油飯","decorType":"restaurant"},{"id":"node-4070047992","lat":24.990781,"lon":121.541393,"name":"阿裕米粉烤肉","decorType":"restaurant"},{"id":"node-4142560391","lat":24.979547,"lon":121.544476,"name":"清六食堂","decorType":"restaurant"},{"id":"node-4142796789","lat":24.979513,"lon":121.544378,"name":"小樂天餃子館","decorType":"restaurant"},{"id":"node-4142798399","lat":24.980577,"lon":121.544694,"name":"山頂咖啡","decorType":"cafe"},{"id":"node-4142798495","lat":24.980908,"lon":121.544358,"name":"7-Eleven","decorType":"convenience"},{"id":"node-4142809429","lat":24.980965,"lon":121.54458,"name":"禾廬雅廚館","decorType":"restaurant"},{"id":"node-4142892406","lat":24.983064,"lon":121.540523,"name":"集客人間茶館","decorType":"cafe"},{"id":"node-4142892484","lat":24.983134,"lon":121.54063,"name":"舊識西餐廳","decorType":"restaurant"},{"id":"node-4143010317","lat":24.981008,"lon":121.544304,"name":"拉亞漢堡","decorType":"burger"},{"id":"node-4143011639","lat":24.9812,"lon":121.544245,"name":"韓成之家","decorType":"restaurant"},{"id":"node-4143035557","lat":24.981088,"lon":121.544277,"name":"黑人牛肉麵店","decorType":"restaurant"},{"id":"node-4143035558","lat":24.980597,"lon":121.544066,"name":"日本九州拉麵","decorType":"restaurant"},{"id":"node-4143918621","lat":24.980337,"lon":121.542117,"name":"清心福全","decorType":"cafe"},{"id":"node-4143920267","lat":24.979001,"lon":121.54272,"name":"巧主廚の咖哩","decorType":"restaurant"},{"id":"node-4143924194","lat":24.97931,"lon":121.542802,"name":"伊仟","decorType":"hair_salon"},{"id":"node-4143929424","lat":24.979109,"lon":121.542613,"name":"韓風饌","decorType":"restaurant"},{"id":"node-4143947789","lat":24.979561,"lon":121.543082,"name":"全家便利商店","decorType":"convenience"},{"id":"node-4143947790","lat":24.979154,"lon":121.542651,"name":"阿舍麵館","decorType":"restaurant"},{"id":"node-4143951002","lat":24.979459,"lon":121.544184,"name":"Casa義式香草廚房","decorType":"restaurant"},{"id":"node-4144485936","lat":24.979405,"lon":121.544016,"name":"未命名拉麵店","decorType":"ramen"},{"id":"node-4144499871","lat":24.983059,"lon":121.543058,"name":"大埔鐵板燒","decorType":"restaurant"},{"id":"node-4144510617","lat":24.98277,"lon":121.542143,"name":"康是美","decorType":"pharmacy"},{"id":"node-4160758328","lat":24.9826,"lon":121.54372,"name":"瑞義意麵","decorType":"restaurant"},{"id":"node-4199678596","lat":24.982865,"lon":121.53702,"name":"民權工業區一","decorType":"bus_stop"},{"id":"node-4199682093","lat":24.982969,"lon":121.537241,"name":"民權工業區一","decorType":"bus_stop"},{"id":"node-4232142416","lat":24.985189,"lon":121.540963,"name":"大林工程行","decorType":"hardware"},{"id":"node-4328118425","lat":24.985431,"lon":121.540205,"name":"彭園會館","decorType":"restaurant"},{"id":"node-4328118619","lat":24.98226,"lon":121.54161,"name":"馬可先生","decorType":"bakery"},{"id":"node-4334072410","lat":24.977407,"lon":121.53852,"name":"關山便當","decorType":"restaurant"},{"id":"node-4371589420","lat":24.984264,"lon":121.541219,"name":"捷運大坪林站","decorType":"bus_stop"},{"id":"node-4384257966","lat":24.979548,"lon":121.538526,"name":"二十張靈糧福音中心","decorType":"shrine"},{"id":"node-4384257968","lat":24.983041,"lon":121.542471,"name":"京御鐵板燒","decorType":"restaurant"},{"id":"node-4384257979","lat":24.984127,"lon":121.543123,"name":"台南溫體牛","decorType":"restaurant"},{"id":"node-4384257980","lat":24.983054,"lon":121.542357,"name":"周胖子餃子館","decorType":"restaurant"},{"id":"node-4384257984","lat":24.983295,"lon":121.536981,"name":"大坪林靈糧福音中心","decorType":"shrine"},{"id":"node-4384257985","lat":24.986573,"lon":121.541416,"name":"大眾黑白切","decorType":"restaurant"},{"id":"node-4384258991","lat":24.986169,"lon":121.54147,"name":"家庭理髮","decorType":"hair_salon"},{"id":"node-4384258993","lat":24.982739,"lon":121.538208,"name":"小頭目熱炒鵝肉燒烤海鮮","decorType":"restaurant"},{"id":"node-4384258996","lat":24.991304,"lon":121.542571,"name":"崴力通訊","decorType":"electronics"},{"id":"node-4384259007","lat":24.991136,"lon":121.542527,"name":"早點","decorType":"restaurant"},{"id":"node-4384259009","lat":24.983106,"lon":121.537799,"name":"星巴克","decorType":"cafe"},{"id":"node-4384259012","lat":24.983047,"lon":121.542789,"name":"白寶奶奶港式菠蘿包","decorType":"bakery"},{"id":"node-4384259019","lat":24.979814,"lon":121.538296,"name":"永和豆漿","decorType":"restaurant"},{"id":"node-4384259020","lat":24.982517,"lon":121.542091,"name":"永哥港式點心坊","decorType":"restaurant"},{"id":"node-4384259021","lat":24.983076,"lon":121.538595,"name":"海鮮鍋物","decorType":"restaurant"},{"id":"node-4384259027","lat":24.982793,"lon":121.541839,"name":"福圓號","decorType":"bakery"},{"id":"node-4384259207","lat":24.985305,"lon":121.542489,"name":"萊爾富","decorType":"convenience"},{"id":"node-4384259213","lat":24.991289,"lon":121.542562,"name":"銅板美食涼麵王","decorType":"restaurant"},{"id":"node-4384259217","lat":24.98317,"lon":121.542989,"name":"阿輝牛肉城","decorType":"restaurant"},{"id":"node-4384259220","lat":24.985681,"lon":121.54189,"name":"雜貨店","decorType":"convenience"},{"id":"node-4384259227","lat":24.985072,"lon":121.542036,"name":"香祥海鮮店","decorType":"restaurant"},{"id":"node-4459970427","lat":24.97998,"lon":121.540576,"name":"九湯屋","decorType":"restaurant"},{"id":"node-4464406489","lat":24.97747,"lon":121.540341,"name":"豆花朴","decorType":"restaurant"},{"id":"node-4512469693","lat":24.991732,"lon":121.54009,"name":"阿皮耶藝術","decorType":"art_gallery"},{"id":"node-4512469695","lat":24.99039,"lon":121.539508,"name":"開口笑早餐店","decorType":"restaurant"},{"id":"node-4512469696","lat":24.990106,"lon":121.540615,"name":"老酒霸","decorType":"restaurant"},{"id":"node-4512469697","lat":24.990594,"lon":121.541248,"name":"棉花田生機飲食","decorType":"supermarket"},{"id":"node-4524318924","lat":24.991874,"lon":121.54009,"name":"快樂髮廊","decorType":"hair_salon"},{"id":"node-4524318925","lat":24.990879,"lon":121.541341,"name":"曼都髮廊","decorType":"hair_salon"},{"id":"node-4524318926","lat":24.991688,"lon":121.541222,"name":"儷晶美容髮藝","decorType":"hair_salon"},{"id":"node-4524318930","lat":24.990623,"lon":121.542018,"name":"巷口炒飯王","decorType":"restaurant"},{"id":"node-4524318931","lat":24.99039,"lon":121.542314,"name":"爆漿卡通雞蛋糕","decorType":"bakery"},{"id":"node-4524318932","lat":24.990429,"lon":121.542323,"name":"洞之家","decorType":"restaurant"},{"id":"node-4524318933","lat":24.990461,"lon":121.542342,"name":"大橋頭魯肉飯","decorType":"restaurant"},{"id":"node-4524318935","lat":24.990503,"lon":121.542353,"name":"一家麵店","decorType":"restaurant"},{"id":"node-4524318947","lat":24.990981,"lon":121.539314,"name":"紫羅蘭髮廊","decorType":"hair_salon"},{"id":"node-4524318948","lat":24.990831,"lon":121.539186,"name":"比堤髮型設計","decorType":"hair_salon"},{"id":"node-4524318953","lat":24.991442,"lon":121.544796,"name":"華陀門弘道院","decorType":"shrine"},{"id":"node-4524343993","lat":24.983287,"lon":121.537711,"name":"瓦城","decorType":"restaurant"},{"id":"node-4524344001","lat":24.978234,"lon":121.539207,"name":"台南擔仔麵","decorType":"restaurant"},{"id":"node-4524344003","lat":24.982675,"lon":121.538004,"name":"米尼美式餐廳","decorType":"restaurant"},{"id":"node-4524344004","lat":24.983365,"lon":121.537663,"name":"路易莎咖啡","decorType":"cafe"},{"id":"node-4524344021","lat":24.98307,"lon":121.540593,"name":"米塔手感烘培","decorType":"bakery"},{"id":"node-4524344022","lat":24.983095,"lon":121.539051,"name":"仙妮蔂德","decorType":"pharmacy"},{"id":"node-4524344025","lat":24.98272,"lon":121.537779,"name":"均安藥局","decorType":"pharmacy"},{"id":"node-4524344026","lat":24.982668,"lon":121.535651,"name":"50嵐","decorType":"cafe"},{"id":"node-4524344028","lat":24.982767,"lon":121.539669,"name":"聖德科斯","decorType":"supermarket"},{"id":"node-4531455524","lat":24.982784,"lon":121.536939,"name":"方圓涮涮屋","decorType":"restaurant"},{"id":"node-4538270107","lat":24.989221,"lon":121.541632,"name":"如意甜品","decorType":"cafe"},{"id":"node-4538270108","lat":24.989038,"lon":121.541574,"name":"應善壇","decorType":"shrine"},{"id":"node-4538270109","lat":24.989265,"lon":121.541606,"name":"蚵仔之家","decorType":"restaurant"},{"id":"node-4538270111","lat":24.9896,"lon":121.541315,"name":"傑凱瑞通訊行","decorType":"electronics"},{"id":"node-4577670809","lat":24.980954,"lon":121.540983,"name":"美廉社","decorType":"supermarket"},{"id":"node-4739658683","lat":24.989424,"lon":121.545092,"name":"7-Eleven","decorType":"convenience"},{"id":"node-4739658684","lat":24.989376,"lon":121.544985,"name":"電腦先生","decorType":"electronics"},{"id":"node-4774166262","lat":24.989513,"lon":121.541492,"name":"麻辣天后炒香鍋","decorType":"restaurant"},{"id":"node-4834782015","lat":24.979186,"lon":121.542495,"name":"隆鼎御品豬腳","decorType":"restaurant"},{"id":"node-4834782531","lat":24.981544,"lon":121.537811,"name":"高記燒臘廚房","decorType":"restaurant"},{"id":"node-4834782532","lat":24.977567,"lon":121.54019,"name":"全家便利商店","decorType":"convenience"},{"id":"node-4834782538","lat":24.980566,"lon":121.542063,"name":"哈湯鍋","decorType":"restaurant"},{"id":"node-4834782540","lat":24.98049,"lon":121.54208,"name":"財記圓環肉羹","decorType":"restaurant"},{"id":"node-4834782543","lat":24.980105,"lon":121.542157,"name":"小放牛","decorType":"restaurant"},{"id":"node-4834782544","lat":24.980618,"lon":121.542042,"name":"老王炸烤","decorType":"restaurant"},{"id":"node-4834782545","lat":24.980469,"lon":121.542088,"name":"麵家Sanka","decorType":"restaurant"},{"id":"node-4834782546","lat":24.980475,"lon":121.542628,"name":"玄天上帝壇","decorType":"shrine"},{"id":"node-4834782550","lat":24.980747,"lon":121.547426,"name":"全家便利商店","decorType":"convenience"},{"id":"node-4834782551","lat":24.982086,"lon":121.546409,"name":"美廉社","decorType":"supermarket"},{"id":"node-4834782552","lat":24.984618,"lon":121.54342,"name":"三聖堂","decorType":"shrine"},{"id":"node-4834782553","lat":24.985715,"lon":121.542806,"name":"五府宮","decorType":"shrine"},{"id":"node-4834782732","lat":24.980993,"lon":121.54119,"name":"再生藥局","decorType":"pharmacy"},{"id":"node-4865913835","lat":24.983176,"lon":121.537858,"name":"j-MART佳瑪","decorType":"cosmetics"},{"id":"node-4868081760","lat":24.983476,"lon":121.538851,"name":"玄理宮","decorType":"shrine"},{"id":"node-4937165283","lat":24.991441,"lon":121.540949,"name":"勝悅髮型頭皮饒護館","decorType":"hair_salon"},{"id":"node-5055048128","lat":24.985742,"lon":121.535741,"name":"慈濟醫院站","decorType":"bus_stop"},{"id":"node-5108706539","lat":24.985892,"lon":121.539889,"name":"台北真理堂新店會館","decorType":"shrine"},{"id":"node-5108706579","lat":24.986896,"lon":121.539257,"name":"新店復興郵局","decorType":"post_office"},{"id":"node-5108706580","lat":24.986918,"lon":121.538915,"name":"復興精緻早午餐","decorType":"restaurant"},{"id":"node-5108706581","lat":24.983095,"lon":121.539367,"name":"寶雅","decorType":"pharmacy"},{"id":"node-5108706583","lat":24.982677,"lon":121.539218,"name":"en-suey","decorType":"clothing"},{"id":"node-5108706584","lat":24.983071,"lon":121.538642,"name":"WHY FASHION HAIR SALON","decorType":"hair_salon"},{"id":"node-5108706587","lat":24.983066,"lon":121.53877,"name":"堤亞漢堡","decorType":"restaurant"},{"id":"node-5108706596","lat":24.984532,"lon":121.541253,"name":"彩登造型","decorType":"hair_salon"},{"id":"node-5108709482","lat":24.985444,"lon":121.546645,"name":"永興廟","decorType":"shrine"},{"id":"node-5108709485","lat":24.989795,"lon":121.541017,"name":"草地水缸","decorType":"restaurant"},{"id":"node-5108709498","lat":24.990067,"lon":121.53694,"name":"未命名公園","decorType":"park"},{"id":"node-5108728522","lat":24.990391,"lon":121.54083,"name":"來來時尚美學中心","decorType":"cosmetics"},{"id":"node-5108728526","lat":24.990323,"lon":121.541601,"name":"未命名服飾店","decorType":"clothing"},{"id":"node-5108728527","lat":24.990452,"lon":121.541731,"name":"未命名服飾店","decorType":"clothing"},{"id":"node-5108728528","lat":24.991082,"lon":121.541481,"name":"字秀理髮","decorType":"hair_salon"},{"id":"node-5108728529","lat":24.991,"lon":121.541463,"name":"麗風名店","decorType":"clothing"},{"id":"node-5108728530","lat":24.99102,"lon":121.541418,"name":"巧媛服飾店","decorType":"clothing"},{"id":"node-5137724171","lat":24.982852,"lon":121.542201,"name":"捷運大坪林站(民權路)","decorType":"bus_stop"},{"id":"node-5137724172","lat":24.982987,"lon":121.542564,"name":"捷運大坪林站(民權路)","decorType":"bus_stop"},{"id":"node-5201459725","lat":24.986926,"lon":121.547694,"name":"釋迦田川味牛肉麵","decorType":"restaurant"},{"id":"node-5732975758","lat":24.986015,"lon":121.546179,"name":"頂峰鐵板燒","decorType":"restaurant"},{"id":"node-6006761486","lat":24.986929,"lon":121.547787,"name":"八哥重慶酸辣粉","decorType":"restaurant"},{"id":"node-6006771118","lat":24.986954,"lon":121.547915,"name":"弘爺早餐店","decorType":"restaurant"},{"id":"node-6006831546","lat":24.986935,"lon":121.547824,"name":"呼呼眨等世新店","decorType":"restaurant"},{"id":"node-6024199816","lat":24.986904,"lon":121.547553,"name":"呷尚飽","decorType":"restaurant"},{"id":"node-6024211756","lat":24.986804,"lon":121.541728,"name":"隨意滷味","decorType":"restaurant"},{"id":"node-6024211757","lat":24.986822,"lon":121.541339,"name":"寶慶海鮮熱炒","decorType":"restaurant"},{"id":"node-6024211758","lat":24.986804,"lon":121.54184,"name":"帝王食補 中興店","decorType":"restaurant"},{"id":"node-6024211759","lat":24.985981,"lon":121.541866,"name":"瑞麟美而美","decorType":"burger"},{"id":"node-6024211760","lat":24.985911,"lon":121.541869,"name":"鄭記台南碗粿","decorType":"restaurant"},{"id":"node-6024232291","lat":24.985135,"lon":121.540997,"name":"哈克早餐店","decorType":"restaurant"},{"id":"node-6024241232","lat":24.984589,"lon":121.541539,"name":"原粹蔬食作","decorType":"restaurant"},{"id":"node-6024241233","lat":24.984295,"lon":121.541592,"name":"轉角早午餐","decorType":"restaurant"},{"id":"node-6024241234","lat":24.984223,"lon":121.541288,"name":"鮮堡漢堡","decorType":"restaurant"},{"id":"node-6024250868","lat":24.986973,"lon":121.546486,"name":"牛霸天牛肉麵食堂","decorType":"restaurant"},{"id":"node-6024258533","lat":24.990167,"lon":121.547235,"name":"雞肉飯","decorType":"restaurant"},{"id":"node-6024259059","lat":24.990066,"lon":121.547414,"name":"燴飯","decorType":"restaurant"},{"id":"node-6024333530","lat":24.986969,"lon":121.548043,"name":"未命名咖啡廳","decorType":"cafe"},{"id":"node-6155600434","lat":24.98037,"lon":121.541,"name":"Qburger","decorType":"burger"},{"id":"node-6155600435","lat":24.982764,"lon":121.539496,"name":"JOAN Outlet Mart","decorType":"clothing"},{"id":"node-6155600436","lat":24.982775,"lon":121.539545,"name":"isonsf","decorType":"clothing"},{"id":"node-6155600437","lat":24.98277,"lon":121.53961,"name":"MOMA","decorType":"clothing"},{"id":"node-6155600438","lat":24.984753,"lon":121.540659,"name":"好燒","decorType":"restaurant"},{"id":"node-6155600439","lat":24.97967,"lon":121.544415,"name":"嘉義火雞肉飯鹹米糕","decorType":"restaurant"},{"id":"node-6155600440","lat":24.979649,"lon":121.54442,"name":"士林米粉湯","decorType":"restaurant"},{"id":"node-6155600442","lat":24.979593,"lon":121.544436,"name":"花雕雞","decorType":"restaurant"},{"id":"node-6155600451","lat":24.980949,"lon":121.541525,"name":"首都烘培餐廳","decorType":"restaurant"},{"id":"node-6176758328","lat":24.976349,"lon":121.535215,"name":"8度早午餐店","decorType":"restaurant"},{"id":"node-6180749162","lat":24.986852,"lon":121.547229,"name":"重慶酸辣粉","decorType":"restaurant"},{"id":"node-6191052471","lat":24.989925,"lon":121.546663,"name":"學生餐廳","decorType":"restaurant"},{"id":"node-6578037833","lat":24.985102,"lon":121.546953,"name":"家庭理髮","decorType":"hair_salon"},{"id":"node-6578037835","lat":24.985055,"lon":121.547797,"name":"家和洗衣館","decorType":"laundry"},{"id":"node-6578037836","lat":24.985054,"lon":121.547877,"name":"DESIGN HAIR","decorType":"cosmetics"},{"id":"node-6879098751","lat":24.978338,"lon":121.542744,"name":"未命名郵局","decorType":"post_office"},{"id":"node-6879098752","lat":24.977899,"lon":121.543239,"name":"鞋全家福","decorType":"clothing"},{"id":"node-6924948075","lat":24.982738,"lon":121.543112,"name":"出口 5","decorType":"station"},{"id":"node-7667241063","lat":24.991356,"lon":121.543474,"name":"凱蒂日式精品店","decorType":"clothing"},{"id":"node-7689995446","lat":24.983045,"lon":121.541127,"name":"順捷數位通訊","decorType":"electronics"},{"id":"node-7689995448","lat":24.983055,"lon":121.540933,"name":"源士林粥品","decorType":"restaurant"},{"id":"node-7689995449","lat":24.983056,"lon":121.540897,"name":"維春藥局","decorType":"pharmacy"},{"id":"node-7689995450","lat":24.983055,"lon":121.540841,"name":"歐儷屋精品","decorType":"clothing"},{"id":"node-7689995461","lat":24.98048,"lon":121.54175,"name":"好好味冰火波羅油專賣店","decorType":"bakery"},{"id":"node-7689995464","lat":24.9803,"lon":121.541799,"name":"路易莎","decorType":"cafe"},{"id":"node-7689995471","lat":24.979995,"lon":121.541898,"name":"原崎造型沙龍","decorType":"hair_salon"},{"id":"node-7709735228","lat":24.989216,"lon":121.539243,"name":"阿飛的蝴蝶","decorType":"cafe"},{"id":"node-7709735236","lat":24.990106,"lon":121.541711,"name":"驢爸爸涼麵","decorType":"restaurant"},{"id":"node-7775550226","lat":24.989561,"lon":121.541991,"name":"利庵咖哩","decorType":"restaurant"},{"id":"node-8015864030","lat":24.976549,"lon":121.542575,"name":"阿郎鹹酥雞","decorType":"restaurant"},{"id":"node-8015864031","lat":24.976623,"lon":121.542479,"name":"溫洲大餛飩","decorType":"restaurant"},{"id":"node-8039906979","lat":24.976738,"lon":121.542347,"name":"旺達熱炒","decorType":"restaurant"},{"id":"node-8039906980","lat":24.976576,"lon":121.542544,"name":"幸福咖哩屋","decorType":"restaurant"},{"id":"node-8039906981","lat":24.977108,"lon":121.540552,"name":"我愛買蔬果","decorType":"supermarket"},{"id":"node-8044165102","lat":24.97715,"lon":121.543016,"name":"喜來香牛肉麵","decorType":"restaurant"},{"id":"node-8195481558","lat":24.976573,"lon":121.540407,"name":"微笑生活藥局","decorType":"pharmacy"},{"id":"node-8237614300","lat":24.977063,"lon":121.543022,"name":"cama café","decorType":"cafe"},{"id":"node-8385313739","lat":24.979215,"lon":121.542484,"name":"八方雲集","decorType":"burger"},{"id":"node-8503650298","lat":24.976683,"lon":121.542414,"name":"美而美早餐店","decorType":"restaurant"},{"id":"node-8503650299","lat":24.977924,"lon":121.539923,"name":"東陽鵝肉","decorType":"restaurant"},{"id":"node-8503650300","lat":24.977154,"lon":121.541836,"name":"皇室吉利堡","decorType":"restaurant"},{"id":"node-8567279335","lat":24.991498,"lon":121.542419,"name":"寶雅","decorType":"pharmacy"},{"id":"node-8579299733","lat":24.977855,"lon":121.542515,"name":"池上原味香便當","decorType":"restaurant"},{"id":"node-8614834669","lat":24.983048,"lon":121.542711,"name":"義汁小豬 Steak Pasta","decorType":"restaurant"},{"id":"node-8614834670","lat":24.983047,"lon":121.542734,"name":"炸鷄大獅","decorType":"burger"},{"id":"node-8614834671","lat":24.98305,"lon":121.542689,"name":"通化街米粉湯魯肉飯","decorType":"restaurant"},{"id":"node-8629204830","lat":24.976802,"lon":121.542413,"name":"美而美小吃店","decorType":"restaurant"},{"id":"node-8703880602","lat":24.977061,"lon":121.542132,"name":"幸福鐵板燒","decorType":"restaurant"},{"id":"node-8703880603","lat":24.976993,"lon":121.542217,"name":"攏來食堂","decorType":"restaurant"},{"id":"node-8703880604","lat":24.976972,"lon":121.542096,"name":"老真點心世界","decorType":"restaurant"},{"id":"node-8744232129","lat":24.977418,"lon":121.54037,"name":"福隆月台便當","decorType":"restaurant"},{"id":"node-8793303239","lat":24.977254,"lon":121.540518,"name":"聯美五金生活百貨","decorType":"hardware"},{"id":"node-9004407446","lat":24.976815,"lon":121.542275,"name":"咘咕鍋","decorType":"restaurant"},{"id":"node-9004407447","lat":24.976872,"lon":121.542217,"name":"嘉嘉自助洗衣店","decorType":"laundry"},{"id":"node-9004407448","lat":24.976597,"lon":121.542519,"name":"蝦皮店到店","decorType":"convenience"},{"id":"node-9067402993","lat":24.979894,"lon":121.544339,"name":"黑角","decorType":"restaurant"},{"id":"node-9081911282","lat":24.976919,"lon":121.542155,"name":"叮叮氧食","decorType":"restaurant"},{"id":"node-9083906613","lat":24.976313,"lon":121.537344,"name":"老饕團長","decorType":"restaurant"},{"id":"node-9123841829","lat":24.976734,"lon":121.546111,"name":"定食8","decorType":"restaurant"},{"id":"node-9123841830","lat":24.976908,"lon":121.546036,"name":"大紅袍麻辣燙","decorType":"restaurant"},{"id":"node-9182753605","lat":24.982051,"lon":121.542088,"name":"肉骨潘","decorType":"restaurant"},{"id":"node-9182753606","lat":24.982173,"lon":121.541965,"name":"茉羚","decorType":"restaurant"},{"id":"node-9207746620","lat":24.983055,"lon":121.542305,"name":"四爺麻辣食堂","decorType":"restaurant"},{"id":"node-9207746621","lat":24.982769,"lon":121.542288,"name":"小木屋鬆餅","decorType":"restaurant"},{"id":"node-9207746622","lat":24.982771,"lon":121.542342,"name":"早餐屋","decorType":"restaurant"},{"id":"node-9212197806","lat":24.98092,"lon":121.541588,"name":"台灣大哥大","decorType":"electronics"},{"id":"node-9212197807","lat":24.98046,"lon":121.541658,"name":"鳳城燒臘快餐便當","decorType":"restaurant"},{"id":"node-9221345594","lat":24.98278,"lon":121.542829,"name":"紅葉蛋糕","decorType":"sweetshop"},{"id":"node-9245887069","lat":24.982157,"lon":121.543864,"name":"一鼎魯肉飯","decorType":"restaurant"},{"id":"node-9256386973","lat":24.982784,"lon":121.539352,"name":"宣私房小廚","decorType":"restaurant"},{"id":"node-9327511746","lat":24.981247,"lon":121.54378,"name":"蝦皮店到店","decorType":"convenience"},{"id":"node-9327511750","lat":24.978854,"lon":121.540765,"name":"蝦皮店到店","decorType":"convenience"},{"id":"node-9336850564","lat":24.990079,"lon":121.540895,"name":"五桐號","decorType":"cafe"},{"id":"node-9336850566","lat":24.98995,"lon":121.541695,"name":"萬歲豚骨麻辣屋","decorType":"restaurant"},{"id":"node-9363954221","lat":24.979419,"lon":121.542411,"name":"泰吉城","decorType":"restaurant"},{"id":"node-9363954225","lat":24.979239,"lon":121.542474,"name":"隆鼎御品豬腳","decorType":"restaurant"},{"id":"node-9364032136","lat":24.979079,"lon":121.543618,"name":"寶強路口","decorType":"bus_stop"},{"id":"node-9376359557","lat":24.982793,"lon":121.541793,"name":"一手私藏世界紅茶","decorType":"cafe"},{"id":"node-9391261118","lat":24.98594,"lon":121.540794,"name":"蝦皮店到店","decorType":"convenience"},{"id":"node-9401545425","lat":24.987001,"lon":121.54534,"name":"蝦皮店到店","decorType":"convenience"},{"id":"node-9410315995","lat":24.98201,"lon":121.541667,"name":"金美藥局","decorType":"pharmacy"},{"id":"node-9410315998","lat":24.981596,"lon":121.541757,"name":"世明藥局","decorType":"pharmacy"},{"id":"node-9410316000","lat":24.981482,"lon":121.541788,"name":"里仁","decorType":"supermarket"},{"id":"node-9415461376","lat":24.980659,"lon":121.542029,"name":"帕米義麵屋","decorType":"restaurant"},{"id":"node-9438416443","lat":24.982577,"lon":121.54322,"name":"中興早餐店","decorType":"restaurant"},{"id":"node-9534929171","lat":24.979743,"lon":121.536339,"name":"蝦皮店到店","decorType":"convenience"},{"id":"node-9613222163","lat":24.98232,"lon":121.54128,"name":"福勝亭","decorType":"restaurant"},{"id":"node-9673261495","lat":24.982076,"lon":121.537577,"name":"蝦皮店到店","decorType":"convenience"},{"id":"node-9709227707","lat":24.980338,"lon":121.5414,"name":"麥味登","decorType":"restaurant"},{"id":"node-9734006989","lat":24.980203,"lon":121.540753,"name":"坤記北港焿","decorType":"restaurant"},{"id":"node-9734006990","lat":24.980424,"lon":121.54127,"name":"全家便利商店","decorType":"convenience"},{"id":"node-9736334992","lat":24.981398,"lon":121.542246,"name":"寶安越南美食坊","decorType":"restaurant"},{"id":"node-9965993898","lat":24.978926,"lon":121.542038,"name":"好享宴小館","decorType":"restaurant"},{"id":"node-9965993899","lat":24.978901,"lon":121.54175,"name":"全家便利商店","decorType":"convenience"},{"id":"node-9965993900","lat":24.978903,"lon":121.541054,"name":"山東水餃王","decorType":"restaurant"},{"id":"node-10076731003","lat":24.983068,"lon":121.539742,"name":"hazukido八月堂概念店","decorType":"restaurant"},{"id":"node-10076731004","lat":24.983064,"lon":121.539703,"name":"質菲雅國際美容機構","decorType":"hair_salon"},{"id":"node-10123697288","lat":24.980398,"lon":121.541462,"name":"老楊蚵仔麵線","decorType":"restaurant"},{"id":"node-10178060331","lat":24.980503,"lon":121.541459,"name":"兄弟麵館","decorType":"restaurant"},{"id":"node-10249982583","lat":24.98172,"lon":121.537548,"name":"池上吾家木盒便當","decorType":"restaurant"},{"id":"node-10249982584","lat":24.981787,"lon":121.537757,"name":"麥味登","decorType":"restaurant"},{"id":"node-10249982585","lat":24.983425,"lon":121.537619,"name":"鮮五丼","decorType":"restaurant"},{"id":"node-10249982586","lat":24.983498,"lon":121.537581,"name":"三商巧福","decorType":"restaurant"},{"id":"node-10914461716","lat":24.978581,"lon":121.542774,"name":"獵人谷之夢","decorType":"supermarket"},{"id":"node-11015800941","lat":24.983286,"lon":121.540315,"name":"三媽臭臭鍋","decorType":"restaurant"},{"id":"node-11131466358","lat":24.983044,"lon":121.540223,"name":"莊家班麻油雞","decorType":"restaurant"},{"id":"node-11198785937","lat":24.983192,"lon":121.536803,"name":"未命名餐廳","decorType":"restaurant"},{"id":"node-11361801227","lat":24.984674,"lon":121.54277,"name":"大呼過癮","decorType":"restaurant"},{"id":"node-11368558931","lat":24.983044,"lon":121.54255,"name":"康裕藥局","decorType":"pharmacy"},{"id":"node-11392563202","lat":24.989073,"lon":121.541563,"name":"禾牧麵食料理","decorType":"restaurant"},{"id":"node-11392563203","lat":24.990671,"lon":121.541862,"name":"燈籠滷味(創始店)","decorType":"restaurant"},{"id":"node-11517930575","lat":24.980306,"lon":121.541277,"name":"瑪岌牛肉麵","decorType":"restaurant"},{"id":"node-11556627094","lat":24.982817,"lon":121.541645,"name":"大坪林","decorType":"station"},{"id":"node-11882673549","lat":24.977937,"lon":121.547125,"name":"TOK盡興食光","decorType":"restaurant"},{"id":"node-11934162576","lat":24.977125,"lon":121.543018,"name":"古味小吃店","decorType":"restaurant"},{"id":"node-11934162577","lat":24.977096,"lon":121.54302,"name":"起家雞","decorType":"restaurant"},{"id":"node-11965836400","lat":24.977769,"lon":121.546668,"name":"熱浪島南洋蔬食茶堂","decorType":"restaurant"},{"id":"node-12031091097","lat":24.983048,"lon":121.542769,"name":"深夜未歸","decorType":"restaurant"},{"id":"node-12071592268","lat":24.980415,"lon":121.541774,"name":"以串之名","decorType":"restaurant"},{"id":"node-12185478402","lat":24.981667,"lon":121.538239,"name":"功夫豬","decorType":"restaurant"},{"id":"node-12254079935","lat":24.978162,"lon":121.542456,"name":"Boulevard Cafe","decorType":"restaurant"},{"id":"node-12331148901","lat":24.979869,"lon":121.540229,"name":"日光蔬苑","decorType":"restaurant"},{"id":"node-12397792627","lat":24.981649,"lon":121.541396,"name":"迷客夏","decorType":"cafe"},{"id":"node-12429486544","lat":24.977991,"lon":121.546881,"name":"誠品書店","decorType":"library"},{"id":"node-12722696203","lat":24.980933,"lon":121.542376,"name":"佳香豆漿","decorType":"restaurant"},{"id":"node-12722746504","lat":24.98305,"lon":121.542754,"name":"TIANA HAIR SALON","decorType":"hair_salon"},{"id":"node-12722746505","lat":24.983044,"lon":121.542583,"name":"玉如內衣","decorType":"clothing"},{"id":"node-12806074084","lat":24.979809,"lon":121.542285,"name":"悅食堂","decorType":"restaurant"},{"id":"node-12855279101","lat":24.983506,"lon":121.54189,"name":"禾豐安麵食館","decorType":"restaurant"},{"id":"node-12855388701","lat":24.981704,"lon":121.540652,"name":"四月羊咖啡館","decorType":"cafe"},{"id":"node-12857531201","lat":24.98045,"lon":121.541393,"name":"楽坡BonBox","decorType":"restaurant"},{"id":"node-13076831855","lat":24.983141,"lon":121.541953,"name":"阿煌炭烤雞排","decorType":"restaurant"},{"id":"node-13114453786","lat":24.976563,"lon":121.542561,"name":"客家燒仙草九份芋圓","decorType":"restaurant"},{"id":"node-13242738859","lat":24.99163,"lon":121.541466,"name":"北投紅茶","decorType":"cafe"},{"id":"node-13242738860","lat":24.991695,"lon":121.541484,"name":"鄭記炭烤世家","decorType":"restaurant"},{"id":"node-13242738862","lat":24.989913,"lon":121.541344,"name":"巷仔內米粉湯","decorType":"restaurant"},{"id":"node-13289012559","lat":24.980517,"lon":121.541495,"name":"大豐藥局","decorType":"pharmacy"},{"id":"node-13290646952","lat":24.983088,"lon":121.54048,"name":"爭鮮","decorType":"restaurant"},{"id":"node-13290646953","lat":24.983118,"lon":121.540422,"name":"艾波索","decorType":"sweetshop"},{"id":"node-13308275960","lat":24.980293,"lon":121.54124,"name":"樂昀牛排館","decorType":"restaurant"},{"id":"node-13308275964","lat":24.980357,"lon":121.541072,"name":"我家自助餐","decorType":"burger"},{"id":"node-13308275965","lat":24.980437,"lon":121.541306,"name":"禾粲食光健康餐盒","decorType":"restaurant"},{"id":"node-13308275966","lat":24.98045,"lon":121.541344,"name":"可愛村便當","decorType":"restaurant"},{"id":"node-13329740738","lat":24.991141,"lon":121.542264,"name":"麗蓉服飾","decorType":"clothing"},{"id":"node-13329740740","lat":24.991286,"lon":121.542259,"name":"福隆月台便當","decorType":"restaurant"},{"id":"node-13329740741","lat":24.990523,"lon":121.541942,"name":"華歌爾","decorType":"clothing"},{"id":"node-13351199250","lat":24.980221,"lon":121.540791,"name":"林里南洋風味小吃","decorType":"restaurant"},{"id":"node-13410524584","lat":24.982624,"lon":121.542058,"name":"千壽司","decorType":"restaurant"},{"id":"way-25878619","lat":24.986157,"lon":121.540321,"name":"鳴遠橋","decorType":"bridge"},{"id":"way-29131381","lat":24.986753,"lon":121.543917,"name":"景美溪橋","decorType":"bridge"},{"id":"way-106370441","lat":24.976413,"lon":121.546821,"name":"中興陸橋","decorType":"bridge"},{"id":"way-106370450","lat":24.976472,"lon":121.546944,"name":"中興陸橋","decorType":"bridge"},{"id":"way-106373399","lat":24.984913,"lon":121.541567,"name":"瑠公圳","decorType":"waterside"},{"id":"way-106374141","lat":24.991689,"lon":121.542476,"name":"景美溪","decorType":"waterside"},{"id":"way-106484925","lat":24.987815,"lon":121.540836,"name":"景美橋","decorType":"bridge"},{"id":"way-111484727","lat":24.986686,"lon":121.543916,"name":"景美溪橋","decorType":"bridge"},{"id":"way-150872522","lat":24.987725,"lon":121.539856,"name":"北新橋","decorType":"bridge"},{"id":"way-150872523","lat":24.987941,"lon":121.539696,"name":"北新橋","decorType":"bridge"},{"id":"way-150901781","lat":24.989223,"lon":121.539654,"name":"羅斯福路六段","decorType":"bridge"},{"id":"way-150901782","lat":24.986126,"lon":121.540214,"name":"鳴遠橋","decorType":"bridge"},{"id":"way-193048630","lat":24.9766,"lon":121.538499,"name":"交通公園","decorType":"park"},{"id":"way-197899760","lat":24.987106,"lon":121.539875,"name":"北新橋","decorType":"bridge"},{"id":"way-198159388","lat":24.982877,"lon":121.541961,"name":"未命名公車站","decorType":"bus_stop"},{"id":"way-213539116","lat":24.979411,"lon":121.542161,"name":"瑠公圳","decorType":"waterside"},{"id":"way-224498220","lat":24.990173,"lon":121.545168,"name":"世新大學圖書館","decorType":"university"},{"id":"way-244708179","lat":24.989555,"lon":121.54743,"name":"大禮堂","decorType":"university"},{"id":"way-245404436","lat":24.989797,"lon":121.546258,"name":"舍我樓","decorType":"university"},{"id":"way-245407007","lat":24.98862,"lon":121.544352,"name":"世界大廈","decorType":"university"},{"id":"way-245407011","lat":24.988519,"lon":121.544325,"name":"生活之窗","decorType":"university"},{"id":"way-245407012","lat":24.989566,"lon":121.545,"name":"行政大樓","decorType":"university"},{"id":"way-245407013","lat":24.989338,"lon":121.544842,"name":"世新大學郵局","decorType":"post_office"},{"id":"way-245407457","lat":24.988899,"lon":121.544763,"name":"翠谷餐廳","decorType":"university"},{"id":"way-245407459","lat":24.989334,"lon":121.545719,"name":"廣播電視電影教學中心","decorType":"university"},{"id":"way-245407592","lat":24.989948,"lon":121.545302,"name":"第一閱覽室","decorType":"university"},{"id":"way-245407593","lat":24.989824,"lon":121.545384,"name":"通識大樓","decorType":"university"},{"id":"way-245410602","lat":24.988828,"lon":121.543576,"name":"新聞大廈","decorType":"university"},{"id":"way-245411850","lat":24.98926,"lon":121.548096,"name":"世新大學LVS智能攝製基地","decorType":"university"},{"id":"way-245422655","lat":24.987321,"lon":121.547999,"name":"世新大學管理學院大樓","decorType":"university"},{"id":"way-245576469","lat":24.990616,"lon":121.545806,"name":"真修寺","decorType":"shrine"},{"id":"way-248614424","lat":24.976479,"lon":121.546154,"name":"家樂福","decorType":"supermarket"},{"id":"way-316477847","lat":24.977175,"lon":121.54251,"name":"新店郵局","decorType":"post_office"},{"id":"way-325015197","lat":24.9894,"lon":121.540175,"name":"未命名公園","decorType":"park"},{"id":"way-334128969","lat":24.989241,"lon":121.539549,"name":"羅斯福路六段","decorType":"bridge"},{"id":"way-347457091","lat":24.991526,"lon":121.54196,"name":"景美進興宮","decorType":"shrine"},{"id":"way-353782067","lat":24.988418,"lon":121.539803,"name":"未命名橋樑","decorType":"bridge"},{"id":"way-353782069","lat":24.990589,"lon":121.536783,"name":"未命名橋樑","decorType":"bridge"},{"id":"way-353782072","lat":24.988432,"lon":121.539799,"name":"未命名橋樑","decorType":"bridge"},{"id":"way-353782073","lat":24.990593,"lon":121.536806,"name":"未命名橋樑","decorType":"bridge"},{"id":"way-353782074","lat":24.990621,"lon":121.536801,"name":"未命名橋樑","decorType":"bridge"},{"id":"way-353782075","lat":24.988425,"lon":121.539768,"name":"未命名橋樑","decorType":"bridge"},{"id":"way-355514668","lat":24.981551,"lon":121.538595,"name":"安盛商旅","decorType":"hotel"},{"id":"way-358671225","lat":24.989122,"lon":121.542689,"name":"石門宮盤古帝王廟","decorType":"shrine"},{"id":"way-359992450","lat":24.985314,"lon":121.545277,"name":"木柵河濱公園","decorType":"park"},{"id":"way-378643838","lat":24.979224,"lon":121.547297,"name":"未命名水邊","decorType":"waterside"},{"id":"way-398005534","lat":24.991651,"lon":121.539507,"name":"聖家會","decorType":"shrine"},{"id":"way-400804149","lat":24.986102,"lon":121.536835,"name":"未命名公園","decorType":"park"},{"id":"way-420661162","lat":24.990622,"lon":121.546104,"name":"真修寺","decorType":"shrine"},{"id":"way-421669211","lat":24.977304,"lon":121.541763,"name":"明德橋","decorType":"bridge"},{"id":"way-422789082","lat":24.977715,"lon":121.541906,"name":"未命名橋樑","decorType":"bridge"},{"id":"way-440646829","lat":24.984633,"lon":121.535824,"name":"新店靜思堂","decorType":"shrine"},{"id":"way-440652120","lat":24.987095,"lon":121.541189,"name":"瑠公圳","decorType":"waterside"},{"id":"way-444108524","lat":24.982089,"lon":121.547597,"name":"未命名水邊","decorType":"waterside"},{"id":"way-444569951","lat":24.991627,"lon":121.535525,"name":"未命名橋樑","decorType":"bridge"},{"id":"way-444569953","lat":24.991574,"lon":121.535648,"name":"未命名橋樑","decorType":"bridge"},{"id":"way-444569959","lat":24.991625,"lon":121.535614,"name":"未命名橋樑","decorType":"bridge"},{"id":"way-444595736","lat":24.987728,"lon":121.53861,"name":"未命名水邊","decorType":"waterside"},{"id":"way-447197594","lat":24.982289,"lon":121.542844,"name":"新店仲信會館","decorType":"hotel"},{"id":"way-463040214","lat":24.976428,"lon":121.541533,"name":"未命名橋樑","decorType":"bridge"},{"id":"way-469939706","lat":24.976702,"lon":121.54154,"name":"未命名公園","decorType":"park"},{"id":"way-494873628","lat":24.984693,"lon":121.544034,"name":"未命名橋樑","decorType":"bridge"},{"id":"way-494873629","lat":24.984753,"lon":121.544006,"name":"未命名橋樑","decorType":"bridge"},{"id":"way-494873630","lat":24.984731,"lon":121.544003,"name":"未命名橋樑","decorType":"bridge"},{"id":"way-494873638","lat":24.980961,"lon":121.542164,"name":"瑠公圳","decorType":"waterside"},{"id":"way-494873639","lat":24.98245,"lon":121.541952,"name":"瑠公圳","decorType":"waterside"},{"id":"way-495735149","lat":24.977571,"lon":121.544206,"name":"裕隆納智捷籃球隊體育館","decorType":"stadium"},{"id":"way-496700000","lat":24.986908,"lon":121.544313,"name":"未命名橋樑","decorType":"bridge"},{"id":"way-497993248","lat":24.987042,"lon":121.545062,"name":"未命名橋樑","decorType":"bridge"},{"id":"way-497993251","lat":24.988296,"lon":121.544243,"name":"未命名橋樑","decorType":"bridge"},{"id":"way-497993912","lat":24.988205,"lon":121.54125,"name":"未命名橋樑","decorType":"bridge"},{"id":"way-512644447","lat":24.987545,"lon":121.547734,"name":"全媒體大樓","decorType":"university"},{"id":"way-512644453","lat":24.986917,"lon":121.545864,"name":"溝子口福德宮","decorType":"shrine"},{"id":"way-519054917","lat":24.985534,"lon":121.53624,"name":"未命名水邊","decorType":"waterside"},{"id":"way-519102838","lat":24.985178,"lon":121.536421,"name":"未命名森林","decorType":"forest"},{"id":"way-519820951","lat":24.985253,"lon":121.536642,"name":"未命名水邊","decorType":"waterside"},{"id":"way-519820952","lat":24.985267,"lon":121.536635,"name":"未命名橋樑","decorType":"bridge"},{"id":"way-519861206","lat":24.985384,"lon":121.535315,"name":"未命名水邊","decorType":"waterside"},{"id":"way-519861208","lat":24.985421,"lon":121.5353,"name":"未命名橋樑","decorType":"bridge"},{"id":"way-545991965","lat":24.976352,"lon":121.53667,"name":"未命名公園","decorType":"park"},{"id":"way-546331797","lat":24.985277,"lon":121.547273,"name":"35巷口公園","decorType":"park"},{"id":"way-547540381","lat":24.976353,"lon":121.536333,"name":"未命名公園","decorType":"park"},{"id":"way-631022141","lat":24.986345,"lon":121.545073,"name":"景美溪右岸自行車道","decorType":"bridge"},{"id":"way-631022144","lat":24.986261,"lon":121.544175,"name":"未命名橋樑","decorType":"bridge"},{"id":"way-631022147","lat":24.987819,"lon":121.540773,"name":"景美橋自行車道","decorType":"bridge"},{"id":"way-631022151","lat":24.987413,"lon":121.541009,"name":"未命名橋樑","decorType":"bridge"},{"id":"way-631603752","lat":24.987415,"lon":121.540708,"name":"未命名橋樑","decorType":"bridge"},{"id":"way-631603753","lat":24.987437,"lon":121.540602,"name":"未命名橋樑","decorType":"bridge"},{"id":"way-631603754","lat":24.987434,"lon":121.540534,"name":"未命名橋樑","decorType":"bridge"},{"id":"way-631603755","lat":24.987431,"lon":121.540447,"name":"未命名橋樑","decorType":"bridge"},{"id":"way-637107002","lat":24.986842,"lon":121.542175,"name":"珍愛小吃鋪","decorType":"restaurant"},{"id":"way-674885753","lat":24.989443,"lon":121.535574,"name":"未命名橋樑","decorType":"bridge"},{"id":"way-674885755","lat":24.989454,"lon":121.53562,"name":"未命名橋樑","decorType":"bridge"},{"id":"way-674885756","lat":24.989383,"lon":121.535596,"name":"未命名橋樑","decorType":"bridge"},{"id":"way-677024330","lat":24.986452,"lon":121.545586,"name":"未命名水邊","decorType":"waterside"},{"id":"way-684879982","lat":24.989004,"lon":121.542516,"name":"竹林義應公廟","decorType":"shrine"},{"id":"way-684879984","lat":24.990499,"lon":121.543901,"name":"紫範宮","decorType":"shrine"},{"id":"way-700487289","lat":24.982403,"lon":121.543442,"name":"未命名森林","decorType":"forest"},{"id":"way-741034948","lat":24.98203,"lon":121.542883,"name":"聖母公園","decorType":"park"},{"id":"way-741034949","lat":24.982291,"lon":121.542587,"name":"大坪林聖三堂","decorType":"shrine"},{"id":"way-760861685","lat":24.987343,"lon":121.540755,"name":"景美溪右岸自行車道","decorType":"bridge"},{"id":"way-760861687","lat":24.987289,"lon":121.541149,"name":"未命名橋樑","decorType":"bridge"},{"id":"way-770953638","lat":24.986729,"lon":121.543944,"name":"景美溪橋","decorType":"bridge"},{"id":"way-770953639","lat":24.98782,"lon":121.540827,"name":"景美橋","decorType":"bridge"},{"id":"way-770953640","lat":24.986119,"lon":121.540261,"name":"鳴遠橋","decorType":"bridge"},{"id":"way-770953641","lat":24.988415,"lon":121.539756,"name":"北新橋","decorType":"bridge"},{"id":"way-825744372","lat":24.991877,"lon":121.544058,"name":"未命名橋樑","decorType":"bridge"},{"id":"way-849084629","lat":24.987705,"lon":121.541106,"name":"瑠公圳","decorType":"waterside"},{"id":"way-849084630","lat":24.987462,"lon":121.541125,"name":"瑠公圳","decorType":"waterside"},{"id":"way-1039534182","lat":24.983131,"lon":121.546118,"name":"未命名橋樑","decorType":"bridge"},{"id":"way-1039534183","lat":24.983137,"lon":121.546146,"name":"未命名橋樑","decorType":"bridge"},{"id":"way-1039534184","lat":24.983152,"lon":121.546118,"name":"未命名橋樑","decorType":"bridge"},{"id":"way-1039534185","lat":24.983152,"lon":121.546089,"name":"未命名橋樑","decorType":"bridge"},{"id":"way-1039534186","lat":24.983146,"lon":121.546106,"name":"未命名橋樑","decorType":"bridge"},{"id":"way-1039534193","lat":24.985153,"lon":121.544949,"name":"未命名公園","decorType":"park"},{"id":"way-1039534207","lat":24.983143,"lon":121.546235,"name":"景美溪左岸自行車道","decorType":"bridge"},{"id":"way-1039864809","lat":24.986901,"lon":121.544311,"name":"未命名橋樑","decorType":"bridge"},{"id":"way-1039864810","lat":24.986875,"lon":121.544308,"name":"未命名橋樑","decorType":"bridge"},{"id":"way-1039864812","lat":24.986827,"lon":121.544786,"name":"未命名橋樑","decorType":"bridge"},{"id":"way-1039864813","lat":24.986651,"lon":121.544782,"name":"未命名橋樑","decorType":"bridge"},{"id":"way-1041888956","lat":24.987574,"lon":121.538406,"name":"未命名橋樑","decorType":"bridge"},{"id":"way-1041888957","lat":24.987569,"lon":121.538453,"name":"未命名橋樑","decorType":"bridge"},{"id":"way-1041888958","lat":24.987506,"lon":121.541874,"name":"未命名橋樑","decorType":"bridge"},{"id":"way-1041888959","lat":24.98752,"lon":121.541913,"name":"未命名橋樑","decorType":"bridge"},{"id":"way-1041888960","lat":24.987527,"lon":121.541873,"name":"未命名橋樑","decorType":"bridge"},{"id":"way-1041888961","lat":24.98759,"lon":121.538411,"name":"未命名橋樑","decorType":"bridge"},{"id":"way-1041888963","lat":24.987572,"lon":121.538567,"name":"景美溪左岸大鵬華城堤外便道至鳴遠橋自行車道","decorType":"bridge"},{"id":"way-1041888965","lat":24.987589,"lon":121.542041,"name":"景美溪左岸自行車道","decorType":"bridge"},{"id":"way-1041888976","lat":24.987815,"lon":121.540895,"name":"未命名橋樑","decorType":"bridge"},{"id":"way-1044136313","lat":24.987627,"lon":121.540157,"name":"未命名橋樑","decorType":"bridge"},{"id":"way-1044136314","lat":24.987637,"lon":121.53994,"name":"未命名橋樑","decorType":"bridge"},{"id":"way-1054531296","lat":24.982827,"lon":121.541353,"name":"未命名公車站","decorType":"bus_stop"},{"id":"way-1126817043","lat":24.987913,"lon":121.547323,"name":"未命名公園","decorType":"park"},{"id":"way-1307916705","lat":24.977309,"lon":121.544736,"name":"寶徠公園","decorType":"park"},{"id":"way-1307919376","lat":24.977849,"lon":121.544376,"name":"未命名水邊","decorType":"waterside"},{"id":"way-1307919377","lat":24.97807,"lon":121.544497,"name":"未命名水邊","decorType":"waterside"},{"id":"way-1307986570","lat":24.979306,"lon":121.545982,"name":"未命名水邊","decorType":"waterside"},{"id":"way-1314168021","lat":24.987772,"lon":121.540765,"name":"未命名橋樑","decorType":"bridge"},{"id":"way-1328588750","lat":24.991696,"lon":121.544157,"name":"未命名水邊","decorType":"waterside"},{"id":"way-1371853787","lat":24.9833,"lon":121.544802,"name":"和興路44巷跨景美溪人行景觀橋","decorType":"bridge"},{"id":"way-1371853790","lat":24.983678,"lon":121.545252,"name":"和興路44巷跨景美溪人行景觀橋","decorType":"bridge"},{"id":"way-1387166498","lat":24.986695,"lon":121.545373,"name":"溝子口萬善堂","decorType":"shrine"}]}