{"bbox":{"south":25.038731,"north":25.054338,"west":121.56125,"east":121.574281},"pois":[{"id":"way-313680581","lat":25.047362,"lon":121.561685,"name":"復盛公園","decorType":"park"},{"id":"way-313680586","lat":25.047748,"lon":121.561359,"name":"臺北偶戲館","decorType":"art_gallery"},{"id":"node-569951808","lat":25.040935,"lon":121.567031,"name":"捷運市政府站","decorType":"bus_stop"},{"id":"node-1501340085","lat":25.040786,"lon":121.564963,"name":"市府轉運站","decorType":"bus_stop"},{"id":"node-1501340090","lat":25.041293,"lon":121.566704,"name":"萊爾富","decorType":"convenience"},{"id":"node-1501340092","lat":25.040803,"lon":121.565136,"name":"捷運市政府站2號出口","decorType":"station"},{"id":"node-1678965162","lat":25.040492,"lon":121.565746,"name":"台北W飯店","decorType":"hotel"},{"id":"node-1828141715","lat":25.044643,"lon":121.566392,"name":"松山高中(基隆路)","decorType":"bus_stop"},{"id":"node-1926383150","lat":25.041198,"lon":121.573697,"name":"愛買","decorType":"supermarket"},{"id":"node-2132228031","lat":25.041255,"lon":121.568316,"name":"小樂天餃子館","decorType":"restaurant"},{"id":"node-2132228052","lat":25.041257,"lon":121.567191,"name":"捷運市政府站4號出口","decorType":"station"},{"id":"node-2309011893","lat":25.040971,"lon":121.565074,"name":"捷運市政府站","decorType":"bus_stop"},{"id":"node-2309134854","lat":25.040829,"lon":121.572462,"name":"市立工農","decorType":"bus_stop"},{"id":"node-2310689471","lat":25.04106,"lon":121.572178,"name":"市立工農","decorType":"bus_stop"},{"id":"node-2323956870","lat":25.0396,"lon":121.568323,"name":"消防局(松仁)","decorType":"bus_stop"},{"id":"node-2375864486","lat":25.04108,"lon":121.562356,"name":"聯合報","decorType":"bus_stop"},{"id":"node-2376924767","lat":25.043513,"lon":121.561618,"name":"gonna+","decorType":"restaurant"},{"id":"node-2376988724","lat":25.042002,"lon":121.56282,"name":"未命名麵包店","decorType":"bakery"},{"id":"node-2377138792","lat":25.041799,"lon":121.563748,"name":"7-Eleven","decorType":"convenience"},{"id":"node-2377138833","lat":25.040836,"lon":121.562479,"name":"7-Eleven","decorType":"convenience"},{"id":"node-2421595465","lat":25.041219,"lon":121.566559,"name":"捷運市政府站","decorType":"bus_stop"},{"id":"node-2421595466","lat":25.041309,"lon":121.563007,"name":"聯合報","decorType":"bus_stop"},{"id":"node-2495272370","lat":25.052348,"lon":121.570406,"name":"南松山(塔悠)","decorType":"bus_stop"},{"id":"node-2517658797","lat":25.051243,"lon":121.564871,"name":"南京公寓(捷運南京三民)","decorType":"bus_stop"},{"id":"node-2517658798","lat":25.051555,"lon":121.564923,"name":"南京公寓(捷運南京三民)","decorType":"bus_stop"},{"id":"node-2517658799","lat":25.051098,"lon":121.569129,"name":"南松山(南京)","decorType":"bus_stop"},{"id":"node-2517658800","lat":25.051469,"lon":121.569008,"name":"南松山 (南京)","decorType":"bus_stop"},{"id":"node-2517658904","lat":25.049868,"lon":121.573806,"name":"松山農會","decorType":"bus_stop"},{"id":"node-2517659489","lat":25.050435,"lon":121.571454,"name":"饒河街觀光夜市 (塔悠)","decorType":"bus_stop"},{"id":"node-2517659492","lat":25.050439,"lon":121.571939,"name":"饒河街觀光夜市 (塔悠)","decorType":"bus_stop"},{"id":"node-2524297016","lat":25.049755,"lon":121.572474,"name":"全家便利商店","decorType":"convenience"},{"id":"node-2524398259","lat":25.049757,"lon":121.573493,"name":"小雅HOTEL","decorType":"hotel"},{"id":"node-2528089318","lat":25.048859,"lon":121.563678,"name":"八德東寧路口","decorType":"bus_stop"},{"id":"node-2528089319","lat":25.048692,"lon":121.563693,"name":"八德東寧路口","decorType":"bus_stop"},{"id":"node-2528089320","lat":25.048764,"lon":121.564591,"name":"八德東寧路口","decorType":"bus_stop"},{"id":"node-2528089321","lat":25.049166,"lon":121.566679,"name":"新聚里","decorType":"bus_stop"},{"id":"node-2528089322","lat":25.049018,"lon":121.56688,"name":"新聚里","decorType":"bus_stop"},{"id":"node-2528089323","lat":25.049354,"lon":121.568429,"name":"基隆路口","decorType":"bus_stop"},{"id":"node-2528089324","lat":25.049949,"lon":121.57145,"name":"饒河街觀光夜市(八德)","decorType":"bus_stop"},{"id":"node-2528089325","lat":25.049803,"lon":121.571454,"name":"饒河街觀光夜市(八德)","decorType":"bus_stop"},{"id":"node-2572568051","lat":25.049452,"lon":121.569985,"name":"金夜賓館","decorType":"hotel"},{"id":"node-2572568052","lat":25.049509,"lon":121.570085,"name":"松山聚福廟","decorType":"shrine"},{"id":"node-2585279037","lat":25.044217,"lon":121.566506,"name":"松山高中 (基隆路)","decorType":"bus_stop"},{"id":"node-2586999958","lat":25.04635,"lon":121.56679,"name":"東興路","decorType":"bus_stop"},{"id":"node-2586999959","lat":25.046471,"lon":121.566566,"name":"東興路","decorType":"bus_stop"},{"id":"node-2586999960","lat":25.043485,"lon":121.56756,"name":"松山高中(松隆)","decorType":"bus_stop"},{"id":"node-2586999961","lat":25.043775,"lon":121.567567,"name":"松山高中(松隆)","decorType":"bus_stop"},{"id":"node-2586999963","lat":25.045795,"lon":121.569717,"name":"興雅國小","decorType":"bus_stop"},{"id":"node-2617568610","lat":25.040402,"lon":121.563199,"name":"7-Eleven","decorType":"convenience"},{"id":"node-2656074182","lat":25.052374,"lon":121.566114,"name":"東引小吃","decorType":"restaurant"},{"id":"node-2656074185","lat":25.052055,"lon":121.566232,"name":"健康人生藥局","decorType":"pharmacy"},{"id":"node-2656074186","lat":25.052375,"lon":121.56396,"name":"7-Eleven","decorType":"convenience"},{"id":"node-2656074187","lat":25.051534,"lon":121.567071,"name":"雅柏汽車旅館","decorType":"hotel"},{"id":"node-2656074188","lat":25.051558,"lon":121.566793,"name":"7-Eleven","decorType":"convenience"},{"id":"node-2656074189","lat":25.051154,"lon":121.56483,"name":"百八漁場","decorType":"restaurant"},{"id":"node-2656074190","lat":25.051257,"lon":121.563429,"name":"50嵐","decorType":"cafe"},{"id":"node-2656074191","lat":25.051236,"lon":121.563056,"name":"麥當勞","decorType":"burger"},{"id":"node-2656074192","lat":25.051226,"lon":121.563183,"name":"肯德基","decorType":"burger"},{"id":"node-2656074193","lat":25.050613,"lon":121.562621,"name":"摩斯漢堡","decorType":"burger"},{"id":"node-2656074194","lat":25.051235,"lon":121.561677,"name":"佳德糕餅","decorType":"bakery"},{"id":"node-2656074195","lat":25.050811,"lon":121.566409,"name":"金山客家小館","decorType":"restaurant"},{"id":"node-2656074196","lat":25.051565,"lon":121.565899,"name":"千翔食品","decorType":"restaurant"},{"id":"node-2656074197","lat":25.051536,"lon":121.566446,"name":"屈臣氏","decorType":"pharmacy"},{"id":"node-2656074198","lat":25.051225,"lon":121.562806,"name":"康是美","decorType":"pharmacy"},{"id":"node-2713524342","lat":25.053147,"lon":121.563936,"name":"西松國小","decorType":"bus_stop"},{"id":"node-2713524343","lat":25.052802,"lon":121.563717,"name":"西松國小","decorType":"bus_stop"},{"id":"node-2713536625","lat":25.05017,"lon":121.565282,"name":"東興路一","decorType":"bus_stop"},{"id":"node-2713536626","lat":25.049893,"lon":121.565519,"name":"東興路一","decorType":"bus_stop"},{"id":"node-2825607578","lat":25.041248,"lon":121.568573,"name":"新村站著吃烤肉","decorType":"restaurant"},{"id":"node-2825607579","lat":25.04125,"lon":121.567582,"name":"台北牛乳大王","decorType":"restaurant"},{"id":"node-2947161054","lat":25.049735,"lon":121.566246,"name":"Breakfast Restaurant","decorType":"restaurant"},{"id":"node-2947161055","lat":25.049824,"lon":121.566041,"name":"Benson's Sushi Restaurant","decorType":"restaurant"},{"id":"node-2947161056","lat":25.052467,"lon":121.566465,"name":"Xiao Mama Boiled Dumplings","decorType":"restaurant"},{"id":"node-2948790710","lat":25.051152,"lon":121.564968,"name":"法豆鮮焙咖啡","decorType":"cafe"},{"id":"node-2951335369","lat":25.04965,"lon":121.56556,"name":"米與多蜜","decorType":"restaurant"},{"id":"node-2954087009","lat":25.045479,"lon":121.569838,"name":"華品川菜館","decorType":"restaurant"},{"id":"node-2954089276","lat":25.045495,"lon":121.569004,"name":"7-Eleven","decorType":"convenience"},{"id":"node-2962739999","lat":25.043455,"lon":121.56743,"name":"全聯福利中心","decorType":"supermarket"},{"id":"node-2962740496","lat":25.043138,"lon":121.565875,"name":"7-Eleven","decorType":"convenience"},{"id":"node-2962740700","lat":25.045421,"lon":121.571192,"name":"永吉郵局","decorType":"post_office"},{"id":"node-2963985747","lat":25.047305,"lon":121.566503,"name":"7-Eleven","decorType":"convenience"},{"id":"node-2965491625","lat":25.047072,"lon":121.566661,"name":"星巴克","decorType":"cafe"},{"id":"node-2965491626","lat":25.047141,"lon":121.56659,"name":"Mister Donut","decorType":"burger"},{"id":"node-2965491627","lat":25.047428,"lon":121.566567,"name":"小阿姨複合式餐飲","decorType":"restaurant"},{"id":"node-2965492497","lat":25.047148,"lon":121.566765,"name":"7-Eleven","decorType":"convenience"},{"id":"node-2987200080","lat":25.042134,"lon":121.565291,"name":"咖啡講市府店","decorType":"cafe"},{"id":"node-2987200084","lat":25.042558,"lon":121.565523,"name":"法朵新馬德里鐵板燒","decorType":"restaurant"},{"id":"node-2987200648","lat":25.042184,"lon":121.565313,"name":"鼎泰健保藥局","decorType":"pharmacy"},{"id":"node-2987200649","lat":25.041286,"lon":121.565227,"name":"7-Eleven","decorType":"convenience"},{"id":"node-3019870848","lat":25.040745,"lon":121.567027,"name":"捷運市政府站3號出口","decorType":"station"},{"id":"node-3019870850","lat":25.041312,"lon":121.565482,"name":"捷運市政府站1號出口","decorType":"station"},{"id":"node-3045739869","lat":25.049965,"lon":121.565566,"name":"客美多咖啡","decorType":"cafe"},{"id":"node-3045739870","lat":25.050454,"lon":121.562623,"name":"紹香涮涮鍋","decorType":"restaurant"},{"id":"node-3045739878","lat":25.050732,"lon":121.562624,"name":"瑪麗羊咖啡茶館","decorType":"cafe"},{"id":"node-3045739913","lat":25.050147,"lon":121.565528,"name":"7-Eleven","decorType":"convenience"},{"id":"node-3045739914","lat":25.050483,"lon":121.564379,"name":"萊爾富","decorType":"convenience"},{"id":"node-3053046423","lat":25.041286,"lon":121.565269,"name":"豆工房咖啡","decorType":"cafe"},{"id":"node-3065793998","lat":25.047719,"lon":121.568136,"name":"基隆路口二","decorType":"bus_stop"},{"id":"node-3065793999","lat":25.048285,"lon":121.568963,"name":"基隆路口","decorType":"bus_stop"},{"id":"node-3079655518","lat":25.049874,"lon":121.56559,"name":"一元堂美食茶館","decorType":"cafe"},{"id":"node-3079655520","lat":25.051529,"lon":121.566619,"name":"南京公寓(捷運南京三民)","decorType":"bus_stop"},{"id":"node-3079655529","lat":25.051574,"lon":121.56524,"name":"清心福全冷飲站","decorType":"cafe"},{"id":"node-3079656795","lat":25.05156,"lon":121.56474,"name":"出口4 (麥帥一橋)","decorType":"station"},{"id":"node-3086736495","lat":25.046941,"lon":121.562626,"name":"市民東寧路口","decorType":"bus_stop"},{"id":"node-3086736496","lat":25.047667,"lon":121.563591,"name":"市民東寧路口","decorType":"bus_stop"},{"id":"node-3086736499","lat":25.046909,"lon":121.561531,"name":"復盛京華(往西)","decorType":"bus_stop"},{"id":"node-3156267989","lat":25.053952,"lon":121.562573,"name":"健康新城","decorType":"bus_stop"},{"id":"node-3159711858","lat":25.040057,"lon":121.568592,"name":"消防局 (松仁)","decorType":"bus_stop"},{"id":"node-3161349905","lat":25.052189,"lon":121.570032,"name":"南松山(塔悠)","decorType":"bus_stop"},{"id":"node-3182476397","lat":25.051235,"lon":121.564585,"name":"出口3 (東興路)","decorType":"station"},{"id":"node-3182476398","lat":25.051327,"lon":121.563136,"name":"出口2 (吉祥路)","decorType":"station"},{"id":"node-3182476401","lat":25.051591,"lon":121.563126,"name":"出口1 (三民路)","decorType":"station"},{"id":"node-3186022961","lat":25.051144,"lon":121.566568,"name":"南京公寓(捷運南京三民)","decorType":"bus_stop"},{"id":"node-3186194977","lat":25.040453,"lon":121.565239,"name":"天仁喫茶趣","decorType":"cafe"},{"id":"node-3186194978","lat":25.040557,"lon":121.565219,"name":"平田驛便當","decorType":"restaurant"},{"id":"node-3186194998","lat":25.040298,"lon":121.56513,"name":"米哥烘培坊","decorType":"bakery"},{"id":"node-3186195000","lat":25.040663,"lon":121.565069,"name":"7-Eleven","decorType":"convenience"},{"id":"node-3195624640","lat":25.050591,"lon":121.571811,"name":"六媽臭臭鍋","decorType":"restaurant"},{"id":"node-3228473273","lat":25.050308,"lon":121.569749,"name":"基隆路口一","decorType":"bus_stop"},{"id":"node-3230194508","lat":25.04565,"lon":121.573588,"name":"國民住宅","decorType":"bus_stop"},{"id":"node-3230194511","lat":25.044948,"lon":121.569692,"name":"松隆路口","decorType":"bus_stop"},{"id":"node-3230194512","lat":25.044981,"lon":121.569386,"name":"松隆路口","decorType":"bus_stop"},{"id":"node-3230194514","lat":25.045518,"lon":121.571635,"name":"興雅國小","decorType":"bus_stop"},{"id":"node-3270256364","lat":25.043317,"lon":121.563132,"name":"NUMÉRO QUATRE","decorType":"cafe"},{"id":"node-3347475194","lat":25.040111,"lon":121.571834,"name":"7-Eleven","decorType":"convenience"},{"id":"node-3353583463","lat":25.040584,"lon":121.565483,"name":"統一時代百貨","decorType":"cosmetics"},{"id":"node-3402180793","lat":25.042328,"lon":121.563276,"name":"金鼎港式燒臘","decorType":"restaurant"},{"id":"node-3407249993","lat":25.041207,"lon":121.568388,"name":"摩斯漢堡","decorType":"burger"},{"id":"node-3407250495","lat":25.041601,"lon":121.570057,"name":"台北集安宮","decorType":"shrine"},{"id":"node-3408723294","lat":25.04111,"lon":121.569884,"name":"消防局 (忠孝)","decorType":"bus_stop"},{"id":"node-3502694423","lat":25.044643,"lon":121.561879,"name":"誠品行旅","decorType":"hotel"},{"id":"node-3512275767","lat":25.041128,"lon":121.5661,"name":"市政府","decorType":"station"},{"id":"node-3596859024","lat":25.040513,"lon":121.562691,"name":"旬味自然鍋物","decorType":"restaurant"},{"id":"node-3655111511","lat":25.039456,"lon":121.569628,"name":"石油展示館","decorType":"art_gallery"},{"id":"node-3666244129","lat":25.047556,"lon":121.573005,"name":"永吉國中","decorType":"bus_stop"},{"id":"node-3666244130","lat":25.047579,"lon":121.573654,"name":"永吉國中","decorType":"bus_stop"},{"id":"node-3714789189","lat":25.040388,"lon":121.570806,"name":"紅帽子喜餅","decorType":"bakery"},{"id":"node-3714789190","lat":25.040359,"lon":121.571535,"name":"祥哥麻辣燙","decorType":"restaurant"},{"id":"node-3714789191","lat":25.040353,"lon":121.571787,"name":"八方雲集","decorType":"burger"},{"id":"node-3714789192","lat":25.040317,"lon":121.571775,"name":"123小吃","decorType":"restaurant"},{"id":"node-3714789193","lat":25.040283,"lon":121.571776,"name":"巨林美而美","decorType":"burger"},{"id":"node-3714789195","lat":25.039985,"lon":121.571745,"name":"麥味登","decorType":"restaurant"},{"id":"node-3714789196","lat":25.039771,"lon":121.571752,"name":"佳美燒臘","decorType":"restaurant"},{"id":"node-3714789197","lat":25.039816,"lon":121.571752,"name":"小黑人米苔目","decorType":"restaurant"},{"id":"node-3714789200","lat":25.039659,"lon":121.571764,"name":"豐原排骨酥麵","decorType":"restaurant"},{"id":"node-3714789201","lat":25.039612,"lon":121.571829,"name":"安安鍋貼水餃館","decorType":"restaurant"},{"id":"node-3714789203","lat":25.039495,"lon":121.571767,"name":"排骨酥麵食館","decorType":"restaurant"},{"id":"node-3714843276","lat":25.040496,"lon":121.573805,"name":"酒食歐風朝","decorType":"restaurant"},{"id":"node-3714843277","lat":25.040719,"lon":121.574111,"name":"7-Eleven","decorType":"convenience"},{"id":"node-3748706225","lat":25.051621,"lon":121.563607,"name":"星巴克","decorType":"cafe"},{"id":"node-3769904737","lat":25.041718,"lon":121.567248,"name":"7-Eleven","decorType":"convenience"},{"id":"node-3811394869","lat":25.052155,"lon":121.563956,"name":"全家便利商店","decorType":"convenience"},{"id":"node-3811394870","lat":25.052284,"lon":121.566123,"name":"全家便利商店","decorType":"convenience"},{"id":"node-3812564394","lat":25.051428,"lon":121.564306,"name":"南京三民","decorType":"station"},{"id":"node-3835833936","lat":25.041142,"lon":121.57304,"name":"壽司郎","decorType":"restaurant"},{"id":"node-3836711946","lat":25.051602,"lon":121.565593,"name":"雪菜素包 · 油豆腐細粉","decorType":"restaurant"},{"id":"node-3851199324","lat":25.051242,"lon":121.562674,"name":"一之軒","decorType":"bakery"},{"id":"node-3881926857","lat":25.047367,"lon":121.566471,"name":"Richard Blanc","decorType":"bakery"},{"id":"node-3881926858","lat":25.048052,"lon":121.566331,"name":"三商巧福","decorType":"restaurant"},{"id":"node-3881926859","lat":25.048013,"lon":121.566169,"name":"丹堤咖啡","decorType":"cafe"},{"id":"node-3939158002","lat":25.050786,"lon":121.568656,"name":"南松山天主堂","decorType":"shrine"},{"id":"node-3939158009","lat":25.05031,"lon":121.561621,"name":"台北市召會第七聚會所11區","decorType":"shrine"},{"id":"node-3939158015","lat":25.051106,"lon":121.571043,"name":"塔悠便當自助餐","decorType":"restaurant"},{"id":"node-3939158352","lat":25.039183,"lon":121.568729,"name":"未命名郵局","decorType":"post_office"},{"id":"node-3939158380","lat":25.051574,"lon":121.566625,"name":"未命名郵局","decorType":"post_office"},{"id":"node-3955430401","lat":25.054191,"lon":121.562196,"name":"健康新城","decorType":"bus_stop"},{"id":"node-3981476457","lat":25.039179,"lon":121.569376,"name":"中油大樓","decorType":"bus_stop"},{"id":"node-3981476458","lat":25.042035,"lon":121.572031,"name":"富台公園","decorType":"bus_stop"},{"id":"node-3981476459","lat":25.0425,"lon":121.57192,"name":"富台公園","decorType":"bus_stop"},{"id":"node-3981476460","lat":25.044463,"lon":121.572099,"name":"永吉松信路口","decorType":"bus_stop"},{"id":"node-3981476461","lat":25.044859,"lon":121.57203,"name":"永吉松信路口","decorType":"bus_stop"},{"id":"node-3981476580","lat":25.047691,"lon":121.57214,"name":"雅祥公園","decorType":"bus_stop"},{"id":"node-3981476581","lat":25.047767,"lon":121.572221,"name":"雅祥公園","decorType":"bus_stop"},{"id":"node-4058075207","lat":25.042294,"lon":121.563425,"name":"初衷小鹿原味鍋物","decorType":"restaurant"},{"id":"node-4058075215","lat":25.042328,"lon":121.563582,"name":"全家便利商店","decorType":"convenience"},{"id":"node-4058075216","lat":25.045343,"lon":121.573915,"name":"北平彩芝樓","decorType":"restaurant"},{"id":"node-4058075219","lat":25.041213,"lon":121.568828,"name":"大樹藥局","decorType":"pharmacy"},{"id":"node-4058075225","lat":25.041332,"lon":121.563555,"name":"未命名郵局","decorType":"post_office"},{"id":"node-4069716696","lat":25.050324,"lon":121.564085,"name":"香港大家好港式粥粉麵飯","decorType":"restaurant"},{"id":"node-4111818890","lat":25.039713,"lon":121.566349,"name":"鼎泰豐","decorType":"restaurant"},{"id":"node-4138748294","lat":25.050756,"lon":121.562464,"name":"全聯福利中心","decorType":"supermarket"},{"id":"node-4148555731","lat":25.039045,"lon":121.564615,"name":"市政府 (松高)","decorType":"bus_stop"},{"id":"node-4148721616","lat":25.051561,"lon":121.569812,"name":"小公館文人旅舍","decorType":"hotel"},{"id":"node-4167717189","lat":25.0388,"lon":121.566764,"name":"丸亀製麺","decorType":"burger"},{"id":"node-4187560319","lat":25.049885,"lon":121.57022,"name":"霞海城隍廟","decorType":"shrine"},{"id":"node-4231372847","lat":25.051221,"lon":121.56139,"name":"太和工坊","decorType":"bakery"},{"id":"node-4231372848","lat":25.051218,"lon":121.561546,"name":"台灣大哥大","decorType":"electronics"},{"id":"node-4231372852","lat":25.051233,"lon":121.562122,"name":"未命名美髮院","decorType":"hair_salon"},{"id":"node-4231372854","lat":25.051233,"lon":121.561795,"name":"彌生軒","decorType":"restaurant"},{"id":"node-4235272603","lat":25.050753,"lon":121.569904,"name":"天使商旅","decorType":"hotel"},{"id":"node-4309145399","lat":25.051506,"lon":121.569814,"name":"杜萊根國際青年旅舍","decorType":"hotel"},{"id":"node-4325693432","lat":25.042872,"lon":121.564571,"name":"信義興雅宮","decorType":"shrine"},{"id":"node-4325693437","lat":25.042479,"lon":121.566175,"name":"全家便利商店","decorType":"convenience"},{"id":"node-4325693477","lat":25.043621,"lon":121.562944,"name":"LeTAO","decorType":"cafe"},{"id":"node-4325693920","lat":25.043348,"lon":121.562886,"name":"蝦皮店到店","decorType":"convenience"},{"id":"node-4328118409","lat":25.041195,"lon":121.569,"name":"日常時光","decorType":"restaurant"},{"id":"node-4328118413","lat":25.043596,"lon":121.572209,"name":"全家便利商店","decorType":"convenience"},{"id":"node-4328118454","lat":25.040306,"lon":121.56161,"name":"未命名郵局","decorType":"post_office"},{"id":"node-4328118600","lat":25.042694,"lon":121.568802,"name":"未命名郵局","decorType":"post_office"},{"id":"node-4328118606","lat":25.04342,"lon":121.570478,"name":"美廉社","decorType":"supermarket"},{"id":"node-4328118623","lat":25.042027,"lon":121.568582,"name":"7-Eleven","decorType":"convenience"},{"id":"node-4328118625","lat":25.043444,"lon":121.568859,"name":"7-Eleven","decorType":"convenience"},{"id":"node-4370609442","lat":25.047885,"lon":121.566472,"name":"VOEZ Café","decorType":"cafe"},{"id":"node-4370612641","lat":25.048083,"lon":121.566236,"name":"鮮五丼","decorType":"restaurant"},{"id":"node-4384257962","lat":25.043522,"lon":121.56291,"name":"屋莎洋食鬆餅屋","decorType":"restaurant"},{"id":"node-4419893326","lat":25.038871,"lon":121.574041,"name":"Yup Cafe & Bistro","decorType":"restaurant"},{"id":"node-4434517890","lat":25.039491,"lon":121.566788,"name":"iPasta","decorType":"restaurant"},{"id":"node-4524863610","lat":25.041748,"lon":121.565022,"name":"未命名郵局","decorType":"post_office"},{"id":"node-4524863898","lat":25.054056,"lon":121.563727,"name":"未命名郵局","decorType":"post_office"},{"id":"node-4524864568","lat":25.04077,"lon":121.567193,"name":"日藥本舖","decorType":"pharmacy"},{"id":"node-4622733295","lat":25.039574,"lon":121.565716,"name":"KiKi Restaurant","decorType":"restaurant"},{"id":"node-4678624019","lat":25.039513,"lon":121.56641,"name":"香矛廚泰式料理","decorType":"restaurant"},{"id":"node-4782136823","lat":25.051718,"lon":121.563623,"name":"Jiizu Hostel","decorType":"hotel"},{"id":"node-4782139821","lat":25.051799,"lon":121.563627,"name":"全家便利商店","decorType":"convenience"},{"id":"node-4786107211","lat":25.040421,"lon":121.567071,"name":"Cozzi Café","decorType":"cafe"},{"id":"node-4809532030","lat":25.0404,"lon":121.566752,"name":"晶華冠軍牛肉麺坊","decorType":"restaurant"},{"id":"node-4837986373","lat":25.05169,"lon":121.561562,"name":"7-Eleven","decorType":"convenience"},{"id":"node-4837986375","lat":25.051124,"lon":121.563444,"name":"全家便利商店","decorType":"convenience"},{"id":"node-4837986381","lat":25.049331,"lon":121.562946,"name":"福德宮","decorType":"shrine"},{"id":"node-4837986382","lat":25.048812,"lon":121.562411,"name":"Mangio","decorType":"restaurant"},{"id":"node-4937891814","lat":25.039615,"lon":121.565842,"name":"吉豚屋","decorType":"burger"},{"id":"node-5098115723","lat":25.042776,"lon":121.566067,"name":"Nathalie Lete娜塔莉台北店","decorType":"cafe"},{"id":"node-5110348190","lat":25.044704,"lon":121.571544,"name":"境靈廟","decorType":"shrine"},{"id":"node-5110348192","lat":25.044062,"lon":121.572457,"name":"台北市召會第五聚會所","decorType":"shrine"},{"id":"node-5110348193","lat":25.042973,"lon":121.572337,"name":"台北新城市教會","decorType":"shrine"},{"id":"node-5110348194","lat":25.042238,"lon":121.573691,"name":"授天宮","decorType":"shrine"},{"id":"node-5110348195","lat":25.042259,"lon":121.574163,"name":"全家便利商店","decorType":"convenience"},{"id":"node-5110348209","lat":25.0511,"lon":121.566416,"name":"香華","decorType":"bakery"},{"id":"node-5110348210","lat":25.05115,"lon":121.563215,"name":"楊記大餛飩","decorType":"restaurant"},{"id":"node-5110348211","lat":25.05103,"lon":121.563308,"name":"八號極品海鮮餐廳","decorType":"restaurant"},{"id":"node-5110348212","lat":25.051332,"lon":121.562247,"name":"未命名郵局","decorType":"post_office"},{"id":"node-5110348546","lat":25.050127,"lon":121.571601,"name":"佳湘意麵餛飩","decorType":"restaurant"},{"id":"node-5110348547","lat":25.050214,"lon":121.571508,"name":"香港豪記燒臘","decorType":"restaurant"},{"id":"node-5110348548","lat":25.050365,"lon":121.571235,"name":"沈家香菇肉粥","decorType":"restaurant"},{"id":"node-5110348549","lat":25.0511,"lon":121.567448,"name":"真耶穌教會","decorType":"shrine"},{"id":"node-5110348550","lat":25.050316,"lon":121.574199,"name":"松山福德宮","decorType":"shrine"},{"id":"node-5110348552","lat":25.050757,"lon":121.571476,"name":"7-Eleven","decorType":"convenience"},{"id":"node-5110348553","lat":25.051579,"lon":121.564256,"name":"小林髮廊","decorType":"hair_salon"},{"id":"node-5110348555","lat":25.051584,"lon":121.56448,"name":"鬍鬚張","decorType":"restaurant"},{"id":"node-5110348556","lat":25.051587,"lon":121.564442,"name":"老虎醬溫州大餛飩","decorType":"restaurant"},{"id":"node-5110348563","lat":25.045829,"lon":121.570179,"name":"萊爾富","decorType":"convenience"},{"id":"node-5110348564","lat":25.045484,"lon":121.56959,"name":"永安教會","decorType":"shrine"},{"id":"node-5110348565","lat":25.046507,"lon":121.569454,"name":"松山禮拜堂","decorType":"shrine"},{"id":"node-5110348566","lat":25.046424,"lon":121.57053,"name":"楊和堂","decorType":"shrine"},{"id":"node-5110348567","lat":25.047654,"lon":121.571187,"name":"貴吾堂","decorType":"shrine"},{"id":"node-5110348569","lat":25.048013,"lon":121.570383,"name":"雅祥宮","decorType":"shrine"},{"id":"node-5110348570","lat":25.048027,"lon":121.569885,"name":"惠佑宮","decorType":"shrine"},{"id":"node-5110348571","lat":25.048456,"lon":121.569452,"name":"忠義宮","decorType":"shrine"},{"id":"node-5110348573","lat":25.048659,"lon":121.570535,"name":"未命名郵局","decorType":"post_office"},{"id":"node-5110348575","lat":25.049575,"lon":121.574015,"name":"一等好旅店","decorType":"hotel"},{"id":"node-5110348576","lat":25.051077,"lon":121.566901,"name":"草食咖啡","decorType":"cafe"},{"id":"node-5110348586","lat":25.051082,"lon":121.570052,"name":"金磚鴨北京烤鴨","decorType":"restaurant"},{"id":"node-5110348738","lat":25.048821,"lon":121.561784,"name":"一禾堂","decorType":"bakery"},{"id":"node-5110348739","lat":25.049497,"lon":121.562723,"name":"全家便利商店","decorType":"convenience"},{"id":"node-5110348742","lat":25.04927,"lon":121.569071,"name":"鐵路便當","decorType":"restaurant"},{"id":"node-5110348743","lat":25.049772,"lon":121.567508,"name":"美廉社","decorType":"supermarket"},{"id":"node-5110348744","lat":25.050534,"lon":121.565977,"name":"萊爾富","decorType":"convenience"},{"id":"node-5110348745","lat":25.051132,"lon":121.566309,"name":"八方雲集","decorType":"burger"},{"id":"node-5110348746","lat":25.051593,"lon":121.565533,"name":"文暢書局","decorType":"library"},{"id":"node-5110348749","lat":25.051589,"lon":121.5653,"name":"福美蔬食自助餐","decorType":"restaurant"},{"id":"node-5110348750","lat":25.051573,"lon":121.565158,"name":"義美食品","decorType":"convenience"},{"id":"node-5110348751","lat":25.051151,"lon":121.565069,"name":"布咯咖啡","decorType":"cafe"},{"id":"node-5110348816","lat":25.040713,"lon":121.572635,"name":"ZY-girl中大尺碼","decorType":"clothing"},{"id":"node-5168755424","lat":25.051699,"lon":121.561703,"name":"cama Coffee","decorType":"cafe"},{"id":"node-5175120724","lat":25.040708,"lon":121.56683,"name":"莫爾頓牛排館","decorType":"restaurant"},{"id":"node-5189707088","lat":25.04112,"lon":121.57382,"name":"肯德基","decorType":"burger"},{"id":"node-5275426977","lat":25.039737,"lon":121.566757,"name":"劍持屋","decorType":"restaurant"},{"id":"node-5275429042","lat":25.039441,"lon":121.566818,"name":"美麗超市","decorType":"supermarket"},{"id":"node-5296916558","lat":25.040578,"lon":121.565293,"name":"TSUTAYA","decorType":"library"},{"id":"node-5296916559","lat":25.040873,"lon":121.565284,"name":"Mister Donut","decorType":"bakery"},{"id":"node-5305672915","lat":25.041658,"lon":121.570104,"name":"台北靈覺寺","decorType":"shrine"},{"id":"node-5313864463","lat":25.044673,"lon":121.568679,"name":"張記臭豆腐","decorType":"restaurant"},{"id":"node-5313864465","lat":25.043476,"lon":121.568689,"name":"康是美","decorType":"pharmacy"},{"id":"node-5313864467","lat":25.041472,"lon":121.568804,"name":"屈臣氏","decorType":"pharmacy"},{"id":"node-5313864468","lat":25.051521,"lon":121.570108,"name":"城市商旅","decorType":"hotel"},{"id":"node-5314324318","lat":25.050613,"lon":121.569812,"name":"富景商旅","decorType":"hotel"},{"id":"node-5342495344","lat":25.04232,"lon":121.563729,"name":"味家魯肉飯","decorType":"restaurant"},{"id":"node-5362641262","lat":25.040536,"lon":121.5728,"name":"古記雞信義店","decorType":"restaurant"},{"id":"node-5492163047","lat":25.041509,"lon":121.565548,"name":"可不可熟成紅茶","decorType":"cafe"},{"id":"node-5495311021","lat":25.044476,"lon":121.56857,"name":"順安宮","decorType":"shrine"},{"id":"node-5529979623","lat":25.040547,"lon":121.57411,"name":"黑蔓芭","decorType":"cafe"},{"id":"node-5530635922","lat":25.042291,"lon":121.563356,"name":"Pizza Hood","decorType":"restaurant"},{"id":"node-5806262653","lat":25.045106,"lon":121.56772,"name":"Cold noodle restaurant","decorType":"restaurant"},{"id":"node-5892417188","lat":25.0446,"lon":121.562958,"name":"菓源","decorType":"cafe"},{"id":"node-6099308597","lat":25.041999,"lon":121.562943,"name":"二代福林福州乾拌麵","decorType":"restaurant"},{"id":"node-6139315494","lat":25.04697,"lon":121.566737,"name":"X-store","decorType":"convenience"},{"id":"node-6139315495","lat":25.042374,"lon":121.564857,"name":"7-Eleven","decorType":"convenience"},{"id":"node-6156190861","lat":25.041347,"lon":121.566288,"name":"上禾池上便當","decorType":"restaurant"},{"id":"node-6156190862","lat":25.041287,"lon":121.566417,"name":"八方雲集","decorType":"burger"},{"id":"node-6156190863","lat":25.041313,"lon":121.565745,"name":"麻古茶坊","decorType":"cafe"},{"id":"node-6255532289","lat":25.040306,"lon":121.565043,"name":"市府轉運站","decorType":"bus_stop"},{"id":"node-6255543999","lat":25.040333,"lon":121.564594,"name":"市府轉運站","decorType":"bus_stop"},{"id":"node-6255544000","lat":25.040313,"lon":121.564651,"name":"市府轉運站","decorType":"bus_stop"},{"id":"node-6255544001","lat":25.040291,"lon":121.564705,"name":"市府轉運站","decorType":"bus_stop"},{"id":"node-6255544002","lat":25.040288,"lon":121.564757,"name":"市府轉運站","decorType":"bus_stop"},{"id":"node-6255544003","lat":25.040288,"lon":121.564812,"name":"市府轉運站","decorType":"bus_stop"},{"id":"node-6255544004","lat":25.040283,"lon":121.564874,"name":"市府轉運站","decorType":"bus_stop"},{"id":"node-6255544005","lat":25.040326,"lon":121.565083,"name":"市府轉運站","decorType":"bus_stop"},{"id":"node-6255544006","lat":25.040761,"lon":121.565086,"name":"市府轉運站","decorType":"bus_stop"},{"id":"node-6255544007","lat":25.040769,"lon":121.56505,"name":"市府轉運站","decorType":"bus_stop"},{"id":"node-6255544008","lat":25.040775,"lon":121.565019,"name":"市府轉運站","decorType":"bus_stop"},{"id":"node-6255544009","lat":25.040288,"lon":121.564938,"name":"市府轉運站","decorType":"bus_stop"},{"id":"node-6255544010","lat":25.040781,"lon":121.564914,"name":"市府轉運站","decorType":"bus_stop"},{"id":"node-6255544011","lat":25.040775,"lon":121.564857,"name":"市府轉運站","decorType":"bus_stop"},{"id":"node-6255544012","lat":25.040765,"lon":121.564779,"name":"市府轉運站","decorType":"bus_stop"},{"id":"node-6255544013","lat":25.040751,"lon":121.564717,"name":"市府轉運站","decorType":"bus_stop"},{"id":"node-6255544014","lat":25.040706,"lon":121.564627,"name":"市府轉運站","decorType":"bus_stop"},{"id":"node-6255544015","lat":25.040682,"lon":121.564586,"name":"市府轉運站","decorType":"bus_stop"},{"id":"node-6255544016","lat":25.040644,"lon":121.564546,"name":"市府轉運站","decorType":"bus_stop"},{"id":"node-6343932887","lat":25.051215,"lon":121.563907,"name":"全家便利商店","decorType":"convenience"},{"id":"node-6376062391","lat":25.04056,"lon":121.567009,"name":"永心鳳茶","decorType":"restaurant"},{"id":"node-6452416866","lat":25.041603,"lon":121.565838,"name":"拼拼拌 都滿韓家","decorType":"restaurant"},{"id":"node-6462425088","lat":25.045314,"lon":121.570338,"name":"戴記獨臭豆腐","decorType":"restaurant"},{"id":"node-6499715186","lat":25.040421,"lon":121.566931,"name":"犇鐵板燒","decorType":"restaurant"},{"id":"node-6499715187","lat":25.040487,"lon":121.567075,"name":"Osteria","decorType":"restaurant"},{"id":"node-6499715188","lat":25.040418,"lon":121.567,"name":"韓斤麻浦","decorType":"restaurant"},{"id":"node-6563310349","lat":25.040154,"lon":121.563461,"name":"台北旌旗教會","decorType":"shrine"},{"id":"node-6578286271","lat":25.048944,"lon":121.566209,"name":"莊家班麻油雞","decorType":"restaurant"},{"id":"node-6578286272","lat":25.04915,"lon":121.566296,"name":"必勝客","decorType":"restaurant"},{"id":"node-6578286273","lat":25.049085,"lon":121.565841,"name":"福記紅白鍋","decorType":"restaurant"},{"id":"node-6578286274","lat":25.049085,"lon":121.565793,"name":"胖子小吃","decorType":"restaurant"},{"id":"node-6578286276","lat":25.049048,"lon":121.565299,"name":"正典鐵板燒","decorType":"restaurant"},{"id":"node-6578286277","lat":25.049092,"lon":121.565343,"name":"真福記烤鴨","decorType":"restaurant"},{"id":"node-6578286278","lat":25.049015,"lon":121.565034,"name":"王家麵館","decorType":"restaurant"},{"id":"node-6578286279","lat":25.049196,"lon":121.565648,"name":"卡滋日式豬排專賣店","decorType":"restaurant"},{"id":"node-6578286283","lat":25.051868,"lon":121.566118,"name":"7-Eleven","decorType":"convenience"},{"id":"node-6676095490","lat":25.051128,"lon":121.564658,"name":"大潤發迷你站","decorType":"convenience"},{"id":"node-6978549485","lat":25.050824,"lon":121.56624,"name":"九湯屋日本拉麵","decorType":"restaurant"},{"id":"node-6978549686","lat":25.049528,"lon":121.566269,"name":"默契小館","decorType":"restaurant"},{"id":"node-7031628750","lat":25.050529,"lon":121.574172,"name":"口昍品平價牛排","decorType":"restaurant"},{"id":"node-7031800543","lat":25.041289,"lon":121.566669,"name":"魔髮部屋","decorType":"hair_salon"},{"id":"node-7056026983","lat":25.040686,"lon":121.567002,"name":"日本橋海鮮丼","decorType":"restaurant"},{"id":"node-7074468496","lat":25.051212,"lon":121.563683,"name":"御蓮斎","decorType":"restaurant"},{"id":"node-7090057985","lat":25.0504,"lon":121.561879,"name":"幸福的一天","decorType":"restaurant"},{"id":"node-7175334740","lat":25.050147,"lon":121.572764,"name":"萬里香熱炒","decorType":"restaurant"},{"id":"node-7175334764","lat":25.043302,"lon":121.571847,"name":"達美樂松信店","decorType":"restaurant"},{"id":"node-7175334770","lat":25.043586,"lon":121.571889,"name":"蚵埕","decorType":"restaurant"},{"id":"node-7175334780","lat":25.050492,"lon":121.574119,"name":"口吅品麻辣臭豆腐","decorType":"restaurant"},{"id":"node-7175344510","lat":25.048317,"lon":121.572082,"name":"尚鼎麻辣鍋","decorType":"restaurant"},{"id":"node-7175344516","lat":25.046008,"lon":121.572234,"name":"麥味登","decorType":"restaurant"},{"id":"node-7175344521","lat":25.0454,"lon":121.573986,"name":"大埔鐵板燒","decorType":"restaurant"},{"id":"node-7175344543","lat":25.044114,"lon":121.571917,"name":"阿呂叔叔炸物專賣店","decorType":"restaurant"},{"id":"node-7175344554","lat":25.050374,"lon":121.573356,"name":"生蠔哥","decorType":"restaurant"},{"id":"node-7175344587","lat":25.05015,"lon":121.572374,"name":"小明拔絲地瓜","decorType":"restaurant"},{"id":"node-7175344593","lat":25.045937,"lon":121.57198,"name":"火鍋世家","decorType":"restaurant"},{"id":"node-7175344611","lat":25.041487,"lon":121.57206,"name":"安吉食堂","decorType":"restaurant"},{"id":"node-7175344619","lat":25.041687,"lon":121.571808,"name":"吳姑姑","decorType":"restaurant"},{"id":"node-7175344630","lat":25.050423,"lon":121.573341,"name":"火焰骰子牛","decorType":"restaurant"},{"id":"node-7175344635","lat":25.050333,"lon":121.574213,"name":"東發號 油飯・麵線","decorType":"restaurant"},{"id":"node-7175344667","lat":25.04611,"lon":121.571994,"name":"悟饕台北","decorType":"restaurant"},{"id":"node-7175344672","lat":25.04727,"lon":121.573169,"name":"羊家將羊肉爐","decorType":"restaurant"},{"id":"node-7175344694","lat":25.043383,"lon":121.571856,"name":"永和四海豆漿","decorType":"restaurant"},{"id":"node-7175344701","lat":25.045776,"lon":121.571701,"name":"鑫鱻生猛活海鮮","decorType":"restaurant"},{"id":"node-7175344705","lat":25.050294,"lon":121.573187,"name":"起司先生","decorType":"restaurant"},{"id":"node-7175344711","lat":25.050301,"lon":121.574247,"name":"饒河街圓環魯肉飯","decorType":"restaurant"},{"id":"node-7175344734","lat":25.04621,"lon":121.571944,"name":"好味屋餐廳","decorType":"restaurant"},{"id":"node-7175344741","lat":25.050154,"lon":121.572686,"name":"饒河炸彈蔥油餅","decorType":"burger"},{"id":"node-7175344746","lat":25.045941,"lon":121.572279,"name":"溫暖 Atatakai","decorType":"restaurant"},{"id":"node-7175344764","lat":25.041635,"lon":121.571807,"name":"南方漁場","decorType":"restaurant"},{"id":"node-7175344771","lat":25.045832,"lon":121.571952,"name":"怡人早餐店","decorType":"restaurant"},{"id":"node-7175344776","lat":25.050269,"lon":121.573269,"name":"饒河夜市餡餅世家","decorType":"restaurant"},{"id":"node-7175344781","lat":25.050333,"lon":121.573535,"name":"后庄排骨酥麵","decorType":"restaurant"},{"id":"node-7213752469","lat":25.040532,"lon":121.567204,"name":"瓦城 Thai Town","decorType":"restaurant"},{"id":"node-7216240729","lat":25.040374,"lon":121.56578,"name":"大心","decorType":"restaurant"},{"id":"node-7277460643","lat":25.051448,"lon":121.569884,"name":"司機俱樂部滷肉飯","decorType":"restaurant"},{"id":"node-7282086785","lat":25.053276,"lon":121.56616,"name":"東京大阪燒","decorType":"burger"},{"id":"node-7615685376","lat":25.049312,"lon":121.562744,"name":"17工坊義大利麵","decorType":"restaurant"},{"id":"node-7695936437","lat":25.03989,"lon":121.566555,"name":"黑毛屋本家","decorType":"restaurant"},{"id":"node-7700216600","lat":25.040594,"lon":121.565784,"name":"NARA Thai Cuisine 泰國料理","decorType":"restaurant"},{"id":"node-7700216601","lat":25.040508,"lon":121.565434,"name":"開飯川食堂","decorType":"restaurant"},{"id":"node-7700216602","lat":25.040506,"lon":121.565533,"name":"銅盤嚴選韓式烤肉","decorType":"restaurant"},{"id":"node-7700216603","lat":25.040509,"lon":121.565335,"name":"Mo-Mo Paradise","decorType":"restaurant"},{"id":"node-7700216604","lat":25.040638,"lon":121.565437,"name":"Smith X Hsu 現代茶館","decorType":"restaurant"},{"id":"node-7700216605","lat":25.040636,"lon":121.565536,"name":"蔦屋書店 WIRED TOKYO","decorType":"restaurant"},{"id":"node-7700216606","lat":25.04064,"lon":121.565338,"name":"涮乃葉","decorType":"restaurant"},{"id":"node-7700216607","lat":25.040377,"lon":121.565431,"name":"TGI Fridays","decorType":"restaurant"},{"id":"node-7700216608","lat":25.040375,"lon":121.56553,"name":"杏桃鬆餅屋 UZNA OMOM","decorType":"restaurant"},{"id":"node-7700216609","lat":25.040379,"lon":121.565332,"name":"府城擔仔麵虱目魚","decorType":"restaurant"},{"id":"node-7700216610","lat":25.040381,"lon":121.565233,"name":"GUGU廚房義式料理","decorType":"restaurant"},{"id":"node-7700216611","lat":25.040373,"lon":121.565628,"name":"韓食拌樂 bibim","decorType":"restaurant"},{"id":"node-7700216612","lat":25.040504,"lon":121.565631,"name":"聖加海南雞飯","decorType":"restaurant"},{"id":"node-7700216613","lat":25.040511,"lon":121.565236,"name":"小南門 傳統豆花","decorType":"restaurant"},{"id":"node-7700216614","lat":25.040642,"lon":121.565239,"name":"21風味館","decorType":"burger"},{"id":"node-7700216615","lat":25.040634,"lon":121.565635,"name":"北村豆腐家","decorType":"restaurant"},{"id":"node-7700216616","lat":25.040249,"lon":121.565329,"name":"泰昌餅家","decorType":"restaurant"},{"id":"node-7700216617","lat":25.04077,"lon":121.565341,"name":"大戸屋","decorType":"restaurant"},{"id":"node-7700216618","lat":25.040247,"lon":121.565428,"name":"海壽司 Hi Sushi 迴轉壽司","decorType":"restaurant"},{"id":"node-7700216619","lat":25.040768,"lon":121.56544,"name":"博多天麩羅 山海","decorType":"restaurant"},{"id":"node-7700216620","lat":25.040245,"lon":121.565527,"name":"鉄火牛排","decorType":"restaurant"},{"id":"node-7700216621","lat":25.040766,"lon":121.565539,"name":"京都 餃子の王將","decorType":"restaurant"},{"id":"node-7700216622","lat":25.040772,"lon":121.565242,"name":"大河屋 日式燒肉丼、串燒","decorType":"restaurant"},{"id":"node-7700216623","lat":25.040248,"lon":121.565236,"name":"尾張 鶏三和 親子丼專賣店","decorType":"restaurant"},{"id":"node-7700216624","lat":25.040243,"lon":121.565625,"name":"靜岡勝政日式豬排","decorType":"restaurant"},{"id":"node-7700216625","lat":25.040764,"lon":121.565638,"name":"Café X Meal MUJI 無印良品餐廳","decorType":"restaurant"},{"id":"node-7702000260","lat":25.041313,"lon":121.566382,"name":"炫豐髮粉","decorType":"hair_salon"},{"id":"node-7800405336","lat":25.040709,"lon":121.561974,"name":"逸鮮棧","decorType":"restaurant"},{"id":"node-7800405342","lat":25.040888,"lon":121.561957,"name":"石亭別棧","decorType":"restaurant"},{"id":"node-7800498003","lat":25.039898,"lon":121.562265,"name":"酒窖餐廳","decorType":"restaurant"},{"id":"node-7800498004","lat":25.044605,"lon":121.562865,"name":"玖龍冰室","decorType":"restaurant"},{"id":"node-7800498005","lat":25.040325,"lon":121.562461,"name":"騏麟素食館","decorType":"restaurant"},{"id":"node-7800498006","lat":25.044084,"lon":121.563194,"name":"夏滇泰特色料理","decorType":"restaurant"},{"id":"node-7800498007","lat":25.040495,"lon":121.562981,"name":"十二籃粥火鍋","decorType":"restaurant"},{"id":"node-7800498008","lat":25.042199,"lon":121.563494,"name":"大初 Tenppanyaki","decorType":"restaurant"},{"id":"node-7800498009","lat":25.042496,"lon":121.565456,"name":"皇品葉記港式燒臘","decorType":"restaurant"},{"id":"node-7800498010","lat":25.044413,"lon":121.563408,"name":"蔬食餐酒館","decorType":"restaurant"},{"id":"node-7800498011","lat":25.042218,"lon":121.56319,"name":"吐司股長","decorType":"restaurant"},{"id":"node-7800498012","lat":25.04221,"lon":121.563072,"name":"五之神製作所","decorType":"restaurant"},{"id":"node-7800498013","lat":25.043162,"lon":121.563101,"name":"她的餐酒","decorType":"restaurant"},{"id":"node-7800498014","lat":25.040314,"lon":121.562234,"name":"嵐山日本料理","decorType":"restaurant"},{"id":"node-7800498015","lat":25.043009,"lon":121.562842,"name":"草蔬宴義式蔬食餐廳","decorType":"restaurant"},{"id":"node-7800498016","lat":25.040304,"lon":121.563129,"name":"寶吉祥蔬食料理廚房","decorType":"restaurant"},{"id":"node-7800498017","lat":25.044109,"lon":121.563077,"name":"家咖哩","decorType":"restaurant"},{"id":"node-7800498018","lat":25.042691,"lon":121.563204,"name":"本味洋食","decorType":"restaurant"},{"id":"node-7800498019","lat":25.040311,"lon":121.562895,"name":"元食cafe","decorType":"restaurant"},{"id":"node-7800498021","lat":25.041948,"lon":121.56523,"name":"宸料理","decorType":"restaurant"},{"id":"node-7800498022","lat":25.042243,"lon":121.563866,"name":"凱琳手作蛋餅和羋亞瓦特","decorType":"restaurant"},{"id":"node-7800498025","lat":25.040526,"lon":121.562775,"name":"請請義大利餐廳","decorType":"restaurant"},{"id":"node-7800498026","lat":25.042721,"lon":121.563792,"name":"韓川館","decorType":"restaurant"},{"id":"node-7800498028","lat":25.042461,"lon":121.562838,"name":"正德小吃店","decorType":"restaurant"},{"id":"node-7800498029","lat":25.04334,"lon":121.563475,"name":"喵豆花","decorType":"restaurant"},{"id":"node-7800498030","lat":25.04256,"lon":121.562826,"name":"11 Cafe","decorType":"restaurant"},{"id":"node-7800498031","lat":25.042214,"lon":121.563736,"name":"米奇早餐店","decorType":"restaurant"},{"id":"node-7800498033","lat":25.043423,"lon":121.563404,"name":"琺蘭綺瑥朵英式茶餐館","decorType":"restaurant"},{"id":"node-7800498034","lat":25.039924,"lon":121.562577,"name":"夏威夷餐廳","decorType":"restaurant"},{"id":"node-7800498035","lat":25.042024,"lon":121.564167,"name":"Awesome Burger","decorType":"burger"},{"id":"node-7800498036","lat":25.039507,"lon":121.562349,"name":"PIZZA PARK","decorType":"restaurant"},{"id":"node-7800498037","lat":25.040278,"lon":121.562778,"name":"亮萌私房料理","decorType":"restaurant"},{"id":"node-7800498038","lat":25.03954,"lon":121.562164,"name":"好餓哦","decorType":"restaurant"},{"id":"node-7800498039","lat":25.044147,"lon":121.563509,"name":"七三茶堂","decorType":"restaurant"},{"id":"node-7800498040","lat":25.039676,"lon":121.562446,"name":"30 Thirty","decorType":"restaurant"},{"id":"node-7800498041","lat":25.041788,"lon":121.565472,"name":"宋廚菜館","decorType":"restaurant"},{"id":"node-7800498042","lat":25.042261,"lon":121.564007,"name":"比利時咖啡","decorType":"restaurant"},{"id":"node-7800498044","lat":25.039949,"lon":121.562325,"name":"屋頂上的貓","decorType":"restaurant"},{"id":"node-7800498045","lat":25.04415,"lon":121.5634,"name":"TankQ Cafe & Bar","decorType":"restaurant"},{"id":"node-7800500964","lat":25.049786,"lon":121.56318,"name":"大鵬壽司","decorType":"restaurant"},{"id":"node-7800500970","lat":25.049493,"lon":121.563347,"name":"阿公阿嬤豆漿","decorType":"restaurant"},{"id":"node-7800500976","lat":25.049198,"lon":121.563164,"name":"京華吉祥營養俱樂部","decorType":"restaurant"},{"id":"node-7800500977","lat":25.049122,"lon":121.562475,"name":"早餐堡","decorType":"restaurant"},{"id":"node-7800500984","lat":25.049275,"lon":121.562673,"name":"上品蔥抓餅&檳榔","decorType":"restaurant"},{"id":"node-7800516491","lat":25.049194,"lon":121.562645,"name":"九兩雞排王","decorType":"restaurant"},{"id":"node-7800576496","lat":25.048798,"lon":121.562241,"name":"赤坂拉麵","decorType":"restaurant"},{"id":"node-7800576497","lat":25.048869,"lon":121.562376,"name":"吳記麻辣鴛鴦火鍋","decorType":"restaurant"},{"id":"node-7800576501","lat":25.04882,"lon":121.562479,"name":"興武六麵館","decorType":"restaurant"},{"id":"node-7800576507","lat":25.048808,"lon":121.562326,"name":"はんは","decorType":"restaurant"},{"id":"node-7800594050","lat":25.050598,"lon":121.568084,"name":"考山路","decorType":"restaurant"},{"id":"node-7800594051","lat":25.050048,"lon":121.564234,"name":"全羅道韓式拌飯","decorType":"restaurant"},{"id":"node-7800594052","lat":25.048331,"lon":121.562937,"name":"京華涼麵","decorType":"restaurant"},{"id":"node-7800594053","lat":25.049817,"lon":121.567295,"name":"私廚俱樂部","decorType":"restaurant"},{"id":"node-7800594055","lat":25.050802,"lon":121.569974,"name":"好食在食堂","decorType":"restaurant"},{"id":"node-7800594059","lat":25.047764,"lon":121.563408,"name":"張大媽美食","decorType":"restaurant"},{"id":"node-7800594061","lat":25.049779,"lon":121.567138,"name":"Dream.K Restaurant","decorType":"restaurant"},{"id":"node-7800594066","lat":25.049935,"lon":121.564387,"name":"享初精緻早午餐","decorType":"restaurant"},{"id":"node-7800594068","lat":25.048701,"lon":121.563616,"name":"58海鮮","decorType":"restaurant"},{"id":"node-7800594071","lat":25.054264,"lon":121.561592,"name":"安迪城堡","decorType":"restaurant"},{"id":"node-7800594073","lat":25.050353,"lon":121.564315,"name":"老黑九","decorType":"restaurant"},{"id":"node-7800594078","lat":25.050069,"lon":121.564387,"name":"麥味登","decorType":"restaurant"},{"id":"node-7800594081","lat":25.050246,"lon":121.564293,"name":"小倆口麵線王","decorType":"restaurant"},{"id":"node-7800611886","lat":25.050161,"lon":121.564381,"name":"哆啦の店","decorType":"restaurant"},{"id":"node-7800611887","lat":25.048978,"lon":121.562669,"name":"饗味小吃館","decorType":"restaurant"},{"id":"node-7800611888","lat":25.049812,"lon":121.56742,"name":"閑閑餐酒館","decorType":"restaurant"},{"id":"node-7800611889","lat":25.048622,"lon":121.563239,"name":"加分100%浜中特選昆布鍋物","decorType":"restaurant"},{"id":"node-7800611890","lat":25.048498,"lon":121.563565,"name":"中原客棧","decorType":"restaurant"},{"id":"node-7800611891","lat":25.049885,"lon":121.564504,"name":"醡醬麵大王","decorType":"restaurant"},{"id":"node-7800611894","lat":25.050309,"lon":121.563976,"name":"御香精緻素食","decorType":"restaurant"},{"id":"node-7800611895","lat":25.051124,"lon":121.568081,"name":"藍田養生月子餐","decorType":"restaurant"},{"id":"node-7800611896","lat":25.050825,"lon":121.568702,"name":"莫爾咖啡廚房","decorType":"restaurant"},{"id":"node-7801777469","lat":25.04874,"lon":121.564273,"name":"藍色早餐吧","decorType":"restaurant"},{"id":"node-7801777473","lat":25.04804,"lon":121.564678,"name":"餛飩舖子","decorType":"restaurant"},{"id":"node-7801777474","lat":25.049474,"lon":121.565301,"name":"集客人間茶館","decorType":"restaurant"},{"id":"node-7801777476","lat":25.049637,"lon":121.566028,"name":"王記餃子舖","decorType":"restaurant"},{"id":"node-7801777477","lat":25.04804,"lon":121.564476,"name":"熊燒Bar串燒","decorType":"restaurant"},{"id":"node-7801777478","lat":25.047906,"lon":121.564059,"name":"台北ㄐ廠生猛海鮮","decorType":"restaurant"},{"id":"node-7801777479","lat":25.048696,"lon":121.564395,"name":"福原樓","decorType":"restaurant"},{"id":"node-7801777481","lat":25.04945,"lon":121.564671,"name":"正典鐵板燒","decorType":"restaurant"},{"id":"node-7801777484","lat":25.049487,"lon":121.564856,"name":"老家下酒菜","decorType":"restaurant"},{"id":"node-7801780686","lat":25.049949,"lon":121.562892,"name":"花台秋迷","decorType":"restaurant"},{"id":"node-7801780687","lat":25.049098,"lon":121.565302,"name":"李記麻辣鴛鴦火鍋店","decorType":"restaurant"},{"id":"node-7801780689","lat":25.050221,"lon":121.562673,"name":"早安美芝城","decorType":"burger"},{"id":"node-7801780690","lat":25.049938,"lon":121.563013,"name":"鴻圓越式河粉","decorType":"restaurant"},{"id":"node-7801780691","lat":25.049074,"lon":121.565211,"name":"香港龍威燒臘","decorType":"restaurant"},{"id":"node-8118207165","lat":25.039494,"lon":121.565234,"name":"7-Eleven","decorType":"convenience"},{"id":"node-8118207166","lat":25.038774,"lon":121.566854,"name":"7-Eleven","decorType":"convenience"},{"id":"node-8118207167","lat":25.04066,"lon":121.567025,"name":"7-Eleven","decorType":"convenience"},{"id":"node-8118207182","lat":25.051074,"lon":121.568967,"name":"7-Eleven","decorType":"convenience"},{"id":"node-8118207183","lat":25.052727,"lon":121.567755,"name":"7-Eleven","decorType":"convenience"},{"id":"node-8118272737","lat":25.054307,"lon":121.564155,"name":"全家便利商店","decorType":"convenience"},{"id":"node-8372532618","lat":25.039399,"lon":121.566571,"name":"恆隆行","decorType":"electronics"},{"id":"node-8372532619","lat":25.039572,"lon":121.565558,"name":"恆隆行","decorType":"electronics"},{"id":"node-8372532621","lat":25.038815,"lon":121.566819,"name":"恆隆行","decorType":"electronics"},{"id":"node-8372532626","lat":25.040755,"lon":121.565761,"name":"恆隆行","decorType":"electronics"},{"id":"node-8375101582","lat":25.039552,"lon":121.566333,"name":"iStore","decorType":"electronics"},{"id":"node-8385313306","lat":25.042413,"lon":121.563586,"name":"八方雲集","decorType":"burger"},{"id":"node-8385313681","lat":25.044736,"lon":121.57424,"name":"八方雲集","decorType":"burger"},{"id":"node-8432400462","lat":25.040252,"lon":121.571855,"name":"市立工農(正門)","decorType":"bus_stop"},{"id":"node-8455124351","lat":25.051526,"lon":121.566721,"name":"南京公寓 (捷運南京三民)","decorType":"bus_stop"},{"id":"node-8686153393","lat":25.041187,"lon":121.569483,"name":"一品活蝦","decorType":"restaurant"},{"id":"node-8686212560","lat":25.041189,"lon":121.569397,"name":"築田便當","decorType":"restaurant"},{"id":"node-8686237119","lat":25.041212,"lon":121.568914,"name":"大鼎傳統美食","decorType":"restaurant"},{"id":"node-8821182318","lat":25.050645,"lon":121.566179,"name":"建美蜜錢食品行","decorType":"sweetshop"},{"id":"node-9049634891","lat":25.042889,"lon":121.567337,"name":"HWC黑沃咖啡-台北市府店","decorType":"cafe"},{"id":"node-9049665945","lat":25.042005,"lon":121.564293,"name":"The 雞 Spot","decorType":"restaurant"},{"id":"node-9364864622","lat":25.041304,"lon":121.565933,"name":"路易莎咖啡","decorType":"cafe"},{"id":"node-9364864623","lat":25.04145,"lon":121.566153,"name":"新娘子小吃","decorType":"restaurant"},{"id":"node-9364864624","lat":25.041455,"lon":121.56625,"name":"溫州大餛飩","decorType":"restaurant"},{"id":"node-9364864626","lat":25.041468,"lon":121.566716,"name":"餃子樂","decorType":"restaurant"},{"id":"node-9364864627","lat":25.041349,"lon":121.566711,"name":"午葉","decorType":"cafe"},{"id":"node-9364864628","lat":25.041798,"lon":121.56725,"name":"全家便利商店","decorType":"convenience"},{"id":"node-9364864629","lat":25.041718,"lon":121.5674,"name":"上海市牛肉麵","decorType":"restaurant"},{"id":"node-9381950234","lat":25.042424,"lon":121.568017,"name":"龍涎居","decorType":"restaurant"},{"id":"node-9381950235","lat":25.042427,"lon":121.568117,"name":"南北舍小館","decorType":"restaurant"},{"id":"node-9381950236","lat":25.042424,"lon":121.568171,"name":"樹樂集","decorType":"cafe"},{"id":"node-9381950237","lat":25.042426,"lon":121.568253,"name":"大胃鍋","decorType":"restaurant"},{"id":"node-9381950238","lat":25.042417,"lon":121.568313,"name":"享咖啡","decorType":"cafe"},{"id":"node-9381950239","lat":25.042423,"lon":121.56841,"name":"誠記越南麵食館","decorType":"restaurant"},{"id":"node-9381950240","lat":25.042405,"lon":121.568561,"name":"胡饕米粉湯","decorType":"restaurant"},{"id":"node-9381950241","lat":25.04238,"lon":121.568657,"name":"傷心酸辣粉","decorType":"restaurant"},{"id":"node-9381950242","lat":25.042375,"lon":121.568897,"name":"雙和盛麵餃館","decorType":"restaurant"},{"id":"node-9381950243","lat":25.042375,"lon":121.568962,"name":"傳說食堂","decorType":"restaurant"},{"id":"node-9381950244","lat":25.042369,"lon":121.569104,"name":"烤食煮盒","decorType":"restaurant"},{"id":"node-9381950245","lat":25.042373,"lon":121.569292,"name":"Lady媽媽廚房","decorType":"restaurant"},{"id":"node-9381950246","lat":25.042226,"lon":121.569304,"name":"站食可以","decorType":"restaurant"},{"id":"node-9381950247","lat":25.042229,"lon":121.569223,"name":"牛一牛厚切牛排","decorType":"restaurant"},{"id":"node-9381950248","lat":25.042231,"lon":121.569135,"name":"傲翔中泰料理","decorType":"restaurant"},{"id":"node-9381950249","lat":25.04224,"lon":121.568954,"name":"四川涼麵","decorType":"restaurant"},{"id":"node-9381950252","lat":25.042209,"lon":121.568798,"name":"梁社漢排骨","decorType":"restaurant"},{"id":"node-9381950253","lat":25.042013,"lon":121.568807,"name":"康圓麵疙瘩","decorType":"restaurant"},{"id":"node-9381950254","lat":25.041847,"lon":121.568795,"name":"鼎越豐麵食館","decorType":"restaurant"},{"id":"node-9381950255","lat":25.04189,"lon":121.568632,"name":"鴨肉謝","decorType":"restaurant"},{"id":"node-9381950259","lat":25.042162,"lon":121.568646,"name":"威爾貝克手烘咖啡吧","decorType":"cafe"},{"id":"node-9381950260","lat":25.041626,"lon":121.568629,"name":"FLASH COFFEE","decorType":"cafe"},{"id":"node-9381950261","lat":25.041459,"lon":121.568617,"name":"滇味廚房","decorType":"restaurant"},{"id":"node-9381950263","lat":25.042257,"lon":121.568123,"name":"榮麵館","decorType":"restaurant"},{"id":"node-9395836054","lat":25.045755,"lon":121.572777,"name":"蝦皮店到店","decorType":"convenience"},{"id":"node-9419614007","lat":25.041244,"lon":121.567865,"name":"艾朋牛排餐酒館","decorType":"restaurant"},{"id":"node-9419622872","lat":25.041244,"lon":121.567696,"name":"すき家","decorType":"burger"},{"id":"node-9419677159","lat":25.041286,"lon":121.567688,"name":"福勝亭","decorType":"restaurant"},{"id":"node-9419810152","lat":25.041517,"lon":121.568495,"name":"福嗑","decorType":"restaurant"},{"id":"node-9419810155","lat":25.041884,"lon":121.568408,"name":"旭興乾洗","decorType":"laundry"},{"id":"node-9419810156","lat":25.042022,"lon":121.568009,"name":"回憶理髮廳","decorType":"hair_salon"},{"id":"node-9419810158","lat":25.042078,"lon":121.56724,"name":"鮨味亭日本料理","decorType":"restaurant"},{"id":"node-9419810160","lat":25.042419,"lon":121.567792,"name":"Wanna Eat","decorType":"restaurant"},{"id":"node-9419810162","lat":25.04189,"lon":121.570298,"name":"半島牛肉麵","decorType":"restaurant"},{"id":"node-9470756525","lat":25.051478,"lon":121.56821,"name":"旭咖啡 直火咖啡豆烘焙","decorType":"cafe"},{"id":"node-9480188917","lat":25.050319,"lon":121.561707,"name":"瑞帛咖啡","decorType":"cafe"},{"id":"node-9544350817","lat":25.039782,"lon":121.574131,"name":"瑰夏咖啡永春店","decorType":"cafe"},{"id":"node-9572372851","lat":25.041248,"lon":121.567782,"name":"客美多咖啡","decorType":"cafe"},{"id":"node-9610069272","lat":25.042526,"lon":121.568798,"name":"烤師傅","decorType":"restaurant"},{"id":"node-9610069273","lat":25.042499,"lon":121.568664,"name":"劉媽媽快餐店","decorType":"restaurant"},{"id":"node-9610069275","lat":25.042549,"lon":121.568873,"name":"BOBOLU","decorType":"cafe"},{"id":"node-9610069276","lat":25.042618,"lon":121.568849,"name":"瑞記 海南雞飯","decorType":"restaurant"},{"id":"node-9610069278","lat":25.042653,"lon":121.568542,"name":"安心藥局","decorType":"pharmacy"},{"id":"node-9610069279","lat":25.042822,"lon":121.568822,"name":"正忠排骨飯","decorType":"restaurant"},{"id":"node-9610069281","lat":25.042964,"lon":121.568823,"name":"曼都髮型","decorType":"cosmetics"},{"id":"node-9610069282","lat":25.043091,"lon":121.568663,"name":"全家便利商店","decorType":"convenience"},{"id":"node-9610069285","lat":25.043032,"lon":121.568824,"name":"兄妹早餐","decorType":"restaurant"},{"id":"node-9610069286","lat":25.043269,"lon":121.568683,"name":"有饌便當","decorType":"restaurant"},{"id":"node-9610069287","lat":25.043314,"lon":121.568681,"name":"鮮綠水果量販店","decorType":"supermarket"},{"id":"node-9610069288","lat":25.043212,"lon":121.568685,"name":"迷客夏","decorType":"cafe"},{"id":"node-9610069289","lat":25.043192,"lon":121.568841,"name":"五桐號","decorType":"cafe"},{"id":"node-9623629191","lat":25.043101,"lon":121.568813,"name":"夏威魚","decorType":"restaurant"},{"id":"node-9989035451","lat":25.040938,"lon":121.566829,"name":"捷運市政府站","decorType":"bus_stop"},{"id":"node-9989035452","lat":25.040946,"lon":121.566595,"name":"捷運市政府站","decorType":"bus_stop"},{"id":"node-9989035453","lat":25.040961,"lon":121.56572,"name":"捷運市政府站","decorType":"bus_stop"},{"id":"node-9989035454","lat":25.04097,"lon":121.565319,"name":"捷運市政府站","decorType":"bus_stop"},{"id":"node-10161164615","lat":25.038949,"lon":121.567492,"name":"Texas Road House","decorType":"restaurant"},{"id":"node-10246451209","lat":25.049639,"lon":121.565804,"name":"植日生手作蔬食","decorType":"restaurant"},{"id":"node-10247965809","lat":25.049721,"lon":121.565555,"name":"晨露","decorType":"cafe"},{"id":"node-10248229809","lat":25.050031,"lon":121.565758,"name":"Protein Kitchen","decorType":"restaurant"},{"id":"node-10250102309","lat":25.050166,"lon":121.566809,"name":"Pause Studio","decorType":"cafe"},{"id":"node-10252340009","lat":25.050229,"lon":121.566624,"name":"未命名自主洗衣店&乾洗店","decorType":"laundry"},{"id":"node-10252927709","lat":25.04998,"lon":121.563596,"name":"Come Food","decorType":"restaurant"},{"id":"node-10657361624","lat":25.040999,"lon":121.561722,"name":"岱妮純蠶絲","decorType":"clothing"},{"id":"node-10673023427","lat":25.040988,"lon":121.562726,"name":"Descente","decorType":"clothing"},{"id":"node-10675699621","lat":25.041467,"lon":121.564053,"name":"Curista Coffee 奎士咖啡","decorType":"cafe"},{"id":"node-10675829360","lat":25.041718,"lon":121.565707,"name":"Auntie Anne's","decorType":"burger"},{"id":"node-10675829369","lat":25.041431,"lon":121.565516,"name":"珍煮丹","decorType":"cafe"},{"id":"node-10675849150","lat":25.040406,"lon":121.562668,"name":"王鍋屋","decorType":"restaurant"},{"id":"node-10680156309","lat":25.040543,"lon":121.562488,"name":"怡客咖啡","decorType":"cafe"},{"id":"node-10680156328","lat":25.040552,"lon":121.562201,"name":"路易莎咖啡","decorType":"cafe"},{"id":"node-10680156329","lat":25.040551,"lon":121.562356,"name":"飯點台式自助餐","decorType":"restaurant"},{"id":"node-10680158914","lat":25.040501,"lon":121.563261,"name":"HAPPYHAIR","decorType":"hair_salon"},{"id":"node-10680158915","lat":25.040357,"lon":121.563172,"name":"全家便利商店","decorType":"convenience"},{"id":"node-10682899620","lat":25.042497,"lon":121.562834,"name":"銀兔湯咖哩","decorType":"restaurant"},{"id":"node-10682899621","lat":25.042602,"lon":121.562832,"name":"LFP香料香水實驗室","decorType":"pharmacy"},{"id":"node-10682899622","lat":25.042761,"lon":121.56285,"name":"PapàRoy 義式手作料理","decorType":"restaurant"},{"id":"node-10682899645","lat":25.043176,"lon":121.563015,"name":"Burger Out","decorType":"burger"},{"id":"node-10682946170","lat":25.041546,"lon":121.565356,"name":"PINEDE 彼內朵 市府店","decorType":"bakery"},{"id":"node-10685028270","lat":25.042082,"lon":121.56563,"name":"SAKImoto Bakery","decorType":"cafe"},{"id":"node-10685052838","lat":25.042234,"lon":121.566042,"name":"一心豪飲","decorType":"cafe"},{"id":"node-10685052839","lat":25.04259,"lon":121.565971,"name":"激安的食事酒場","decorType":"restaurant"},{"id":"node-10685052840","lat":25.042639,"lon":121.566013,"name":"KONMA","decorType":"restaurant"},{"id":"node-10685060139","lat":25.042367,"lon":121.565853,"name":"珍Q涼麵","decorType":"restaurant"},{"id":"node-10859528404","lat":25.051312,"lon":121.561303,"name":"漢堡王","decorType":"burger"},{"id":"node-11309203704","lat":25.051216,"lon":121.561443,"name":"佳德禮餅","decorType":"sweetshop"},{"id":"node-11378647767","lat":25.044893,"lon":121.568885,"name":"MK","decorType":"cafe"},{"id":"node-11389641905","lat":25.050661,"lon":121.565469,"name":"Shabu shabu","decorType":"restaurant"},{"id":"node-11389653476","lat":25.051188,"lon":121.565239,"name":"Moma","decorType":"clothing"},{"id":"node-11389654418","lat":25.051177,"lon":121.565133,"name":"A toast","decorType":"restaurant"},{"id":"node-11389654499","lat":25.052027,"lon":121.565599,"name":"未命名餐廳","decorType":"restaurant"},{"id":"node-11389668288","lat":25.051906,"lon":121.565888,"name":"未命名麵包店","decorType":"bakery"},{"id":"node-11413955777","lat":25.042024,"lon":121.564736,"name":"路易莎咖啡","decorType":"cafe"},{"id":"node-11413972990","lat":25.042063,"lon":121.564759,"name":"Peter Better Cafe","decorType":"cafe"},{"id":"node-11415760491","lat":25.048029,"lon":121.566132,"name":"星巴克","decorType":"cafe"},{"id":"node-11415763541","lat":25.048731,"lon":121.565726,"name":"未命名漢堡店","decorType":"burger"},{"id":"node-11431701931","lat":25.051126,"lon":121.56694,"name":"躍獅京東藥局","decorType":"pharmacy"},{"id":"node-11431774233","lat":25.051125,"lon":121.566783,"name":"康是美","decorType":"pharmacy"},{"id":"node-11431774234","lat":25.051128,"lon":121.566861,"name":"米星亞","decorType":"clothing"},{"id":"node-11433316993","lat":25.04205,"lon":121.56373,"name":"Cuppa Cuppa","decorType":"cafe"},{"id":"node-11434621106","lat":25.04975,"lon":121.56605,"name":"Quán An Viêt Nam","decorType":"restaurant"},{"id":"node-11438361461","lat":25.041201,"lon":121.569324,"name":"牛肉麵 雞湯","decorType":"restaurant"},{"id":"node-11524112083","lat":25.043365,"lon":121.572702,"name":"TA Coffee","decorType":"cafe"},{"id":"node-11629596310","lat":25.051002,"lon":121.563972,"name":"Subway","decorType":"burger"},{"id":"node-11629614791","lat":25.051175,"lon":121.563372,"name":"Cafe!N","decorType":"cafe"},{"id":"node-11639684913","lat":25.045862,"lon":121.569156,"name":"Stand Up","decorType":"cafe"},{"id":"node-11639684920","lat":25.045696,"lon":121.574124,"name":"全家便利商店","decorType":"convenience"},{"id":"node-11639889057","lat":25.04351,"lon":121.574041,"name":"7-Eleven","decorType":"convenience"},{"id":"node-11639903244","lat":25.043024,"lon":121.574059,"name":"未命名服飾店","decorType":"clothing"},{"id":"node-11639907827","lat":25.045742,"lon":121.572486,"name":"未命名自主洗衣店&乾洗店","decorType":"laundry"},{"id":"node-11639926867","lat":25.042662,"lon":121.574047,"name":"Top Beauty","decorType":"cosmetics"},{"id":"node-11639933958","lat":25.045703,"lon":121.573989,"name":"7-Eleven","decorType":"convenience"},{"id":"node-11639938250","lat":25.042067,"lon":121.574143,"name":"The One Pharmacy","decorType":"pharmacy"},{"id":"node-11654992515","lat":25.044674,"lon":121.561356,"name":"Ten thousand","decorType":"cafe"},{"id":"node-11715680062","lat":25.050406,"lon":121.562784,"name":"He Coffee","decorType":"cafe"},{"id":"node-11715719334","lat":25.049781,"lon":121.565599,"name":"The Bund","decorType":"hair_salon"},{"id":"node-11728932285","lat":25.043815,"lon":121.563594,"name":"未命名美髮院","decorType":"hair_salon"},{"id":"node-11762884109","lat":25.050422,"lon":121.562626,"name":"7-Eleven","decorType":"convenience"},{"id":"node-11889059687","lat":25.044519,"lon":121.565412,"name":"松山高中早餐部","decorType":"restaurant"},{"id":"node-11889059746","lat":25.044521,"lon":121.565338,"name":"松山高中麵食部","decorType":"restaurant"},{"id":"node-11915023345","lat":25.049281,"lon":121.565347,"name":"The Godbeef","decorType":"restaurant"},{"id":"node-11967442756","lat":25.041419,"lon":121.562302,"name":"聯合報","decorType":"bus_stop"},{"id":"node-12012048290","lat":25.049019,"lon":121.564212,"name":"萬客什鍋","decorType":"restaurant"},{"id":"node-12121535787","lat":25.042803,"lon":121.563812,"name":"養鍋石頭涮涮鍋","decorType":"restaurant"},{"id":"node-12121535789","lat":25.043806,"lon":121.562841,"name":"提提研面膜松菸概念店","decorType":"cosmetics"},{"id":"node-12133457432","lat":25.04479,"lon":121.570385,"name":"萊客早餐吧","decorType":"restaurant"},{"id":"node-12145462014","lat":25.042023,"lon":121.564328,"name":"巢飯麵食館","decorType":"restaurant"},{"id":"node-12353823167","lat":25.050942,"lon":121.563953,"name":"卡洛貍健康餐盒","decorType":"restaurant"},{"id":"node-12422897258","lat":25.047401,"lon":121.564133,"name":"國家鐵道博物館籌備處","decorType":"art_gallery"},{"id":"node-12479745623","lat":25.040507,"lon":121.567235,"name":"饗饗","decorType":"restaurant"},{"id":"node-12749242152","lat":25.053132,"lon":121.56991,"name":"南松山(塔悠)","decorType":"bus_stop"},{"id":"node-12798795583","lat":25.044546,"lon":121.566745,"name":"Nataraj Indian Cuisine","decorType":"restaurant"},{"id":"node-12798817976","lat":25.04358,"lon":121.563587,"name":"Wunique","decorType":"sweetshop"},{"id":"node-12798817977","lat":25.045174,"lon":121.5671,"name":"未命名餐廳","decorType":"restaurant"},{"id":"node-12798825202","lat":25.04171,"lon":121.565214,"name":"Chubby Burger","decorType":"burger"},{"id":"node-12799609280","lat":25.04244,"lon":121.566804,"name":"Snob Café","decorType":"cafe"},{"id":"node-12799611355","lat":25.042747,"lon":121.56565,"name":"UUCAFE 北歐精品咖啡 台北概念店","decorType":"cafe"},{"id":"node-12799611904","lat":25.042696,"lon":121.565627,"name":"Feeling","decorType":"restaurant"},{"id":"node-12803376788","lat":25.043196,"lon":121.563231,"name":"未命名咖啡廳","decorType":"cafe"},{"id":"node-12803393045","lat":25.042631,"lon":121.56351,"name":"初 CHU Bakery","decorType":"bakery"},{"id":"node-12803395422","lat":25.043189,"lon":121.563169,"name":"Hërs Biströ","decorType":"restaurant"},{"id":"node-12803399352","lat":25.043183,"lon":121.563298,"name":"Bean U","decorType":"restaurant"},{"id":"node-12810732326","lat":25.043928,"lon":121.561573,"name":"全家便利商店","decorType":"convenience"},{"id":"node-12810757137","lat":25.043328,"lon":121.563286,"name":"Tropo Cafe","decorType":"cafe"},{"id":"node-12810971995","lat":25.043154,"lon":121.563602,"name":"Age","decorType":"bakery"},{"id":"node-12818452805","lat":25.043466,"lon":121.569264,"name":"未命名咖啡廳","decorType":"cafe"},{"id":"node-12818457018","lat":25.043629,"lon":121.568842,"name":"未命名咖啡廳","decorType":"cafe"},{"id":"node-12818459696","lat":25.043446,"lon":121.570145,"name":"未命名藥局","decorType":"pharmacy"},{"id":"node-12821412271","lat":25.044256,"lon":121.568899,"name":"CoCo都可","decorType":"cafe"},{"id":"node-12821589957","lat":25.050625,"lon":121.566569,"name":"Klatch Hair Salon","decorType":"hair_salon"},{"id":"node-12821832449","lat":25.050799,"lon":121.566471,"name":"瑞美美","decorType":"restaurant"},{"id":"node-12829789306","lat":25.049523,"lon":121.566102,"name":"Lucky House Breakfast","decorType":"restaurant"},{"id":"node-12863709068","lat":25.042781,"lon":121.565675,"name":"Skrabur","decorType":"burger"},{"id":"node-12863760101","lat":25.047378,"lon":121.568476,"name":"上順興 香Q飯糰","decorType":"restaurant"},{"id":"node-12863795296","lat":25.042804,"lon":121.563135,"name":"御菓子花雨","decorType":"sweetshop"},{"id":"node-12863795300","lat":25.042285,"lon":121.56293,"name":"飽貝 bo'bagel - 貝果專賣店","decorType":"burger"},{"id":"node-12872224641","lat":25.04274,"lon":121.567291,"name":"Bouillon 布雍家","decorType":"restaurant"},{"id":"node-12918897643","lat":25.041859,"lon":121.565603,"name":"Tea tac toe","decorType":"cafe"},{"id":"node-12918899261","lat":25.042388,"lon":121.565816,"name":"未命名餐廳","decorType":"restaurant"},{"id":"node-12959183242","lat":25.049161,"lon":121.566354,"name":"7-Eleven","decorType":"convenience"},{"id":"node-12959198248","lat":25.049218,"lon":121.566814,"name":"未命名餐廳","decorType":"restaurant"},{"id":"node-12959213233","lat":25.049146,"lon":121.566157,"name":"未命名咖啡廳","decorType":"cafe"},{"id":"node-13018450966","lat":25.042201,"lon":121.563447,"name":"未命名餐廳","decorType":"restaurant"},{"id":"node-13077909851","lat":25.039608,"lon":121.565328,"name":"DREAM PLAZA","decorType":"cosmetics"},{"id":"node-13246803660","lat":25.048887,"lon":121.564071,"name":"未命名郵局","decorType":"post_office"},{"id":"node-13298601214","lat":25.042394,"lon":121.564055,"name":"Holiqday","decorType":"cafe"},{"id":"node-13413775734","lat":25.050132,"lon":121.567203,"name":"萊爾富","decorType":"convenience"},{"id":"node-13413775739","lat":25.045391,"lon":121.574259,"name":"萊爾富","decorType":"convenience"},{"id":"node-13417208145","lat":25.050032,"lon":121.565553,"name":"康是美","decorType":"pharmacy"},{"id":"node-13429737501","lat":25.050806,"lon":121.565217,"name":"Long Huo Huo","decorType":"burger"},{"id":"way-48793396","lat":25.051015,"lon":121.57011,"name":"麥帥二橋","decorType":"bridge"},{"id":"way-48793401","lat":25.050848,"lon":121.570462,"name":"正氣橋","decorType":"bridge"},{"id":"way-48793403","lat":25.052647,"lon":121.571757,"name":"麥帥一橋","decorType":"bridge"},{"id":"way-48793405","lat":25.045549,"lon":121.566847,"name":"市民大道","decorType":"bridge"},{"id":"way-48793406","lat":25.04494,"lon":121.565171,"name":"市民大道高架道路","decorType":"bridge"},{"id":"way-50159996","lat":25.045432,"lon":121.567186,"name":"市民大道高架道路","decorType":"bridge"},{"id":"way-50159997","lat":25.044981,"lon":121.565151,"name":"市民大道高架道路","decorType":"bridge"},{"id":"way-51268667","lat":25.053045,"lon":121.57015,"name":"未命名橋樑","decorType":"bridge"},{"id":"way-51813001","lat":25.052718,"lon":121.571666,"name":"麥帥一橋","decorType":"bridge"},{"id":"way-160053381","lat":25.045878,"lon":121.567301,"name":"正氣橋","decorType":"bridge"},{"id":"way-160053390","lat":25.04681,"lon":121.567796,"name":"市民大道","decorType":"bridge"},{"id":"way-160185688","lat":25.046936,"lon":121.567937,"name":"正氣橋","decorType":"bridge"},{"id":"way-190288494","lat":25.053753,"lon":121.564166,"name":"西松公園","decorType":"park"},{"id":"way-229056584","lat":25.04306,"lon":121.562501,"name":"未命名橋樑","decorType":"bridge"},{"id":"way-244126197","lat":25.051661,"lon":121.570909,"name":"未命名橋樑","decorType":"bridge"},{"id":"way-252398632","lat":25.049008,"lon":121.569146,"name":"正氣橋","decorType":"bridge"},{"id":"way-252494908","lat":25.052673,"lon":121.57297,"name":"麥帥一橋","decorType":"bridge"},{"id":"way-252494927","lat":25.047015,"lon":121.567929,"name":"市民大道","decorType":"bridge"},{"id":"way-254652469","lat":25.047797,"lon":121.574137,"name":"五常公園","decorType":"park"},{"id":"way-257354810","lat":25.041962,"lon":121.572311,"name":"富台公園","decorType":"park"},{"id":"way-260122177","lat":25.052105,"lon":121.567733,"name":"寶清公園","decorType":"park"},{"id":"way-274647897","lat":25.039687,"lon":121.566651,"name":"新光三越A4館","decorType":"cosmetics"},{"id":"way-278136702","lat":25.043776,"lon":121.567467,"name":"革新公園","decorType":"park"},{"id":"way-287217253","lat":25.054141,"lon":121.568916,"name":"健康公園","decorType":"park"},{"id":"way-298063022","lat":25.040537,"lon":121.567896,"name":"忠信廣場","decorType":"park"},{"id":"way-300503368","lat":25.050548,"lon":121.564074,"name":"吉祥公園","decorType":"park"},{"id":"way-304148117","lat":25.050868,"lon":121.570534,"name":"正氣橋","decorType":"bridge"},{"id":"way-310909564","lat":25.039496,"lon":121.567121,"name":"人行空橋","decorType":"bridge"},{"id":"way-312729918","lat":25.040538,"lon":121.565103,"name":"市府轉運站","decorType":"station"},{"id":"way-313584144","lat":25.050767,"lon":121.571871,"name":"松山水福宮","decorType":"shrine"},{"id":"way-313587972","lat":25.050626,"lon":121.573943,"name":"長老教會松山教會","decorType":"shrine"},{"id":"way-324294418","lat":25.048942,"lon":121.569108,"name":"正氣橋","decorType":"bridge"},{"id":"way-328519342","lat":25.039257,"lon":121.567995,"name":"未命名公園","decorType":"park"},{"id":"way-333599216","lat":25.042198,"lon":121.570091,"name":"永吉福德宮","decorType":"shrine"},{"id":"way-333599236","lat":25.041588,"lon":121.570507,"name":"萬善堂","decorType":"shrine"},{"id":"way-333599334","lat":25.044595,"lon":121.568671,"name":"興雅福德宮","decorType":"shrine"},{"id":"way-333599355","lat":25.045692,"lon":121.569056,"name":"未命名橋樑","decorType":"bridge"},{"id":"way-333599361","lat":25.045813,"lon":121.569006,"name":"未命名橋樑","decorType":"bridge"},{"id":"way-333599362","lat":25.045573,"lon":121.569,"name":"未命名橋樑","decorType":"bridge"},{"id":"way-352004595","lat":25.050923,"lon":121.573993,"name":"成美左11","decorType":"bridge"},{"id":"way-352004618","lat":25.050861,"lon":121.573034,"name":"成美左12","decorType":"bridge"},{"id":"way-352004706","lat":25.05143,"lon":121.571226,"name":"成美左13","decorType":"bridge"},{"id":"way-359743631","lat":25.041255,"lon":121.572892,"name":"柯旅天閣飯店","decorType":"hotel"},{"id":"way-362289790","lat":25.049328,"lon":121.571143,"name":"未命名公園","decorType":"park"},{"id":"way-366004483","lat":25.048511,"lon":121.563472,"name":"蒲園飯店","decorType":"hotel"},{"id":"way-377014461","lat":25.053074,"lon":121.564471,"name":"安平公園","decorType":"park"},{"id":"way-379326176","lat":25.039284,"lon":121.567945,"name":"未命名水邊","decorType":"waterside"},{"id":"way-379326177","lat":25.039291,"lon":121.567489,"name":"未命名水邊","decorType":"waterside"},{"id":"way-379326179","lat":25.039286,"lon":121.567717,"name":"未命名水邊","decorType":"waterside"},{"id":"way-384078103","lat":25.052776,"lon":121.571644,"name":"機慢車道","decorType":"bridge"},{"id":"way-384078105","lat":25.051587,"lon":121.57077,"name":"未命名橋樑","decorType":"bridge"},{"id":"way-384078106","lat":25.053912,"lon":121.573966,"name":"未命名橋樑","decorType":"bridge"},{"id":"way-384078107","lat":25.051958,"lon":121.570856,"name":"未命名橋樑","decorType":"bridge"},{"id":"way-384078110","lat":25.052538,"lon":121.571768,"name":"機慢車道","decorType":"bridge"},{"id":"way-384078112","lat":25.051411,"lon":121.571157,"name":"未命名橋樑","decorType":"bridge"},{"id":"way-384078115","lat":25.052357,"lon":121.572941,"name":"未命名橋樑","decorType":"bridge"},{"id":"way-390780641","lat":25.050908,"lon":121.562442,"name":"白鬚公廟","decorType":"shrine"},{"id":"way-392097085","lat":25.049331,"lon":121.57411,"name":"未命名公園","decorType":"park"},{"id":"way-431945129","lat":25.042499,"lon":121.569748,"name":"富生二公園","decorType":"park"},{"id":"way-434508475","lat":25.043835,"lon":121.566042,"name":"松山高中人行陸橋","decorType":"bridge"},{"id":"way-506584775","lat":25.038896,"lon":121.567865,"name":"未命名水邊","decorType":"waterside"},{"id":"way-516129748","lat":25.047601,"lon":121.571852,"name":"雅祥公園","decorType":"park"},{"id":"way-516129756","lat":25.046034,"lon":121.570623,"name":"福祥公園","decorType":"park"},{"id":"way-549464951","lat":25.042604,"lon":121.568636,"name":"華大旅店","decorType":"hotel"},{"id":"way-552513838","lat":25.052805,"lon":121.573503,"name":"麥帥一橋","decorType":"bridge"},{"id":"way-555513382","lat":25.045185,"lon":121.566622,"name":"百家班基隆路店","decorType":"restaurant"},{"id":"way-567293011","lat":25.052337,"lon":121.572501,"name":"麥帥一橋","decorType":"bridge"},{"id":"way-818279847","lat":25.049318,"lon":121.570319,"name":"未命名公園","decorType":"park"},{"id":"way-877532238","lat":25.041141,"lon":121.565628,"name":"未命名公車站","decorType":"bus_stop"},{"id":"way-1054529713","lat":25.051426,"lon":121.563876,"name":"未命名公車站","decorType":"bus_stop"},{"id":"way-1070592917","lat":25.053848,"lon":121.57394,"name":"未命名橋樑","decorType":"bridge"},{"id":"way-1070592918","lat":25.053876,"lon":121.573914,"name":"未命名橋樑","decorType":"bridge"},{"id":"way-1070592919","lat":25.053885,"lon":121.57394,"name":"未命名橋樑","decorType":"bridge"},{"id":"way-1071561135","lat":25.05146,"lon":121.571191,"name":"成美左13","decorType":"bridge"},{"id":"way-1071561136","lat":25.051444,"lon":121.571191,"name":"成美左13","decorType":"bridge"},{"id":"way-1071561140","lat":25.052552,"lon":121.572558,"name":"未命名橋樑","decorType":"bridge"},{"id":"way-1071561141","lat":25.051409,"lon":121.571161,"name":"未命名橋樑","decorType":"bridge"},{"id":"way-1073045431","lat":25.050911,"lon":121.574031,"name":"成美左11","decorType":"bridge"},{"id":"way-1073045434","lat":25.050905,"lon":121.574034,"name":"成美左11","decorType":"bridge"},{"id":"way-1073045435","lat":25.050847,"lon":121.573055,"name":"成美左12","decorType":"bridge"},{"id":"way-1073045436","lat":25.050841,"lon":121.573057,"name":"成美左12","decorType":"bridge"},{"id":"way-1147283527","lat":25.041828,"lon":121.564455,"name":"紅典酒店式公寓","decorType":"hotel"},{"id":"way-1216424933","lat":25.04226,"lon":121.564779,"name":"Just Inn Xin Yi 正旅館 信義","decorType":"hotel"},{"id":"way-1259586258","lat":25.047775,"lon":121.568742,"name":"未命名公園","decorType":"park"},{"id":"way-1262196739","lat":25.052213,"lon":121.567879,"name":"未命名公園","decorType":"park"},{"id":"way-1272677946","lat":25.045479,"lon":121.565366,"name":"市民大道高架道路","decorType":"bridge"},{"id":"way-1272677947","lat":25.051294,"lon":121.570002,"name":"麥帥二橋","decorType":"bridge"},{"id":"way-1272682373","lat":25.045054,"lon":121.564834,"name":"市民大道高架道路","decorType":"bridge"},{"id":"way-1272683351","lat":25.05186,"lon":121.571733,"name":"麥帥一橋","decorType":"bridge"},{"id":"way-1308944450","lat":25.044652,"lon":121.566373,"name":"未命名橋樑","decorType":"bridge"},{"id":"way-1308944469","lat":25.04443,"lon":121.565627,"name":"未命名水邊","decorType":"waterside"},{"id":"way-1335095032","lat":25.038803,"lon":121.563352,"name":"未命名公園","decorType":"park"},{"id":"way-1335095034","lat":25.038952,"lon":121.561812,"name":"未命名公園","decorType":"park"},{"id":"way-1335095035","lat":25.039033,"lon":121.561811,"name":"未命名公園","decorType":"park"},{"id":"way-1335095036","lat":25.038976,"lon":121.562224,"name":"未命名公園","decorType":"park"},{"id":"way-1335095037","lat":25.038962,"lon":121.562402,"name":"未命名公園","decorType":"park"},{"id":"way-1335095038","lat":25.038915,"lon":121.562562,"name":"未命名公園","decorType":"park"},{"id":"way-1335095039","lat":25.038832,"lon":121.562599,"name":"未命名公園","decorType":"park"},{"id":"way-1335095052","lat":25.038923,"lon":121.563201,"name":"未命名水邊","decorType":"waterside"},{"id":"way-1335101082","lat":25.038883,"lon":121.561617,"name":"未命名公園","decorType":"park"},{"id":"way-1339394551","lat":25.039468,"lon":121.56703,"name":"人行空橋","decorType":"bridge"},{"id":"way-1339401631","lat":25.038892,"lon":121.568085,"name":"未命名水邊","decorType":"waterside"},{"id":"way-1339863081","lat":25.039268,"lon":121.567441,"name":"未命名公園","decorType":"park"},{"id":"way-1339865608","lat":25.039294,"lon":121.568289,"name":"未命名公園","decorType":"park"},{"id":"way-1339878255","lat":25.039405,"lon":121.564344,"name":"未命名水邊","decorType":"waterside"},{"id":"way-1339878257","lat":25.039409,"lon":121.56405,"name":"未命名水邊","decorType":"waterside"},{"id":"way-1339888567","lat":25.039335,"lon":121.565076,"name":"未命名水邊","decorType":"waterside"},{"id":"way-1339889441","lat":25.039332,"lon":121.565386,"name":"未命名水邊","decorType":"waterside"},{"id":"way-1342680633","lat":25.044942,"lon":121.566179,"name":"未命名水邊","decorType":"waterside"},{"id":"way-1342935579","lat":25.046719,"lon":121.566965,"name":"未命名水邊","decorType":"waterside"},{"id":"way-1389684652","lat":25.043836,"lon":121.567305,"name":"未命名公園","decorType":"park"},{"id":"way-1389965671","lat":25.043264,"lon":121.567879,"name":"未命名公園","decorType":"park"},{"id":"way-1389965676","lat":25.042463,"lon":121.569753,"name":"未命名公園","decorType":"park"},{"id":"way-1389965677","lat":25.042192,"lon":121.569808,"name":"未命名公園","decorType":"park"},{"id":"way-1390277318","lat":25.047482,"lon":121.571923,"name":"未命名公園","decorType":"park"},{"id":"way-1390296809","lat":25.041832,"lon":121.570661,"name":"未命名公園","decorType":"park"},{"id":"way-1390847383","lat":25.044498,"lon":121.562468,"name":"未命名公園","decorType":"park"},{"id":"way-1430527611","lat":25.039598,"lon":121.573099,"name":"籃球場","decorType":"park"},{"id":"way-1451304633","lat":25.04903,"lon":121.564094,"name":"承攜行旅台北八德館","decorType":"hotel"}]}