{"bbox":{"south":25.10115625,"north":25.1167625,"west":121.60034375,"east":121.61337499999999},"pois":[{"id":"node-1662419003","lat":25.1110332,"lon":121.6052448,"name":"長青派出所","decorType":"bus_stop"},{"id":"node-1662419006","lat":25.112591,"lon":121.6063259,"name":"未命名公車站","decorType":"bus_stop"},{"id":"node-1662419010","lat":25.1140143,"lon":121.6067523,"name":"長青路213巷口","decorType":"bus_stop"},{"id":"node-1662419012","lat":25.1147344,"lon":121.6077017,"name":"老爺山莊","decorType":"bus_stop"},{"id":"node-1662419018","lat":25.1097583,"lon":121.6051658,"name":"國家公園別墅","decorType":"bus_stop"},{"id":"node-2482626145","lat":25.1071042,"lon":121.6065219,"name":"大邱田山","decorType":"mountain"},{"id":"node-2482646687","lat":25.1049731,"lon":121.6109519,"name":"大邱田山東峰","decorType":"mountain"},{"id":"node-2482647109","lat":25.1027069,"lon":121.6005035,"name":"石崁山","decorType":"mountain"},{"id":"node-2482647815","lat":25.1085061,"lon":121.6015369,"name":"白石湖山東峰","decorType":"mountain"},{"id":"node-4716085536","lat":25.1167037,"lon":121.6013333,"name":"孩子公園","decorType":"bus_stop"},{"id":"node-5390505164","lat":25.1146896,"lon":121.6075983,"name":"老爺山莊","decorType":"bus_stop"},{"id":"node-5390505169","lat":25.113252,"lon":121.604588,"name":"翠柏新村","decorType":"bus_stop"},{"id":"node-5407726112","lat":25.1139336,"lon":121.6050491,"name":"翠柏新村","decorType":"bus_stop"},{"id":"node-5407726119","lat":25.109854,"lon":121.6053903,"name":"國家公園別墅","decorType":"bus_stop"},{"id":"node-5407727124","lat":25.1110926,"lon":121.6054938,"name":"長青派出所","decorType":"bus_stop"},{"id":"node-5407727125","lat":25.1161499,"lon":121.6007156,"name":"孩子公園","decorType":"bus_stop"},{"id":"node-5407727140","lat":25.1135006,"lon":121.6033325,"name":"翠柏新村","decorType":"bus_stop"},{"id":"node-5407727163","lat":25.1131437,"lon":121.6068875,"name":"長青山莊","decorType":"bus_stop"},{"id":"node-5407727165","lat":25.11322,"lon":121.6068036,"name":"長青山莊","decorType":"bus_stop"},{"id":"node-8432400490","lat":25.101745,"lon":121.606758,"name":"大邱田","decorType":"bus_stop"},{"id":"node-8432400491","lat":25.101705,"lon":121.606821,"name":"大邱田","decorType":"bus_stop"},{"id":"node-10855689728","lat":25.1024993,"lon":121.6121528,"name":"未命名山丘","decorType":"mountain"},{"id":"node-12171124416","lat":25.1082477,"lon":121.6026959,"name":"白石湖山東","decorType":"mountain"},{"id":"way-305947733","lat":25.1152854,"lon":121.6123012,"name":"未命名森林","decorType":"forest"},{"id":"way-422591546","lat":25.1115859,"lon":121.602583,"name":"未命名水邊","decorType":"waterside"},{"id":"way-422591547","lat":25.112088,"lon":121.6038824,"name":"未命名水邊","decorType":"waterside"},{"id":"way-430668172","lat":25.1025474,"lon":121.6088436,"name":"內溝溪","decorType":"waterside"},{"id":"way-513086601","lat":25.1068181,"lon":121.6090692,"name":"老祖殿","decorType":"shrine"},{"id":"way-513086602","lat":25.1067039,"lon":121.6092706,"name":"興善宮","decorType":"shrine"},{"id":"way-562231366","lat":25.1015838,"lon":121.6068047,"name":"大邱田土地公廟","decorType":"shrine"},{"id":"way-683313209","lat":25.1031683,"lon":121.6062201,"name":"五路財神廟","decorType":"shrine"},{"id":"way-775668264","lat":25.1153118,"lon":121.6120151,"name":"未命名水邊","decorType":"waterside"},{"id":"way-775668265","lat":25.1140732,"lon":121.6126791,"name":"未命名水邊","decorType":"waterside"},{"id":"way-1167323675","lat":25.1036861,"lon":121.6098031,"name":"未命名水邊","decorType":"waterside"},{"id":"way-1320349482","lat":25.1104921,"lon":121.6079302,"name":"未命名水邊","decorType":"waterside"},{"id":"way-1320349483","lat":25.109139,"lon":121.6087852,"name":"未命名水邊","decorType":"waterside"},{"id":"way-1443855363","lat":25.1080592,"lon":121.6114725,"name":"未命名水邊","decorType":"waterside"},{"id":"way-1443855376","lat":25.1024765,"lon":121.6112662,"name":"未命名水邊","decorType":"waterside"},{"id":"way-1443855378","lat":25.1019755,"lon":121.6091648,"name":"內溝溪","decorType":"waterside"},{"id":"way-1443855379","lat":25.1038927,"lon":121.6072633,"name":"內溝溪","decorType":"waterside"},{"id":"way-1443855380","lat":25.1035696,"lon":121.6077021,"name":"內溝溪","decorType":"waterside"},{"id":"way-1443855381","lat":25.1041906,"lon":121.6068159,"name":"內溝溪","decorType":"waterside"},{"id":"way-1443855382","lat":25.1042077,"lon":121.6067287,"name":"內溝溪","decorType":"waterside"},{"id":"way-1443855383","lat":25.1033059,"lon":121.6081152,"name":"內溝溪","decorType":"waterside"},{"id":"way-1443855384","lat":25.1030404,"lon":121.6085339,"name":"內溝溪","decorType":"waterside"},{"id":"way-1443855385","lat":25.1020478,"lon":121.6091263,"name":"內溝溪","decorType":"waterside"},{"id":"way-1443855386","lat":25.1016174,"lon":121.6094853,"name":"內溝溪","decorType":"waterside"},{"id":"way-1443855387","lat":25.1012384,"lon":121.6098273,"name":"內溝溪","decorType":"waterside"},{"id":"way-1450364895","lat":25.1114659,"lon":121.6046291,"name":"未命名水邊","decorType":"waterside"},{"id":"way-1450364896","lat":25.110965,"lon":121.6053138,"name":"未命名水邊","decorType":"waterside"}]}